Workbook
Name ACEROLA: OFFSET(#REF!,0,0,COUNTA(#REF!),1)
Name CUSTOSCOMPRA: #REF!

Sheet CATEGORIAS
B2: Situação | C2: Categoria | D2: Conta Pai
B3: Grupo | C3: 1.1 Receitas Diretas | D3: =IF(Tabela2[[#This Row],[Situação]]<>"Grupo",D2,Tabela2[[#This Row],[Categoria]]) -> 1.1 Receitas Diretas
B4: Inativo | C4: Clientes - Venda de Mercadoria Fabricadas | D4: =IF(Tabela2[[#This Row],[Situação]]<>"Grupo",D3,Tabela2[[#This Row],[Categoria]]) -> 1.1 Receitas Diretas
B5: Ativo | C5: Receitas | D5: =IF(Tabela2[[#This Row],[Situação]]<>"Grupo",D4,Tabela2[[#This Row],[Categoria]]) -> 1.1 Receitas Diretas
B6: Inativo | C6: Clientes - Revenda de Mercadoria | D6: =IF(Tabela2[[#This Row],[Situação]]<>"Grupo",D5,Tabela2[[#This Row],[Categoria]]) -> 1.1 Receitas Diretas
B7: Inativo | C7: <Disponível> | D7: =IF(Tabela2[[#This Row],[Situação]]<>"Grupo",D6,Tabela2[[#This Row],[Categoria]]) -> 1.1 Receitas Diretas
B8: Grupo | C8: 1.2 Receitas Indiretas | D8: =IF(Tabela2[[#This Row],[Situação]]<>"Grupo",D7,Tabela2[[#This Row],[Categoria]]) -> 1.2 Receitas Indiretas
B9: Ativo | C9: Dividendos Recebidos | D9: =IF(Tabela2[[#This Row],[Situação]]<>"Grupo",D8,Tabela2[[#This Row],[Categoria]]) -> 1.2 Receitas Indiretas
B10: Ativo | C10: Rendimentos de Aplicações | D10: =IF(Tabela2[[#This Row],[Situação]]<>"Grupo",D9,Tabela2[[#This Row],[Categoria]]) -> 1.2 Receitas Indiretas
B11: Inativo | C11: <Disponível> | D11: =IF(Tabela2[[#This Row],[Situação]]<>"Grupo",D10,Tabela2[[#This Row],[Categoria]]) -> 1.2 Receitas Indiretas
B12: Grupo | C12: 1.3 Devoluções | D12: =IF(Tabela2[[#This Row],[Situação]]<>"Grupo",D11,Tabela2[[#This Row],[Categoria]]) -> 1.3 Devoluções
B13: Ativo | C13: Devoluções de Compra de Mercadoria de Revenda | D13: =IF(Tabela2[[#This Row],[Situação]]<>"Grupo",D12,Tabela2[[#This Row],[Categoria]]) -> 1.3 Devoluções
B14: Ativo | C14: Devoluções de Compra de Material de Consumo | D14: =IF(Tabela2[[#This Row],[Situação]]<>"Grupo",D13,Tabela2[[#This Row],[Categoria]]) -> 1.3 Devoluções
... B128: Ativo | C128: Distribuição de Lucros | D128: =IF(Tabela2[[#This Row],[Situação]]<>"Grupo",D127,Tabela2[[#This Row],[Categoria]]) -> 2.8 Outras Despesas
B129: Inativo | C129: <Disponível> | D129: =IF(Tabela2[[#This Row],[Situação]]<>"Grupo",D126,Tabela2[[#This Row],[Categoria]]) -> 2.8 Outras Despesas
B130: Grupo | C130: 2.9 Devoluções de Vendas | D130: =IF(Tabela2[[#This Row],[Situação]]<>"Grupo",D129,Tabela2[[#This Row],[Categoria]]) -> 2.9 Devoluções de Vendas
B131: Ativo | C131: Devoluções de Vendas de Mercadoria | D131: =IF(Tabela2[[#This Row],[Situação]]<>"Grupo",D130,Tabela2[[#This Row],[Categoria]]) -> 2.9 Devoluções de Vendas
B132: Ativo | C132: Devoluções de Vendas de Serviços Prestados | D132: =IF(Tabela2[[#This Row],[Situação]]<>"Grupo",D131,Tabela2[[#This Row],[Categoria]]) -> 2.9 Devoluções de Vendas
B133: Inativo | C133: <Disponível> | D133: =IF(Tabela2[[#This Row],[Situação]]<>"Grupo",D132,Tabela2[[#This Row],[Categoria]]) -> 2.9 Devoluções de Vendas
B134: Grupo | C134: <Incluir novo grupo de Despesa> | D134: =IF(Tabela2[[#This Row],[Situação]]<>"Grupo",D133,Tabela2[[#This Row],[Categoria]]) -> <Incluir novo grupo de Despesa>
B135: Grupo | C135: 99 Transferências | D135: =IF(Tabela2[[#This Row],[Situação]]<>"Grupo",D134,Tabela2[[#This Row],[Categoria]]) -> 99 Transferências
B136: Ativo | C136: Pagamento Devolvido | D136: =IF(Tabela2[[#This Row],[Situação]]<>"Grupo",D135,Tabela2[[#This Row],[Categoria]]) -> 99 Transferências
B137: Ativo | C137: Entrada de Transferência | D137: =IF(Tabela2[[#This Row],[Situação]]<>"Grupo",D136,Tabela2[[#This Row],[Categoria]]) -> 99 Transferências
B138: Ativo | C138: Saída de Transferência | D138: =IF(Tabela2[[#This Row],[Situação]]<>"Grupo",D137,Tabela2[[#This Row],[Categoria]]) -> 99 Transferências

Sheet BD PREVISTO
L1: =-145080/512 -> -283.35938
B3: Data de Crédito ou Pagto (completa) | C3: Data de Pagto ou Recbto (completa) | D3: Data de Emissão (completa) | E3: Data de Registro (completa) | F3: Data de Previsão (completa) | G3: Cliente ou Fornecedor (Nome Fantasia) | H3: Tipo | I3: Categoria | J3: Valor da Conta | K3: Pago ou Recebido | L3: A Pagar ou Receber | M3: Conta Corrente | N3: Departamento | O3: Observação da Conta | P3: Origem | Q3: NF/CF | R3: Número do Documento | S3: Tipo do Documento | T3: Conta Pai
D4: 46097 | E4: 46097 | F4: 46099 | G4: REALIZE GESTAO | H4: 1. Contas a Receber | I4: Pagamento Devolvido | J4: 144000 | K4: 4166.99 | L4: 139833.01 | M4: Caixa Econômica Federal | N4: 1. Adminstrativo | O4: devolução valor transferido para outra conta | P4: Conta a Receber | Q4: N/D | R4: N/D | S4: Outros | T4: =_xlfn.XLOOKUP(Tabela14[[#This Row],[Categoria]],CATEGORIAS!$C:$C,CATEGORIAS!$D:$D,"") -> 99 Transferências
D5: 46094 | E5: 46094 | F5: 46099 | G5: ANDRE LUCIANO DE OLIVEIRA SALGADO | H5: 1. Contas a Receber | I5: Empréstimos Bancários | J5: 4100 | K5: 0 | L5: 4100 | M5: BRB - Banco de Brasília | N5: 1. Adminstrativo | O5: Empréstimo dessa operação para outra operação do André. colocar devolução para dia 17 de março | P5: Conta a Receber | Q5: N/D | R5: N/D | S5: Outros | T5: =_xlfn.XLOOKUP(Tabela14[[#This Row],[Categoria]],CATEGORIAS!$C:$C,CATEGORIAS!$D:$D,"") -> 1.4 Outras Entradas
D6: 46097 | E6: 46097 | F6: 46099 | G6: REALIZE GESTAO | H6: 1. Contas a Receber | I6: Pagamento Devolvido | J6: 2595.6 | K6: 0 | L6: 2595.6 | M6: Caixa Econômica Federal | N6: 1. Adminstrativo | O6: DESPESA DE OUTRO PROJETO QUE TEM QUE VOLTAR | P6: Conta a Receber | Q6: N/D | R6: N/D | S6: Outros | T6: =_xlfn.XLOOKUP(Tabela14[[#This Row],[Categoria]],CATEGORIAS!$C:$C,CATEGORIAS!$D:$D,"") -> 99 Transferências
D7: 46136 | E7: 46136 | F7: 46120 | G7: OITO APOIO ADMINISTRATIVO E LOGISTICO | H7: 2. Contas a Pagar | I7: Pagamento de Empréstimos | J7: -14716.35 | K7: 0 | L7: -14716.35 | M7: Caixinha | N7: 1. Adminstrativo | O7: EMPRESTIMO BRADESCO - R$ 182.000,00 | P7: Conta a Pagar | Q7: N/D | R7: N/D | S7: Outros | T7: =_xlfn.XLOOKUP(Tabela14[[#This Row],[Categoria]],CATEGORIAS!$C:$C,CATEGORIAS!$D:$D,"") -> 2.5 Despesas Financeiras / Bancos
D8: 46136 | E8: 46136 | F8: 46113 | G8: FM SOLUÇOES | H8: 2. Contas a Pagar | I8: Pagamento de Empréstimos | J8: -9000 | K8: 0 | L8: -9000 | M8: Caixinha | N8: 1. Adminstrativo | O8: CONTA GARANTIDA SAFRA R$ 120.000,00 | P8: Conta a Pagar | Q8: N/D | R8: N/D | S8: Outros | T8: =_xlfn.XLOOKUP(Tabela14[[#This Row],[Categoria]],CATEGORIAS!$C:$C,CATEGORIAS!$D:$D,"") -> 2.5 Despesas Financeiras / Bancos
D9: 46094 | E9: 46094 | F9: 46129 | G9: MARCELO DE ANGELO | H9: 2. Contas a Pagar | I9: Pagamento de Empréstimos | J9: -30000 | K9: 0 | L9: -30000 | M9: Cartão Marcelo - Comp 11 Venc 17 | N9: 1. Adminstrativo | O9: Pagamento de parcela de crédito passado no cartão | P9: Conta a Pagar | Q9: N/D | R9: N/D | S9: Outros | T9: =_xlfn.XLOOKUP(Tabela14[[#This Row],[Categoria]],CATEGORIAS!$C:$C,CATEGORIAS!$D:$D,"") -> 2.5 Despesas Financeiras / Bancos
D10: 46166 | E10: 46166 | F10: 46150 | G10: OITO APOIO ADMINISTRATIVO E LOGISTICO | H10: 2. Contas a Pagar | I10: Pagamento de Empréstimos | J10: -14716.35 | K10: 0 | L10: -14716.35 | M10: Caixinha | N10: 1. Adminstrativo | O10: EMPRESTIMO BRADESCO - R$ 182.000,00 | P10: Contas a Pagar (repetição) | Q10: N/D | R10: N/D | S10: Outros | T10: =_xlfn.XLOOKUP(Tabela14[[#This Row],[Categoria]],CATEGORIAS!$C:$C,CATEGORIAS!$D:$D,"") -> 2.5 Despesas Financeiras / Bancos
D11: 46094 | E11: 46094 | F11: 46159 | G11: MARCELO DE ANGELO | H11: 2. Contas a Pagar | I11: Pagamento de Empréstimos | J11: -30000 | K11: 0 | L11: -30000 | M11: Cartão Marcelo - Comp 11 Venc 17 | N11: 1. Adminstrativo | O11: Pagamento de parcela de crédito passado no cartão | P11: Contas a Pagar (repetição) | Q11: N/D | R11: N/D | S11: Outros | T11: =_xlfn.XLOOKUP(Tabela14[[#This Row],[Categoria]],CATEGORIAS!$C:$C,CATEGORIAS!$D:$D,"") -> 2.5 Despesas Financeiras / Bancos
D12: 46166 | E12: 46166 | F12: 46143 | G12: FM SOLUÇOES | H12: 2. Contas a Pagar | I12: Pagamento de Empréstimos | J12: -9600 | K12: 0 | L12: -9600 | M12: Caixinha | N12: 1. Adminstrativo | O12: CONTA GARANTIDA SAFRA R$ 120.000,00 | P12: Contas a Pagar (repetição) | Q12: N/D | R12: N/D | S12: Outros | T12: =_xlfn.XLOOKUP(Tabela14[[#This Row],[Categoria]],CATEGORIAS!$C:$C,CATEGORIAS!$D:$D,"") -> 2.5 Despesas Financeiras / Bancos
D13: 46197 | E13: 46197 | F13: 46181 | G13: OITO APOIO ADMINISTRATIVO E LOGISTICO | H13: 2. Contas a Pagar | I13: Pagamento de Empréstimos | J13: -14716.35 | K13: 0 | L13: -14716.35 | M13: Caixinha | N13: 1. Adminstrativo | O13: EMPRESTIMO BRADESCO - R$ 182.000,00 | P13: Contas a Pagar (repetição) | Q13: N/D | R13: N/D | S13: Outros | T13: =_xlfn.XLOOKUP(Tabela14[[#This Row],[Categoria]],CATEGORIAS!$C:$C,CATEGORIAS!$D:$D,"") -> 2.5 Despesas Financeiras / Bancos
D14: 46097 | E14: 46097 | F14: 46169 | G14: MARCELO DE ANGELO | H14: 2. Contas a Pagar | I14: Pagamento de Empréstimos | J14: -19006.15 | K14: 0 | L14: -19006.15 | M14: Cartão Marcelo - Comp 11 Venc 17 | N14: 1. Adminstrativo | O14: Pagamento do empréstimo de 248k feito pelo Marcelo [11:44, 16/03/2026] Felipe Fleury: Vamos fazer assim, coloca 4 e na quinta quitação dos 248k [11:45, 16/03/2026] Felipe Fleury: Os 248k cheio no quinto mês | P14: Conta a Pagar | Q14: N/D | R14: N/D | S14: Outros | T14: =_xlfn.XLOOKUP(Tabela14[[#This Row],[Categoria]],CATEGORIAS!$C:$C,CATEGORIAS!$D:$D,"") -> 2.5 Despesas Financeiras / Bancos
D15: 46197 | E15: 46197 | F15: 46174 | G15: FM SOLUÇOES | H15: 2. Contas a Pagar | I15: Pagamento de Empréstimos | J15: -9600 | K15: 0 | L15: -9600 | M15: Caixinha | N15: 1. Adminstrativo | O15: CONTA GARANTIDA SAFRA R$ 120.000,00 | P15: Contas a Pagar (repetição) | Q15: N/D | R15: N/D | S15: Outros | T15: =_xlfn.XLOOKUP(Tabela14[[#This Row],[Categoria]],CATEGORIAS!$C:$C,CATEGORIAS!$D:$D,"") -> 2.5 Despesas Financeiras / Bancos
... D111: 46192 | E111: 46192 | F111: 46196 | G111: PREVISAO | H111: 2. Contas a Pagar | I111: MAO DE OBRA | J111: -14579.1 | K111: 0 | L111: 0 | M111: Caixinha | N111: 3.14 MASSA NIVELADORA | O111: Mao de obra terceirizada Emassamento e lixamento interno paredes e teto | P111: Conta a Pagar | Q111: N/D | R111: N/D | S111: Outros | T111: =_xlfn.XLOOKUP(Tabela14[[#This Row],[Categoria]],CATEGORIAS!$C:$C,CATEGORIAS!$D:$D,"") -> 2.1 Despesas Diretas
F112: 46140 | G112: PREVISAO | H112: 2. Contas a Pagar | I112: Tubos e conexoes | J112: -1516.8 | L112: -1516.8 | M112: Caixinha | N112: 3.15 ESPERAS DE ESGOTO RADIER | O112: Tubo PVC DN 40mm branco rígido para esgoto sanitário | P112: Conta a Pagar | Q112: N/D | R112: N/D | S112: Outros | T112: =_xlfn.XLOOKUP(Tabela14[[#This Row],[Categoria]],CATEGORIAS!$C:$C,CATEGORIAS!$D:$D,"") -> 2.1 Despesas Diretas
F113: 46140 | G113: PREVISAO | H113: 2. Contas a Pagar | I113: Tubos e conexoes | J113: -507.73333 | L113: -507.73333 | M113: Caixinha | N113: 3.15 ESPERAS DE ESGOTO RADIER | O113: Tubo PVC DN 50mm branco rígido para esgoto sanitário | P113: Conta a Pagar | Q113: N/D | R113: N/D | S113: Outros | T113: =_xlfn.XLOOKUP(Tabela14[[#This Row],[Categoria]],CATEGORIAS!$C:$C,CATEGORIAS!$D:$D,"") -> 2.1 Despesas Diretas
F114: 46140 | G114: PREVISAO | H114: 2. Contas a Pagar | I114: Tubos e conexoes | J114: -373.33333 | L114: -373.33333 | M114: Caixinha | N114: 3.15 ESPERAS DE ESGOTO RADIER | O114: Tubo PVC DN 75mm branco rígido para esgoto sanitário | P114: Conta a Pagar | Q114: N/D | R114: N/D | S114: Outros | T114: =_xlfn.XLOOKUP(Tabela14[[#This Row],[Categoria]],CATEGORIAS!$C:$C,CATEGORIAS!$D:$D,"") -> 2.1 Despesas Diretas
F115: 46140 | G115: PREVISAO | H115: 2. Contas a Pagar | I115: Tubos e conexoes | J115: -1578.6667 | L115: -1578.6667 | M115: Caixinha | N115: 3.15 ESPERAS DE ESGOTO RADIER | O115: Tubo PVC DN 100mm branco rígido para esgoto sanitário | P115: Conta a Pagar | Q115: N/D | R115: N/D | S115: Outros | T115: =_xlfn.XLOOKUP(Tabela14[[#This Row],[Categoria]],CATEGORIAS!$C:$C,CATEGORIAS!$D:$D,"") -> 2.1 Despesas Diretas
F116: 46140 | G116: PREVISAO | H116: 2. Contas a Pagar | I116: Tubos e conexoes | J116: -1277.44 | L116: -1277.44 | M116: Caixinha | N116: 3.15 ESPERAS DE ESGOTO RADIER | O116: Tubo PVC DN 150mm branco rígido para esgoto sanitário | P116: Conta a Pagar | Q116: N/D | R116: N/D | S116: Outros | T116: =_xlfn.XLOOKUP(Tabela14[[#This Row],[Categoria]],CATEGORIAS!$C:$C,CATEGORIAS!$D:$D,"") -> 2.1 Despesas Diretas
F117: 46140 | G117: PREVISAO | H117: 2. Contas a Pagar | I117: Tubos e conexoes | J117: -181.33333 | L117: -181.33333 | M117: Caixinha | N117: 3.15 ESPERAS DE ESGOTO RADIER | O117: Joelho 90º PVC DN 100mm branco rígido para esgoto sanitário predial | P117: Conta a Pagar | Q117: N/D | R117: N/D | S117: Outros | T117: =_xlfn.XLOOKUP(Tabela14[[#This Row],[Categoria]],CATEGORIAS!$C:$C,CATEGORIAS!$D:$D,"") -> 2.1 Despesas Diretas
F118: 46140 | G118: PREVISAO | H118: 2. Contas a Pagar | I118: Tubos e conexoes | J118: -181.33333 | L118: -181.33333 | M118: Caixinha | N118: 3.15 ESPERAS DE ESGOTO RADIER | O118: Joelho 45º PVC DN 100mm branco rígido para esgoto sanitário predial | P118: Conta a Pagar | Q118: N/D | R118: N/D | S118: Outros | T118: =_xlfn.XLOOKUP(Tabela14[[#This Row],[Categoria]],CATEGORIAS!$C:$C,CATEGORIAS!$D:$D,"") -> 2.1 Despesas Diretas
F119: 46140 | G119: PREVISAO | H119: 2. Contas a Pagar | I119: Tubos e conexoes | J119: -221.86667 | L119: -221.86667 | M119: Caixinha | N119: 3.15 ESPERAS DE ESGOTO RADIER | O119: Joelho 90º PVC DN 40mm branco rígido para esgoto sanitário predial | P119: Conta a Pagar | Q119: N/D | R119: N/D | S119: Outros | T119: =_xlfn.XLOOKUP(Tabela14[[#This Row],[Categoria]],CATEGORIAS!$C:$C,CATEGORIAS!$D:$D,"") -> 2.1 Despesas Diretas
F120: 46140 | G120: PREVISAO | H120: 2. Contas a Pagar | I120: Tubos e conexoes | J120: -61.866667 | L120: -61.866667 | M120: Caixinha | N120: 3.15 ESPERAS DE ESGOTO RADIER | O120: Joelho 45º PVC DN 40mm branco rígido para esgoto sanitário predial | P120: Conta a Pagar | Q120: N/D | R120: N/D | S120: Outros | T120: =_xlfn.XLOOKUP(Tabela14[[#This Row],[Categoria]],CATEGORIAS!$C:$C,CATEGORIAS!$D:$D,"") -> 2.1 Despesas Diretas
F121: 46140 | G121: PREVISAO | H121: 2. Contas a Pagar | I121: Tubos e conexoes | J121: -201.6 | L121: -201.6 | M121: Caixinha | N121: 3.15 ESPERAS DE ESGOTO RADIER | O121: Joelho 90º PVC DN 50mm branco junta elástica para esgoto sanitário | P121: Conta a Pagar | Q121: N/D | R121: N/D | S121: Outros | T121: =_xlfn.XLOOKUP(Tabela14[[#This Row],[Categoria]],CATEGORIAS!$C:$C,CATEGORIAS!$D:$D,"") -> 2.1 Despesas Diretas
F122: 46140 | G122: PREVISAO | H122: 2. Contas a Pagar | I122: Tubos e conexoes | J122: -76.8 | L122: -76.8 | M122: Caixinha | N122: 3.15 ESPERAS DE ESGOTO RADIER | O122: Joelho 45º PVC DN 50mm branco rígido para esgoto sanitário predial | P122: Conta a Pagar | Q122: N/D | R122: N/D | S122: Outros | T122: =_xlfn.XLOOKUP(Tabela14[[#This Row],[Categoria]],CATEGORIAS!$C:$C,CATEGORIAS!$D:$D,"") -> 2.1 Despesas Diretas
F123: 46140 | G123: PREVISAO | H123: 2. Contas a Pagar | I123: Tubos e conexoes | J123: 0 | L123: 0 | M123: Caixinha | N123: 3.15 ESPERAS DE ESGOTO RADIER | O123: Junção 45º simples PVC DN 50x50mm branco rígido para esgoto sanitário predial | P123: Conta a Pagar | Q123: N/D | R123: N/D | S123: Outros | T123: =_xlfn.XLOOKUP(Tabela14[[#This Row],[Categoria]],CATEGORIAS!$C:$C,CATEGORIAS!$D:$D,"") -> 2.1 Despesas Diretas
... F207: 46168 | G207: PREVISAO | H207: 2. Contas a Pagar | I207: Tubos e conexoes | J207: -265.33333 | L207: -265.33333 | M207: Caixinha | N207: 3.15 ESPERAS DE ESGOTO RADIER | O207: carinho de mão reforçado | P207: Conta a Pagar | Q207: N/D | R207: N/D | S207: Outros | T207: =_xlfn.XLOOKUP(Tabela14[[#This Row],[Categoria]],CATEGORIAS!$C:$C,CATEGORIAS!$D:$D,"") -> 2.1 Despesas Diretas
D208: 46178 | E208: 46178 | F208: 46168 | G208: PREVISAO | H208: 2. Contas a Pagar | I208: TINTAS | J208: -17017.6 | K208: 0 | L208: -17017.6 | M208: Caixinha | N208: 3.16 PINTURA INTERNA | O208: TINTA ACRILICA CORALAR BRANCO 18 LITROS - laje ( cor BRANCA ou similar) - 2 demaos | P208: Conta a Pagar | Q208: N/D | R208: N/D | S208: Outros | T208: =_xlfn.XLOOKUP(Tabela14[[#This Row],[Categoria]],CATEGORIAS!$C:$C,CATEGORIAS!$D:$D,"") -> 2.1 Despesas Diretas
D209: 46178 | E209: 46178 | F209: 46168 | G209: PREVISAO | H209: 2. Contas a Pagar | I209: TINTAS | J209: -1164.8 | K209: 0 | L209: -1164.8 | M209: Caixinha | N209: 3.16 PINTURA INTERNA | O209: Fira crepe 50 mm x 50 m | P209: Conta a Pagar | Q209: N/D | R209: N/D | S209: Outros | T209: =_xlfn.XLOOKUP(Tabela14[[#This Row],[Categoria]],CATEGORIAS!$C:$C,CATEGORIAS!$D:$D,"") -> 2.1 Despesas Diretas
D210: 46136 | E210: 46168 | F210: 46182 | G210: PREVISAO | H210: 2. Contas a Pagar | I210: MAO DE OBRA | J210: -3003.39 | K210: 0 | L210: -4807.99 | M210: Caixinha | N210: 3.17 PINTURA EXT. | O210: Mao de obra terceirizada Textura externa | P210: Conta a Pagar | Q210: N/D | R210: N/D | S210: Outros | T210: =_xlfn.XLOOKUP(Tabela14[[#This Row],[Categoria]],CATEGORIAS!$C:$C,CATEGORIAS!$D:$D,"") -> 2.1 Despesas Diretas
D211: 46150 | E211: 46182 | F211: 46196 | G211: PREVISAO | H211: 2. Contas a Pagar | I211: MAO DE OBRA | J211: -3006.59 | K211: 0 | L211: -4807.99 | M211: Caixinha | N211: 3.17 PINTURA EXT. | O211: Mao de obra terceirizada Textura externa | P211: Conta a Pagar | Q211: N/D | R211: N/D | S211: Outros | T211: =_xlfn.XLOOKUP(Tabela14[[#This Row],[Categoria]],CATEGORIAS!$C:$C,CATEGORIAS!$D:$D,"") -> 2.1 Despesas Diretas
D212: 46206 | E212: 46206 | F212: 46199 | G212: PREVISAO | H212: 2. Contas a Pagar | I212: TINTAS | J212: -17017.6 | K212: 0 | L212: -17017.6 | M212: Caixinha | N212: 3.16 PINTURA INTERNA | O212: TINTA ACRILICA CORALAR BRANCO 18 LITROS - laje ( cor BRANCA ou similar) - 2 demaos | P212: Conta a Pagar | Q212: N/D | R212: N/D | S212: Outros | T212: =_xlfn.XLOOKUP(Tabela14[[#This Row],[Categoria]],CATEGORIAS!$C:$C,CATEGORIAS!$D:$D,"") -> 2.1 Despesas Diretas
D213: 46206 | E213: 46206 | F213: 46199 | G213: PREVISAO | H213: 2. Contas a Pagar | I213: TINTAS | J213: -1164.8 | K213: 0 | L213: -1164.8 | M213: Caixinha | N213: 3.16 PINTURA INTERNA | O213: Fira crepe 50 mm x 50 m | P213: Conta a Pagar | Q213: N/D | R213: N/D | S213: Outros | T213: =_xlfn.XLOOKUP(Tabela14[[#This Row],[Categoria]],CATEGORIAS!$C:$C,CATEGORIAS!$D:$D,"") -> 2.1 Despesas Diretas
D214: 46178 | E214: 46178 | F214: 46182 | G214: PREVISAO | H214: 2. Contas a Pagar | I214: MAO DE OBRA | J214: -5102.72 | K214: 0 | L214: -8160 | M214: Caixinha | N214: 3.16 PINTURA INTERNA | O214: Mao de obra terceirizada com equipamentos Pintura interna (2 demãos) | P214: Conta a Pagar | Q214: N/D | R214: N/D | S214: Outros | T214: =_xlfn.XLOOKUP(Tabela14[[#This Row],[Categoria]],CATEGORIAS!$C:$C,CATEGORIAS!$D:$D,"") -> 2.1 Despesas Diretas
D215: 46192 | E215: 46192 | F215: 46196 | G215: PREVISAO | H215: 2. Contas a Pagar | I215: MAO DE OBRA | J215: -8111.07 | K215: 0 | L215: 0 | M215: Caixinha | N215: 3.17 PINTURA EXT. | O215: Mao de obra terceirizada Textura externa | P215: Conta a Pagar | Q215: N/D | R215: N/D | S215: Outros | T215: =_xlfn.XLOOKUP(Tabela14[[#This Row],[Categoria]],CATEGORIAS!$C:$C,CATEGORIAS!$D:$D,"") -> 2.1 Despesas Diretas
D216: 46164 | E216: 46196 | F216: 46196 | G216: PREVISAO | H216: 2. Contas a Pagar | I216: MAO DE OBRA | J216: -5097.28 | K216: 0 | L216: -8160 | M216: Caixinha | N216: 3.16 PINTURA INTERNA | O216: Mao de obra terceirizada com equipamentos Pintura interna (2 demãos) | P216: Conta a Pagar | Q216: N/D | R216: N/D | S216: Outros | T216: =_xlfn.XLOOKUP(Tabela14[[#This Row],[Categoria]],CATEGORIAS!$C:$C,CATEGORIAS!$D:$D,"") -> 2.1 Despesas Diretas
D217: 46164 | E217: 46164 | F217: 46210 | G217: PREVISAO | H217: 2. Contas a Pagar | I217: MAO DE OBRA | J217: -10800.34 | K217: 0 | L217: -11218.64 | M217: Caixinha | N217: 3.17 PINTURA EXT. | O217: Mao de obra terceirizada Textura externa | P217: Conta a Pagar | Q217: N/D | R217: N/D | S217: Outros | T217: =_xlfn.XLOOKUP(Tabela14[[#This Row],[Categoria]],CATEGORIAS!$C:$C,CATEGORIAS!$D:$D,"") -> 2.1 Despesas Diretas
D218: 46150 | E218: 46150 | F218: 46168 | G218: PREVISAO | H218: 2. Contas a Pagar | I218: TINTAS | J218: -24000 | K218: 0 | L218: -24000 | M218: Caixinha | N218: 3.17 PINTURA EXT. | O218: Textura elastomerica na cor | P218: Conta a Pagar | Q218: N/D | R218: N/D | S218: Outros | T218: =_xlfn.XLOOKUP(Tabela14[[#This Row],[Categoria]],CATEGORIAS!$C:$C,CATEGORIAS!$D:$D,"") -> 2.1 Despesas Diretas
D219: 46178 | E219: 46178 | F219: 46199 | G219: PREVISAO | H219: 2. Contas a Pagar | I219: TINTAS | J219: -24000 | K219: 0 | L219: -24000 | M219: Caixinha | N219: 3.17 PINTURA EXT. | O219: Textura elastomerica na cor | P219: Conta a Pagar | Q219: N/D | R219: N/D | S219: Outros | T219: =_xlfn.XLOOKUP(Tabela14[[#This Row],[Categoria]],CATEGORIAS!$C:$C,CATEGORIAS!$D:$D,"") -> 2.1 Despesas Diretas
... D357: 46160 | E357: 46160 | F357: 46201 | G357: GERDAU | H357: 2. Contas a Pagar | I357: FERRAGEM | J357: -10000 | K357: 0 | L357: -10000 | M357: Caixinha | N357: 3.2 RADIER | O357: Aço - Tela Q-138 - 4.2 c/10 - (245 x 600 cm) (frete de 300 + ipi de 133 incluido | P357: Contas a Pagar (repetição) | Q357: N/D | R357: N/D | S357: Outros | T357: =_xlfn.XLOOKUP(Tabela14[[#This Row],[Categoria]],CATEGORIAS!$C:$C,CATEGORIAS!$D:$D,"") -> 2.1 Despesas Diretas
E358: 46122 | F358: 46140 | G358: JM FERRAGENS | H358: 2. Contas a Pagar | I358: FERRAGEM | J358: -14740.41 | K358: 0 | L358: -13098.667 | M358: Caixinha | N358: 3.2 RADIER | O358: Aço - Tela Q-138 - 4.2 c/10 - (245 x 600 cm) (frete de 300 + ipi de 133 incluido | P358: Conta a Pagar | Q358: N/D | R358: N/D | S358: Outros | T358: =_xlfn.XLOOKUP(Tabela14[[#This Row],[Categoria]],CATEGORIAS!$C:$C,CATEGORIAS!$D:$D,"") -> 2.1 Despesas Diretas
E359: 46152 | F359: 46154 | G359: JM FERRAGENS | H359: 2. Contas a Pagar | I359: FERRAGEM | J359: -13940.41 | K359: 0 | L359: -13098.667 | M359: Caixinha | N359: 3.2 RADIER | O359: Aço - Tela Q-138 - 4.2 c/10 - (245 x 600 cm) (frete de 300 + ipi de 133 incluido | P359: Contas a Pagar (repetição) | Q359: N/D | R359: N/D | S359: Outros | T359: =_xlfn.XLOOKUP(Tabela14[[#This Row],[Categoria]],CATEGORIAS!$C:$C,CATEGORIAS!$D:$D,"") -> 2.1 Despesas Diretas
E360: 46137 | F360: 46168 | G360: JM FERRAGENS | H360: 2. Contas a Pagar | I360: FERRAGEM | J360: -13940.41 | K360: 0 | L360: -13098.667 | M360: Caixinha | N360: 3.2 RADIER | O360: Aço - Tela Q-138 - 4.2 c/10 - (245 x 600 cm) (frete de 300 + ipi de 133 incluido | P360: Contas a Pagar (repetição) | Q360: N/D | R360: N/D | S360: Outros | T360: =_xlfn.XLOOKUP(Tabela14[[#This Row],[Categoria]],CATEGORIAS!$C:$C,CATEGORIAS!$D:$D,"") -> 2.1 Despesas Diretas
D361: 46220 | E361: 46220 | F361: 46220 | G361: PREVISAO | H361: 2. Contas a Pagar | I361: Tubos e conexoes | J361: -76.16 | K361: 0 | L361: -76.16 | M361: Caixinha | N361: 3.22 LOUÇAS E METAIS | O361: Veda Rosca Teflon Veda Tubulações 18mm x 50M | P361: Conta a Pagar | Q361: N/D | R361: N/D | S361: Outros | T361: =_xlfn.XLOOKUP(Tabela14[[#This Row],[Categoria]],CATEGORIAS!$C:$C,CATEGORIAS!$D:$D,"") -> 2.1 Despesas Diretas
D362: 46220 | E362: 46220 | F362: 46220 | G362: PREVISAO | H362: 2. Contas a Pagar | I362: Tubos e conexoes | J362: -252.48 | K362: 0 | L362: -252.48 | M362: Caixinha | N362: 3.22 LOUÇAS E METAIS | O362: ENGATE FLEXÍVEL EM PLÁSTICO BRANCO, 1/2" X 40CM | P362: Conta a Pagar | Q362: N/D | R362: N/D | S362: Outros | T362: =_xlfn.XLOOKUP(Tabela14[[#This Row],[Categoria]],CATEGORIAS!$C:$C,CATEGORIAS!$D:$D,"") -> 2.1 Despesas Diretas
D363: 46220 | E363: 46220 | F363: 46220 | G363: PREVISAO | H363: 2. Contas a Pagar | I363: Tubos e conexoes | J363: -152.96 | K363: 0 | L363: -152.96 | M363: Caixinha | N363: 3.22 LOUÇAS E METAIS | O363: Válvula PVC Para Lavatório S/ladrao Amanco | P363: Conta a Pagar | Q363: N/D | R363: N/D | S363: Outros | T363: =_xlfn.XLOOKUP(Tabela14[[#This Row],[Categoria]],CATEGORIAS!$C:$C,CATEGORIAS!$D:$D,"") -> 2.1 Despesas Diretas
D364: 46220 | E364: 46220 | F364: 46220 | G364: PREVISAO | H364: 2. Contas a Pagar | I364: INSUMO | J364: -382.08 | K364: 0 | L364: -382.08 | M364: Caixinha | N364: 3.22 LOUÇAS E METAIS | O364: Selante Acrílico Elastométrico Top Gun 300 ml TG140 Renner | P364: Conta a Pagar | Q364: N/D | R364: N/D | S364: Outros | T364: =_xlfn.XLOOKUP(Tabela14[[#This Row],[Categoria]],CATEGORIAS!$C:$C,CATEGORIAS!$D:$D,"") -> 2.1 Despesas Diretas
D365: 46220 | E365: 46220 | F365: 46220 | G365: PREVISAO | H365: 2. Contas a Pagar | I365: LOUÇAS | J365: -2332.8 | K365: 0 | L365: -2332.8 | M365: Caixinha | N365: 3.22 LOUÇAS E METAIS | O365: COLUNA P/ LAVATÓRIO BRANCO | P365: Conta a Pagar | Q365: N/D | R365: N/D | S365: Outros | T365: =_xlfn.XLOOKUP(Tabela14[[#This Row],[Categoria]],CATEGORIAS!$C:$C,CATEGORIAS!$D:$D,"") -> 2.1 Despesas Diretas
D366: 46220 | E366: 46220 | F366: 46220 | G366: PREVISAO | H366: 2. Contas a Pagar | I366: Tubos e conexoes | J366: -1056 | K366: 0 | L366: -1056 | M366: Caixinha | N366: 3.22 LOUÇAS E METAIS | O366: PARAFUSO PARA VASO E LAVATORIO / 8MM - COM BUCHA | P366: Conta a Pagar | Q366: N/D | R366: N/D | S366: Outros | T366: =_xlfn.XLOOKUP(Tabela14[[#This Row],[Categoria]],CATEGORIAS!$C:$C,CATEGORIAS!$D:$D,"") -> 2.1 Despesas Diretas
D367: 46220 | E367: 46220 | F367: 46220 | G367: PREVISAO | H367: 2. Contas a Pagar | I367: Tubos e conexoes | J367: -479.68 | K367: 0 | L367: -479.68 | M367: Caixinha | N367: 3.22 LOUÇAS E METAIS | O367: Sifão PVC Extensivo Corrugado Universal Para Lavatório E Tanque 7/8"-11/4" 740MM Branco Censi | P367: Conta a Pagar | Q367: N/D | R367: N/D | S367: Outros | T367: =_xlfn.XLOOKUP(Tabela14[[#This Row],[Categoria]],CATEGORIAS!$C:$C,CATEGORIAS!$D:$D,"") -> 2.1 Despesas Diretas
D368: 46220 | E368: 46220 | F368: 46220 | G368: PREVISAO | H368: 2. Contas a Pagar | I368: LOUÇAS | J368: -2460.8 | K368: 0 | L368: -2460.8 | M368: Caixinha | N368: 3.22 LOUÇAS E METAIS | O368: LAVATORIO LOUCA BRANCA C/ COLUNA 470 X 425 MM (SOMENTELAVATÓRIO) | P368: Conta a Pagar | Q368: N/D | R368: N/D | S368: Outros | T368: =_xlfn.XLOOKUP(Tabela14[[#This Row],[Categoria]],CATEGORIAS!$C:$C,CATEGORIAS!$D:$D,"") -> 2.1 Despesas Diretas
D369: 46220 | E369: 46220 | F369: 46220 | G369: PREVISAO | H369: 2. Contas a Pagar | I369: METAL | J369: -1286.4 | K369: 0 | L369: -1286.4 | M369: Caixinha | N369: 3.22 LOUÇAS E METAIS | O369: Torneira Banheiro Lavatório Bancada 1193 Metal C-23 Cromada | P369: Conta a Pagar | Q369: N/D | R369: N/D | S369: Outros | T369: =_xlfn.XLOOKUP(Tabela14[[#This Row],[Categoria]],CATEGORIAS!$C:$C,CATEGORIAS!$D:$D,"") -> 2.1 Despesas Diretas
D370: 46192 | E370: 46192 | F370: 46192 | G370: PREVISAO | H370: 2. Contas a Pagar | I370: Tubos e conexoes | J370: -152.96 | K370: 0 | L370: -152.96 | M370: Caixinha | N370: 3.22 LOUÇAS E METAIS | O370: Válvula PVC Para Lavatório S/ladrao Amanco | P370: Conta a Pagar | Q370: N/D | R370: N/D | S370: Outros | T370: =_xlfn.XLOOKUP(Tabela14[[#This Row],[Categoria]],CATEGORIAS!$C:$C,CATEGORIAS!$D:$D,"") -> 2.1 Despesas Diretas
D371: 46192 | E371: 46192 | F371: 46192 | G371: PREVISAO | H371: 2. Contas a Pagar | I371: Tubos e conexoes | J371: -1056 | K371: 0 | L371: -1056 | M371: Caixinha | N371: 3.22 LOUÇAS E METAIS | O371: PARAFUSO PARA VASO E LAVATORIO / 8MM - COM BUCHA | P371: Conta a Pagar | Q371: N/D | R371: N/D | S371: Outros | T371: =_xlfn.XLOOKUP(Tabela14[[#This Row],[Categoria]],CATEGORIAS!$C:$C,CATEGORIAS!$D:$D,"") -> 2.1 Despesas Diretas
D372: 46192 | E372: 46192 | F372: 46192 | G372: PREVISAO | H372: 2. Contas a Pagar | I372: Tubos e conexoes | J372: -252.48 | K372: 0 | L372: -252.48 | M372: Caixinha | N372: 3.22 LOUÇAS E METAIS | O372: ENGATE FLEXÍVEL EM PLÁSTICO BRANCO, 1/2" X 40CM | P372: Conta a Pagar | Q372: N/D | R372: N/D | S372: Outros | T372: =_xlfn.XLOOKUP(Tabela14[[#This Row],[Categoria]],CATEGORIAS!$C:$C,CATEGORIAS!$D:$D,"") -> 2.1 Despesas Diretas
... D489: 46150 | E489: 46150 | F489: 46154 | G489: PREVIBRAS / LIDER | H489: 2. Contas a Pagar | I489: FABRICA | J489: -31100.43 | K489: 0 | L489: -31100.43 | M489: Caixinha | N489: 3.3 PAREDES COM CONCRETO | O489: material FERRO: KIT Parede e Laje - FOB na Fabrica | P489: Conta a Pagar | Q489: N/D | R489: N/D | S489: Outros | T489: =_xlfn.XLOOKUP(Tabela14[[#This Row],[Categoria]],CATEGORIAS!$C:$C,CATEGORIAS!$D:$D,"") -> 2.1 Despesas Diretas
D490: 46150 | E490: 46150 | F490: 46118 | G490: AEV GUINDASTES | H490: 2. Contas a Pagar | I490: TRANSPORTE | K490: 0 | L490: -7484.4 | M490: Caixinha | N490: 3.3 PAREDES COM CONCRETO | O490: mobilizaçao e desmobilização equipe montagem | P490: Conta a Pagar | Q490: N/D | R490: N/D | S490: Outros | T490: =_xlfn.XLOOKUP(Tabela14[[#This Row],[Categoria]],CATEGORIAS!$C:$C,CATEGORIAS!$D:$D,"") -> 2.4 Despesas Administrativas
D491: 46150 | E491: 46150 | F491: 46168 | G491: AEV GUINDASTES | H491: 2. Contas a Pagar | I491: MAO DE OBRA | J491: -53000 | K491: 0 | L491: -53000 | M491: Caixinha | N491: 3.3 PAREDES COM CONCRETO | O491: Montagem de paredes pré-moldadas (içamento, prumo, alinhamento e escoramento com grauteamento) | P491: Conta a Pagar | Q491: N/D | R491: N/D | S491: Outros | T491: =_xlfn.XLOOKUP(Tabela14[[#This Row],[Categoria]],CATEGORIAS!$C:$C,CATEGORIAS!$D:$D,"") -> 2.1 Despesas Diretas
F492: 46118 | G492: GABRIEL LOGISTICA | H492: 2. Contas a Pagar | I492: TRANSPORTE | L492: -19050 | M492: Caixinha | N492: 3.3 PAREDES COM CONCRETO | O492: Transporte de paredes e lajes (carreta + munck + carga/descarga) ? até 120 km | P492: Conta a Pagar | Q492: N/D | R492: N/D | S492: Outros | T492: =_xlfn.XLOOKUP(Tabela14[[#This Row],[Categoria]],CATEGORIAS!$C:$C,CATEGORIAS!$D:$D,"") -> 2.4 Despesas Administrativas
D493: 46164 | E493: 46164 | F493: 46168 | G493: PREVIBRAS / LIDER | H493: 2. Contas a Pagar | I493: FABRICA | J493: -38381.9 | K493: 0 | L493: -122822.08 | M493: Caixinha | N493: 3.3 PAREDES COM CONCRETO | O493: material CIMENTO : KIT Parede e Laje - FOB na Fabrica | P493: Conta a Pagar | Q493: N/D | R493: N/D | S493: Outros | T493: =_xlfn.XLOOKUP(Tabela14[[#This Row],[Categoria]],CATEGORIAS!$C:$C,CATEGORIAS!$D:$D,"") -> 2.1 Despesas Diretas
D494: 46164 | E494: 46164 | F494: 46168 | G494: PREVIBRAS / LIDER | H494: 2. Contas a Pagar | I494: FABRICA | J494: -130621.8 | K494: 0 | L494: -130621.8 | M494: Caixinha | N494: 3.3 PAREDES COM CONCRETO | O494: material FERRO: KIT Parede e Laje - FOB na Fabrica | P494: Conta a Pagar | Q494: N/D | R494: N/D | S494: Outros | T494: =_xlfn.XLOOKUP(Tabela14[[#This Row],[Categoria]],CATEGORIAS!$C:$C,CATEGORIAS!$D:$D,"") -> 2.1 Despesas Diretas
D495: 46164 | E495: 46164 | F495: 46153 | G495: AEV GUINDASTES | H495: 2. Contas a Pagar | I495: TRANSPORTE | K495: 0 | L495: -2245.32 | M495: Caixinha | N495: 3.3 PAREDES COM CONCRETO | O495: mobilizaçao e desmobilização equipe montagem | P495: Conta a Pagar | Q495: N/D | R495: N/D | S495: Outros | T495: =_xlfn.XLOOKUP(Tabela14[[#This Row],[Categoria]],CATEGORIAS!$C:$C,CATEGORIAS!$D:$D,"") -> 2.4 Despesas Administrativas
D496: 46164 | E496: 46164 | F496: 46182 | G496: AEV GUINDASTES | H496: 2. Contas a Pagar | I496: MAO DE OBRA | J496: -53000 | K496: 0 | L496: -53000 | M496: Caixinha | N496: 3.3 PAREDES COM CONCRETO | O496: Montagem de paredes pré-moldadas (içamento, prumo, alinhamento e escoramento com grauteamento) | P496: Conta a Pagar | Q496: N/D | R496: N/D | S496: Outros | T496: =_xlfn.XLOOKUP(Tabela14[[#This Row],[Categoria]],CATEGORIAS!$C:$C,CATEGORIAS!$D:$D,"") -> 2.1 Despesas Diretas
F497: 46140 | G497: GABRIEL LOGISTICA | H497: 2. Contas a Pagar | I497: TRANSPORTE | L497: -5750 | M497: Caixinha | N497: 3.3 PAREDES COM CONCRETO | O497: Transporte de paredes e lajes (carreta + munck + carga/descarga) ? até 120 km | P497: Conta a Pagar | Q497: N/D | R497: N/D | S497: Outros | T497: =_xlfn.XLOOKUP(Tabela14[[#This Row],[Categoria]],CATEGORIAS!$C:$C,CATEGORIAS!$D:$D,"") -> 2.4 Despesas Administrativas
F498: 46154 | G498: GABRIEL LOGISTICA | H498: 2. Contas a Pagar | I498: TRANSPORTE | L498: -5750 | M498: Caixinha | N498: 3.3 PAREDES COM CONCRETO | O498: Transporte de paredes e lajes (carreta + munck + carga/descarga) ? até 120 km | P498: Conta a Pagar | Q498: N/D | R498: N/D | S498: Outros | T498: =_xlfn.XLOOKUP(Tabela14[[#This Row],[Categoria]],CATEGORIAS!$C:$C,CATEGORIAS!$D:$D,"") -> 2.4 Despesas Administrativas
F499: 46140 | G499: GABRIEL LOGISTICA | H499: 2. Contas a Pagar | I499: IÇAMENTO | L499: -11535 | M499: Caixinha | N499: 3.3 PAREDES COM CONCRETO | O499: Transporte de paredes e lajes (carreta + munck + carga/descarga) ? até 120 km | P499: Conta a Pagar | Q499: N/D | R499: N/D | S499: Outros | T499: =_xlfn.XLOOKUP(Tabela14[[#This Row],[Categoria]],CATEGORIAS!$C:$C,CATEGORIAS!$D:$D,"")
F500: 46154 | G500: GABRIEL LOGISTICA | H500: 2. Contas a Pagar | I500: IÇAMENTO | L500: -13457.5 | M500: Caixinha | N500: 3.3 PAREDES COM CONCRETO | O500: Transporte de paredes e lajes (carreta + munck + carga/descarga) ? até 120 km | P500: Conta a Pagar | Q500: N/D | R500: N/D | S500: Outros | T500: =_xlfn.XLOOKUP(Tabela14[[#This Row],[Categoria]],CATEGORIAS!$C:$C,CATEGORIAS!$D:$D,"")
F501: 46169 | G501: GABRIEL LOGISTICA | H501: 2. Contas a Pagar | I501: IÇAMENTO | L501: -13457.5 | M501: Caixinha | N501: 3.3 PAREDES COM CONCRETO | O501: Transporte de paredes e lajes (carreta + munck + carga/descarga) ? até 120 km | P501: Conta a Pagar | Q501: N/D | R501: N/D | S501: Outros | T501: =_xlfn.XLOOKUP(Tabela14[[#This Row],[Categoria]],CATEGORIAS!$C:$C,CATEGORIAS!$D:$D,"")
F502: 46140 | G502: GABRIEL LOGISTICA | H502: 2. Contas a Pagar | I502: IÇAMENTO | L502: -11430 | M502: Caixinha | N502: 3.3 PAREDES COM CONCRETO | O502: Transporte de paredes e lajes (carreta + munck + carga/descarga) ? até 120 km | P502: Conta a Pagar | Q502: N/D | R502: N/D | S502: Outros | T502: =_xlfn.XLOOKUP(Tabela14[[#This Row],[Categoria]],CATEGORIAS!$C:$C,CATEGORIAS!$D:$D,"")
D503: 46150 | E503: 46150 | F503: 46154 | G503: GABRIEL LOGISTICA | H503: 2. Contas a Pagar | I503: TRANSPORTE | L503: -13335 | M503: Caixinha | N503: 3.3 PAREDES COM CONCRETO | O503: Transporte de paredes e lajes (carreta + munck + carga/descarga) ? até 120 km | P503: Conta a Pagar | Q503: N/D | R503: N/D | S503: Outros | T503: =_xlfn.XLOOKUP(Tabela14[[#This Row],[Categoria]],CATEGORIAS!$C:$C,CATEGORIAS!$D:$D,"") -> 2.4 Despesas Administrativas
F504: 46168 | G504: GABRIEL LOGISTICA | H504: 2. Contas a Pagar | I504: TRANSPORTE | L504: -13335 | M504: Caixinha | N504: 3.3 PAREDES COM CONCRETO | O504: Transporte de paredes e lajes (carreta + munck + carga/descarga) ? até 120 km | P504: Conta a Pagar | Q504: N/D | R504: N/D | S504: Outros | T504: =_xlfn.XLOOKUP(Tabela14[[#This Row],[Categoria]],CATEGORIAS!$C:$C,CATEGORIAS!$D:$D,"") -> 2.4 Despesas Administrativas
F505: 46140 | G505: GABRIEL LOGISTICA | H505: 2. Contas a Pagar | I505: TRANSPORTE | L505: -10350 | M505: Caixinha | N505: 3.3 PAREDES COM CONCRETO | O505: Transporte de paredes e lajes (carreta + munck + carga/descarga) ? até 120 km | P505: Conta a Pagar | Q505: N/D | R505: N/D | S505: Outros | T505: =_xlfn.XLOOKUP(Tabela14[[#This Row],[Categoria]],CATEGORIAS!$C:$C,CATEGORIAS!$D:$D,"") -> 2.4 Despesas Administrativas
F506: 46154 | G506: GABRIEL LOGISTICA | H506: 2. Contas a Pagar | I506: TRANSPORTE | L506: -12075 | M506: Caixinha | N506: 3.3 PAREDES COM CONCRETO | O506: Transporte de paredes e lajes (carreta + munck + carga/descarga) ? até 120 km | P506: Conta a Pagar | Q506: N/D | R506: N/D | S506: Outros | T506: =_xlfn.XLOOKUP(Tabela14[[#This Row],[Categoria]],CATEGORIAS!$C:$C,CATEGORIAS!$D:$D,"") -> 2.4 Despesas Administrativas
F507: 46182 | G507: GABRIEL LOGISTICA | H507: 2. Contas a Pagar | I507: TRANSPORTE | L507: -12075 | M507: Caixinha | N507: 3.3 PAREDES COM CONCRETO | O507: Transporte de paredes e lajes (carreta + munck + carga/descarga) ? até 120 km | P507: Conta a Pagar | Q507: N/D | R507: N/D | S507: Outros | T507: =_xlfn.XLOOKUP(Tabela14[[#This Row],[Categoria]],CATEGORIAS!$C:$C,CATEGORIAS!$D:$D,"") -> 2.4 Despesas Administrativas
F508: 46154 | G508: GABRIEL LOGISTICA | H508: 2. Contas a Pagar | I508: TRANSPORTE | L508: -9270 | M508: Caixinha | N508: 3.3 PAREDES COM CONCRETO | O508: Transporte de paredes e lajes (carreta + munck + carga/descarga) ? até 120 km | P508: Conta a Pagar | Q508: N/D | R508: N/D | S508: Outros | T508: =_xlfn.XLOOKUP(Tabela14[[#This Row],[Categoria]],CATEGORIAS!$C:$C,CATEGORIAS!$D:$D,"") -> 2.4 Despesas Administrativas
F509: 46168 | G509: GABRIEL LOGISTICA | H509: 2. Contas a Pagar | I509: IÇAMENTO | L509: -10815 | M509: Caixinha | N509: 3.3 PAREDES COM CONCRETO | O509: Transporte de paredes e lajes (carreta + munck + carga/descarga) ? até 120 km | P509: Conta a Pagar | Q509: N/D | R509: N/D | S509: Outros | T509: =_xlfn.XLOOKUP(Tabela14[[#This Row],[Categoria]],CATEGORIAS!$C:$C,CATEGORIAS!$D:$D,"")
F510: 46182 | G510: GABRIEL LOGISTICA | H510: 2. Contas a Pagar | I510: IÇAMENTO | L510: -10815 | M510: Caixinha | N510: 3.3 PAREDES COM CONCRETO | O510: Transporte de paredes e lajes (carreta + munck + carga/descarga) ? até 120 km | P510: Conta a Pagar | Q510: N/D | R510: N/D | S510: Outros | T510: =_xlfn.XLOOKUP(Tabela14[[#This Row],[Categoria]],CATEGORIAS!$C:$C,CATEGORIAS!$D:$D,"")
F511: 46154 | G511: GABRIEL LOGISTICA | H511: 2. Contas a Pagar | I511: IÇAMENTO | L511: -3450 | M511: Caixinha | N511: 3.3 PAREDES COM CONCRETO | O511: Transporte de paredes e lajes (carreta + munck + carga/descarga) ? até 120 km | P511: Conta a Pagar | Q511: N/D | R511: N/D | S511: Outros | T511: =_xlfn.XLOOKUP(Tabela14[[#This Row],[Categoria]],CATEGORIAS!$C:$C,CATEGORIAS!$D:$D,"")
F512: 46168 | G512: GABRIEL LOGISTICA | H512: 2. Contas a Pagar | I512: IÇAMENTO | L512: -4025 | M512: Caixinha | N512: 3.3 PAREDES COM CONCRETO | O512: Transporte de paredes e lajes (carreta + munck + carga/descarga) ? até 120 km | P512: Conta a Pagar | Q512: N/D | R512: N/D | S512: Outros | T512: =_xlfn.XLOOKUP(Tabela14[[#This Row],[Categoria]],CATEGORIAS!$C:$C,CATEGORIAS!$D:$D,"")
F513: 46182 | G513: GABRIEL LOGISTICA | H513: 2. Contas a Pagar | I513: IÇAMENTO | L513: -4025 | M513: Caixinha | N513: 3.3 PAREDES COM CONCRETO | O513: Transporte de paredes e lajes (carreta + munck + carga/descarga) ? até 120 km | P513: Conta a Pagar | Q513: N/D | R513: N/D | S513: Outros | T513: =_xlfn.XLOOKUP(Tabela14[[#This Row],[Categoria]],CATEGORIAS!$C:$C,CATEGORIAS!$D:$D,"")
D514: 46178 | E514: 46178 | F514: 46182 | G514: PREVIBRAS / LIDER | H514: 2. Contas a Pagar | I514: FABRICA | J514: -122822.08 | K514: 0 | L514: -122822.08 | M514: Caixinha | N514: 3.3 PAREDES COM CONCRETO | O514: material CIMENTO : KIT Parede e Laje - FOB na Fabrica | P514: Conta a Pagar | Q514: N/D | R514: N/D | S514: Outros | T514: =_xlfn.XLOOKUP(Tabela14[[#This Row],[Categoria]],CATEGORIAS!$C:$C,CATEGORIAS!$D:$D,"") -> 2.1 Despesas Diretas
D515: 46178 | E515: 46178 | F515: 46182 | G515: PREVIBRAS / LIDER | H515: 2. Contas a Pagar | I515: FABRICA | J515: -21381.54 | K515: 0 | L515: -68420.94 | M515: Caixinha | N515: 3.3 PAREDES COM CONCRETO | O515: material FERRO: KIT Parede e Laje - FOB na Fabrica | P515: Conta a Pagar | Q515: N/D | R515: N/D | S515: Outros | T515: =_xlfn.XLOOKUP(Tabela14[[#This Row],[Categoria]],CATEGORIAS!$C:$C,CATEGORIAS!$D:$D,"") -> 2.1 Despesas Diretas
D516: 46178 | E516: 46178 | F516: 46182 | G516: AEV GUINDASTES | H516: 2. Contas a Pagar | I516: MAO DE OBRA | J516: -53000 | K516: 0 | L516: -53000 | M516: Caixinha | N516: 3.3 PAREDES COM CONCRETO | O516: Montagem de paredes pré-moldadas (içamento, prumo, alinhamento e escoramento com grauteamento) | P516: Conta a Pagar | Q516: N/D | R516: N/D | S516: Outros | T516: =_xlfn.XLOOKUP(Tabela14[[#This Row],[Categoria]],CATEGORIAS!$C:$C,CATEGORIAS!$D:$D,"") -> 2.1 Despesas Diretas
D517: 46192 | E517: 46192 | F517: 46196 | G517: PREVIBRAS / LIDER | H517: 2. Contas a Pagar | I517: FABRICA | J517: -102351.74 | K517: 0 | L517: -102351.74 | M517: Caixinha | N517: 3.3 PAREDES COM CONCRETO | O517: material CIMENTO : KIT Parede e Laje - FOB na Fabrica | P517: Conta a Pagar | Q517: N/D | R517: N/D | S517: Outros | T517: =_xlfn.XLOOKUP(Tabela14[[#This Row],[Categoria]],CATEGORIAS!$C:$C,CATEGORIAS!$D:$D,"") -> 2.1 Despesas Diretas
D518: 46192 | E518: 46192 | F518: 46196 | G518: PREVIBRAS / LIDER | H518: 2. Contas a Pagar | I518: FABRICA | J518: -39653.04 | K518: 0 | L518: -105741.95 | M518: Caixinha | N518: 3.3 PAREDES COM CONCRETO | O518: material FERRO: KIT Parede e Laje - FOB na Fabrica | P518: Conta a Pagar | Q518: N/D | R518: N/D | S518: Outros | T518: =_xlfn.XLOOKUP(Tabela14[[#This Row],[Categoria]],CATEGORIAS!$C:$C,CATEGORIAS!$D:$D,"") -> 2.1 Despesas Diretas
D519: 46192 | E519: 46192 | F519: 46196 | G519: AEV GUINDASTES | H519: 2. Contas a Pagar | I519: MAO DE OBRA | J519: -53000 | K519: 0 | L519: -53000 | M519: Caixinha | N519: 3.3 PAREDES COM CONCRETO | O519: Montagem de paredes pré-moldadas (içamento, prumo, alinhamento e escoramento com grauteamento) | P519: Conta a Pagar | Q519: N/D | R519: N/D | S519: Outros | T519: =_xlfn.XLOOKUP(Tabela14[[#This Row],[Categoria]],CATEGORIAS!$C:$C,CATEGORIAS!$D:$D,"") -> 2.1 Despesas Diretas
D520: 46206 | E520: 46206 | F520: 46210 | G520: PREVIBRAS / LIDER | H520: 2. Contas a Pagar | I520: FABRICA | J520: -10085.89 | K520: 0 | L520: -32275 | M520: Caixinha | N520: 3.3 PAREDES COM CONCRETO | O520: material FERRO: KIT Parede e Laje - FOB na Fabrica | P520: Conta a Pagar | Q520: N/D | R520: N/D | S520: Outros | T520: =_xlfn.XLOOKUP(Tabela14[[#This Row],[Categoria]],CATEGORIAS!$C:$C,CATEGORIAS!$D:$D,"") -> 2.1 Despesas Diretas
D521: 46150 | E521: 46150 | F521: 46159 | G521: REDEMAC | H521: 2. Contas a Pagar | I521: INSUMO | J521: -4864 | K521: 0 | L521: -1057.92 | M521: Caixinha | N521: 3.4 GRAUTEAMENTO | O521: Aditivo supercristalizante Penetron | P521: Conta a Pagar | Q521: N/D | R521: N/D | S521: Outros | T521: =_xlfn.XLOOKUP(Tabela14[[#This Row],[Categoria]],CATEGORIAS!$C:$C,CATEGORIAS!$D:$D,"") -> 2.1 Despesas Diretas
D522: 46150 | E522: 46150 | F522: 46171 | G522: REDEMAC | H522: 2. Contas a Pagar | I522: INSUMO | J522: -4864 | K522: 0 | L522: -863.04 | M522: Caixinha | N522: 3.4 GRAUTEAMENTO | O522: Aditivo supercristalizante Penetron | P522: Conta a Pagar | Q522: N/D | R522: N/D | S522: Outros | T522: =_xlfn.XLOOKUP(Tabela14[[#This Row],[Categoria]],CATEGORIAS!$C:$C,CATEGORIAS!$D:$D,"") -> 2.1 Despesas Diretas
D523: 46150 | E523: 46150 | F523: 46159 | G523: REDEMAC | H523: 2. Contas a Pagar | I523: CONCRETO | J523: -5376 | K523: 0 | L523: -2128 | M523: Caixinha | N523: 3.4 GRAUTEAMENTO | O523: graute: areia grossa | P523: Conta a Pagar | Q523: N/D | R523: N/D | S523: Outros | T523: =_xlfn.XLOOKUP(Tabela14[[#This Row],[Categoria]],CATEGORIAS!$C:$C,CATEGORIAS!$D:$D,"") -> 2.1 Despesas Diretas
D524: 46150 | E524: 46150 | F524: 46171 | G524: REDEMAC | H524: 2. Contas a Pagar | I524: CONCRETO | J524: -5376 | K524: 0 | L524: -1736 | M524: Caixinha | N524: 3.4 GRAUTEAMENTO | O524: graute: areia grossa | P524: Conta a Pagar | Q524: N/D | R524: N/D | S524: Outros | T524: =_xlfn.XLOOKUP(Tabela14[[#This Row],[Categoria]],CATEGORIAS!$C:$C,CATEGORIAS!$D:$D,"") -> 2.1 Despesas Diretas
D525: 46150 | E525: 46150 | F525: 46184 | G525: REDEMAC | H525: 2. Contas a Pagar | I525: CONCRETO | J525: -5376 | K525: 0 | L525: -1736 | M525: Caixinha | N525: 3.4 GRAUTEAMENTO | O525: graute: areia grossa | P525: Conta a Pagar | Q525: N/D | R525: N/D | S525: Outros | T525: =_xlfn.XLOOKUP(Tabela14[[#This Row],[Categoria]],CATEGORIAS!$C:$C,CATEGORIAS!$D:$D,"") -> 2.1 Despesas Diretas
... D668: 46192 | E668: 46192 | F668: 46196 | G668: PREVISAO | H668: 2. Contas a Pagar | I668: MAO DE OBRA | J668: -28503.76 | K668: 0 | L668: -28503.76 | M668: Caixinha | N668: 3.9 AZULEJOS | O668: Mao de obra terceirizada assentamento Azulejo | P668: Conta a Pagar | Q668: N/D | R668: N/D | S668: Outros | T668: =_xlfn.XLOOKUP(Tabela14[[#This Row],[Categoria]],CATEGORIAS!$C:$C,CATEGORIAS!$D:$D,"") -> 2.1 Despesas Diretas
K673: 46140 | L673: 46154 | M673: 46168 | N673: 46182 | O673: 46196 | P673: 46210 | Q673: 46224 | R673: 46238

Sheet MEMORIA DE CÁLCULO
G1: =205000/7 -> 29285.714 | H1: POR SEMANA | I1: 10/04 PRIMEIRO PAGAMENTO
C2: PAREDES - TRANSPORTE | D2: 1 BITREM 3950,00 PARA DUAS CASAS | E2: COMPLEMENTO 4 CASAS | F2: =(3950/2)+(3600/4) -> 2875 | G2: 205K | H2: ENTREGA DIÁRIA - TODO DIA TEM BITREM
D3: BITREM | E3: =3950/2 -> 1975 | F3: =+F2*64 -> 184000
A4: TOTAL FRETE | C4: 184000 | D4: VANDERLEIA | E4: 900
A5: SEMANA | B5: DATA | C5: =C4/7 -> 26285.714 | D5: DATA MEDIÇÃO | E5: =E4+E3 -> 2875 | F5: =E5*64 -> 184000
B8: DATA REAL | D8: DATA AJUSTADA MEDIÇÃO
A9: PAGAMENTO | B9: 45757 | C9: =$C$5*0.3 -> 7885.7143 | D9: 46118 | E9: =WEEKDAY(D9) -> 2 | G9: =-C9 -> -7885.7143
B10: =B9+15 -> 45772 | C10: =$C$5*0.35 -> 9200 | D10: 45774 | E10: =WEEKDAY(D10) -> 1 | G10: =-C10 -> -9200
B11: =B10+15 -> 45787 | C11: =$C$5*0.35 -> 9200 | D11: 46153 | E11: =WEEKDAY(D11) -> 2 | G11: =-C11 -> -9200
B12: =B9+7 -> 45764 | C12: =$C$5*0.3 -> 7885.7143 | D12: 45774 | E12: =WEEKDAY(D12) -> 1 | G12: =-C12 -> -7885.7143
B13: =B12+15 -> 45779 | C13: =$C$5*0.35 -> 9200 | D13: 46153 | E13: =WEEKDAY(D13) -> 2 | G13: =-C13 -> -9200
B14: =B13+15 -> 45794 | C14: =$C$5*0.35 -> 9200 | D14: 46167 | E14: =WEEKDAY(D14) -> 2 | G14: =-C14 -> -9200
B15: =B12+7 -> 45771 | C15: =$C$5*0.3 -> 7885.7143 | D15: 45774 | E15: =WEEKDAY(D15) -> 1 | G15: =-C15 -> -7885.7143
B16: =B15+15 -> 45786 | C16: =$C$5*0.35 -> 9200 | D16: 46153 | E16: =WEEKDAY(D16) -> 2 | G16: =-C16 -> -9200
B17: =B16+15 -> 45801 | C17: =$C$5*0.35 -> 9200 | D17: 46167 | E17: =WEEKDAY(D17) -> 2 | G17: =-C17 -> -9200
B18: =B15+7 -> 45778 | C18: =$C$5*0.3 -> 7885.7143 | D18: 46153 | E18: =WEEKDAY(D18) -> 2 | G18: =-C18 -> -7885.7143
B19: =B18+15 -> 45793 | C19: =$C$5*0.35 -> 9200 | D19: 46167 | E19: =WEEKDAY(D19) -> 2 | G19: =-C19 -> -9200
B20: =B19+15 -> 45808 | C20: =$C$5*0.35 -> 9200 | D20: 46181 | E20: =WEEKDAY(D20) -> 2 | G20: =-C20 -> -9200
B21: =B18+7 -> 45785 | C21: =$C$5*0.3 -> 7885.7143 | D21: 46153 | E21: =WEEKDAY(D21) -> 2 | G21: =-C21 -> -7885.7143
B22: =B21+15 -> 45800 | C22: =$C$5*0.35 -> 9200 | D22: 46167 | E22: =WEEKDAY(D22) -> 2 | G22: =-C22 -> -9200
B23: =B22+15 -> 45815 | C23: =$C$5*0.35 -> 9200 | D23: 46181 | E23: =WEEKDAY(D23) -> 2 | G23: =-C23 -> -9200
B24: =B21+7 -> 45792 | C24: =$C$5*0.3 -> 7885.7143 | D24: 46167 | E24: =WEEKDAY(D24) -> 2 | G24: =-C24 -> -7885.7143
B25: =B24+15 -> 45807 | C25: =$C$5*0.35 -> 9200 | D25: 46181 | E25: =WEEKDAY(D25) -> 2 | G25: =-C25 -> -9200
B26: =B25+15 -> 45822 | C26: =$C$5*0.35 -> 9200 | D26: 46195 | E26: =WEEKDAY(D26) -> 2 | G26: =-C26 -> -9200
B27: =B24+7 -> 45799 | C27: =$C$5*0.3 -> 7885.7143 | D27: 46167 | E27: =WEEKDAY(D27) -> 2 | G27: =-C27 -> -7885.7143
B28: =B27+15 -> 45814 | C28: =$C$5*0.35 -> 9200 | D28: 46181 | E28: =WEEKDAY(D28) -> 2 | G28: =-C28 -> -9200
B29: =B28+15 -> 45829 | C29: =$C$5*0.35 -> 9200 | D29: 46195 | E29: =WEEKDAY(D29) -> 2 | G29: =-C29 -> -9200
C30: =SUM(C9:C29) -> 184000 | G30: =-C30 -> -184000
A32: IÇAMENTO | B32: =B35+B38 -> 210000 | C32: =B32/7 -> 30000
A33: DIARIA GUINDASTE | B33: 3000
A34: DIAS | B34: 47
A35: TOTAL | B35: =B33*B34 -> 141000
A36: DIARIA MUNK | B36: 3000
A37: DIAS | B37: 23
A38: TOTAL | B38: =B36*B37 -> 69000
B39: DATA
B40: 45757 | C40: =$C$32*0.3 -> 9000 | D40: 46118 | E40: =WEEKDAY(D40) -> 2 | G40: =-C40 -> -9000
B41: 45772 | C41: =$C$32*0.35 -> 10500 | D41: 45774 | E41: =WEEKDAY(D41) -> 1 | G41: =-C41 -> -10500
B42: 45787 | C42: =$C$32*0.35 -> 10500 | D42: 46153 | E42: =WEEKDAY(D42) -> 2 | G42: =-C42 -> -10500
B43: 45764 | C43: =$C$32*0.3 -> 9000 | D43: 45774 | E43: =WEEKDAY(D43) -> 1 | G43: =-C43 -> -9000
B44: 45779 | C44: =$C$32*0.35 -> 10500 | D44: 46153 | E44: =WEEKDAY(D44) -> 2 | G44: =-C44 -> -10500
B45: 45794 | C45: =$C$32*0.35 -> 10500 | D45: 46167 | E45: =WEEKDAY(D45) -> 2 | G45: =-C45 -> -10500
B46: 45771 | C46: =$C$32*0.3 -> 9000 | D46: 45774 | E46: =WEEKDAY(D46) -> 1 | G46: =-C46 -> -9000
B47: 45786 | C47: =$C$32*0.35 -> 10500 | D47: 46153 | E47: =WEEKDAY(D47) -> 2 | G47: =-C47 -> -10500
B48: 45801 | C48: =$C$32*0.35 -> 10500 | D48: 46167 | E48: =WEEKDAY(D48) -> 2 | G48: =-C48 -> -10500
B49: 45778 | C49: =$C$32*0.3 -> 9000 | D49: 46153 | E49: =WEEKDAY(D49) -> 2 | G49: =-C49 -> -9000
B50: 45793 | C50: =$C$32*0.35 -> 10500 | D50: 46167 | E50: =WEEKDAY(D50) -> 2 | G50: =-C50 -> -10500
B51: 45808 | C51: =$C$32*0.35 -> 10500 | D51: 46181 | E51: =WEEKDAY(D51) -> 2 | G51: =-C51 -> -10500
B52: 45785 | C52: =$C$32*0.3 -> 9000 | D52: 46153 | E52: =WEEKDAY(D52) -> 2 | G52: =-C52 -> -9000
B53: 45800 | C53: =$C$32*0.35 -> 10500 | D53: 46167 | E53: =WEEKDAY(D53) -> 2 | G53: =-C53 -> -10500
B54: 45815 | C54: =$C$32*0.35 -> 10500 | D54: 46181 | E54: =WEEKDAY(D54) -> 2 | G54: =-C54 -> -10500
B55: 45792 | C55: =$C$32*0.3 -> 9000 | D55: 46167 | E55: =WEEKDAY(D55) -> 2 | G55: =-C55 -> -9000
B56: 45807 | C56: =$C$32*0.35 -> 10500 | D56: 46181 | E56: =WEEKDAY(D56) -> 2 | G56: =-C56 -> -10500
B57: 45822 | C57: =$C$32*0.35 -> 10500 | D57: 46195 | E57: =WEEKDAY(D57) -> 2 | G57: =-C57 -> -10500
B58: 45799 | C58: =$C$32*0.3 -> 9000 | D58: 46167 | E58: =WEEKDAY(D58) -> 2 | G58: =-C58 -> -9000
B59: 45814 | C59: =$C$32*0.35 -> 10500 | D59: 46181 | E59: =WEEKDAY(D59) -> 2 | G59: =-C59 -> -10500
B60: 45829 | C60: =$C$32*0.35 -> 10500 | D60: 46195 | E60: =WEEKDAY(D60) -> 2 | G60: =-C60 -> -10500
C61: =SUM(C40:C60) -> 210000
A64: LINHAS 7 ATÉ 39 | B64: METADE NA DATA BOLETOS JM FERRAGENS | C64: A OUTRA METADE UMA QUINZENA PRA FRENTE A 30/45/60
A65: LINHA 42 CONCRETO
L678: 1196695.3

Sheet BD REALIZADO
B2: Data de Crédito ou Pagto (completa) | C2: Data de Pagto ou Recbto (completa) | D2: Data de Emissão (completa) | E2: Data de Registro (completa) | F2: Data de Previsão (completa) | G2: Cliente ou Fornecedor (Nome Fantasia) | H2: Tipo | I2: Categoria | J2: Valor da Conta | K2: Pago ou Recebido | L2: A Pagar ou Receber | M2: Conta Corrente | N2: Departamento | O2: Observação da Conta | P2: Origem | Q2: NF/CF | R2: Número do Documento | S2: Tipo do Documento | T2: Conta Pai
B3: 46080 | C3: 46080 | D3: 46080 | E3: 46080 | F3: 46080 | G3: MARCELO DE ANGELO | H3: 1. Contas a Receber | I3: Empréstimos Bancários | J3: 200000 | K3: 200000 | L3: 0 | M3: BRB - Banco de Brasília | N3: 1. Adminstrativo | O3: N/D | P3: Recebimento de Conta a Receber | Q3: N/D | R3: N/D | S3: Outros | T3: =_xlfn.XLOOKUP(Tabela1[[#This Row],[Categoria]],CATEGORIAS!$C:$C,CATEGORIAS!$D:$D,"") -> 1.4 Outras Entradas
B4: 46082 | C4: 46082 | D4: 46082 | E4: 46082 | F4: 46082 | G4: REALIZE GESTAO | H4: 1. Contas a Receber | I4: Empréstimos Bancários | J4: 199.83 | K4: 199.83 | L4: 0 | M4: BRB - Banco de Brasília | N4: 1. Adminstrativo | O4: VALOR DE SALDO QUE JUSTIFICA A TRANSF DE 213K PARA A CONTA DA CAIXA | P4: Lançamento de Crédito | Q4: N/D | R4: N/D | S4: Outros | T4: =_xlfn.XLOOKUP(Tabela1[[#This Row],[Categoria]],CATEGORIAS!$C:$C,CATEGORIAS!$D:$D,"") -> 1.4 Outras Entradas
B5: 46083 | C5: 46083 | D5: 46083 | E5: 46083 | F5: 46083 | G5: PNEUS BRASILIA | H5: 2. Contas a Pagar | I5: Despesas de Viagens | J5: -1320 | K5: -1320 | L5: 0 | M5: BRB - Banco de Brasília | N5: 3.1 MOBILIZAÇÃO | O5: Compra de 4 pneus pro carro que está com o engenheiro residente - MOBILIZAÇÃO | P5: Pagamento de Conta a Pagar | Q5: N/D | R5: N/D | S5: Outros | T5: =_xlfn.XLOOKUP(Tabela1[[#This Row],[Categoria]],CATEGORIAS!$C:$C,CATEGORIAS!$D:$D,"") -> 2.2 Despesas de Vendas e Marketing
B6: 46083 | C6: 46083 | D6: 46083 | E6: 46083 | F6: 46083 | G6: GUSTAVO CEZAR DE CARVALHO | H6: 2. Contas a Pagar | I6: Despesas de Viagens | J6: -1000 | K6: -1000 | L6: 0 | M6: BRB - Banco de Brasília | N6: 3.1 MOBILIZAÇÃO | O6: Despesas viagem engenheiro residente - MOBILIZAÇÃO | P6: Pagamento de Conta a Pagar | Q6: N/D | R6: N/D | S6: Outros | T6: =_xlfn.XLOOKUP(Tabela1[[#This Row],[Categoria]],CATEGORIAS!$C:$C,CATEGORIAS!$D:$D,"") -> 2.2 Despesas de Vendas e Marketing
B7: 46083 | C7: 46083 | D7: 46083 | E7: 46083 | F7: 46083 | G7: MARCELO DE ANGELO | H7: 1. Contas a Receber | I7: Empréstimos Bancários | J7: 31000 | K7: 31000 | L7: 0 | M7: BRB - Banco de Brasília | N7: 1. Adminstrativo | O7: N/D | P7: Recebimento de Conta a Receber | Q7: N/D | R7: N/D | S7: Outros | T7: =_xlfn.XLOOKUP(Tabela1[[#This Row],[Categoria]],CATEGORIAS!$C:$C,CATEGORIAS!$D:$D,"") -> 1.4 Outras Entradas
B8: 46083 | C8: 46083 | D8: 46082 | E8: 46082 | F8: 46083 | G8: KONTIK CENTRO | H8: 2. Contas a Pagar | I8: Passagens Aéreas | J8: -7820.8 | K8: -7820.8 | L8: 0 | M8: BRB - Banco de Brasília | N8: 3.1 MOBILIZAÇÃO | O8: Passagem aérea ida e volta de André e felipe - MOBILIZAÇÃO | P8: Pagamento de Conta a Pagar | Q8: N/D | R8: N/D | S8: Outros | T8: =_xlfn.XLOOKUP(Tabela1[[#This Row],[Categoria]],CATEGORIAS!$C:$C,CATEGORIAS!$D:$D,"") -> 2.4 Despesas Administrativas
B9: 46084 | C9: 46084 | D9: 46084 | E9: 46084 | F9: 46084 | G9: RADAR HOSPEDAGEM LTDA | H9: 2. Contas a Pagar | I9: Alimentação | J9: -101.8 | K9: -101.8 | L9: 0 | M9: BRB - Banco de Brasília | N9: 3.1 MOBILIZAÇÃO | O9: Alimentação felipe e André - MOBILIZAÇÃO | P9: Pagamento de Conta a Pagar | Q9: N/D | R9: N/D | S9: Outros | T9: =_xlfn.XLOOKUP(Tabela1[[#This Row],[Categoria]],CATEGORIAS!$C:$C,CATEGORIAS!$D:$D,"") -> 2.4 Despesas Administrativas
B10: 46084 | C10: 46084 | D10: 46108 | E10: 46108 | F10: 46084 | G10: TOKIO MARINE SEGURADORA S.A. | H10: 2. Contas a Pagar | I10: ADMINISTRAÇAO | J10: -15971.55 | K10: -15971.55 | L10: 0 | M10: Caixinha | N10: 3.28 DESPESAS ACESSÓRIAS | O10: Conta a Pagar importada automaticamente em 12/03/2026 às 15:03. SEGURO DO EMPRÉSTIMO ADQUIRIDO PELO MARCELO E PAGO POR ELE ABATENDO DO VALOR CREDITADO NA CONTA DA CONSTRUTORA | P10: Pagamento de Conta a Pagar | Q10: N/D | R10: 12 | S10: Outros | T10: =_xlfn.XLOOKUP(Tabela1[[#This Row],[Categoria]],CATEGORIAS!$C:$C,CATEGORIAS!$D:$D,"") -> 2.4 Despesas Administrativas
B11: 46084 | C11: 46084 | D11: 46097 | E11: 46097 | F11: 46097 | G11: MARCELO DE ANGELO | H11: 1. Contas a Receber | I11: Empréstimos Bancários | J11: 15998.324 | K11: 15971.55 | L11: 26.773665 | M11: Caixinha | N11: 1. Adminstrativo | O11: N/D | P11: Recebimento de Conta a Receber | Q11: N/D | R11: N/D | S11: Outros | T11: =_xlfn.XLOOKUP(Tabela1[[#This Row],[Categoria]],CATEGORIAS!$C:$C,CATEGORIAS!$D:$D,"") -> 1.4 Outras Entradas
B12: 46084 | C12: 46084 | D12: 46085 | E12: 46085 | F12: 46084 | G12: MOVIDA PARTICIPACOES S.A. | H12: 2. Contas a Pagar | I12: TRANSPORTE | J12: -423.09 | K12: -423.09 | L12: 0 | M12: BRB - Banco de Brasília | N12: 3.1 MOBILIZAÇÃO | O12: Aluguel carro felipe e André - MOBILIZAÇÃO | P12: Pagamento de Conta a Pagar | Q12: N/D | R12: N/D | S12: Outros | T12: =_xlfn.XLOOKUP(Tabela1[[#This Row],[Categoria]],CATEGORIAS!$C:$C,CATEGORIAS!$D:$D,"") -> 2.4 Despesas Administrativas
B13: 46084 | C13: 46084 | D13: 46094 | E13: 46094 | F13: 46084 | G13: RADAR HOSPEDAGEM LTDA | H13: 2. Contas a Pagar | I13: Hospedagem | J13: -400 | K13: -400 | L13: 0 | M13: BRB - Banco de Brasília | N13: 3.1 MOBILIZAÇÃO | O13: Hospedagem André e felipe - MOBILIZAÇÃO | P13: Pagamento de Conta a Pagar | Q13: N/D | R13: N/D | S13: Outros | T13: =_xlfn.XLOOKUP(Tabela1[[#This Row],[Categoria]],CATEGORIAS!$C:$C,CATEGORIAS!$D:$D,"") -> 2.4 Despesas Administrativas
B14: 46084 | C14: 46084 | D14: 46084 | E14: 46084 | F14: 46084 | G14: ANDRE LUCIANO DE OLIVEIRA SALGADO | H14: 2. Contas a Pagar | I14: TRANSPORTE | J14: -1000 | K14: -1000 | L14: 0 | M14: BRB - Banco de Brasília | N14: 3.1 MOBILIZAÇÃO | O14: Caução aluguel veículo - MOBILIZAÇÃO | P14: Pagamento de Conta a Pagar | Q14: N/D | R14: N/D | S14: Outros | T14: =_xlfn.XLOOKUP(Tabela1[[#This Row],[Categoria]],CATEGORIAS!$C:$C,CATEGORIAS!$D:$D,"") -> 2.4 Despesas Administrativas
... B77: 46099 | C77: 46099 | D77: 46099 | E77: 46099 | F77: 46099 | G77: RESTAURANTE | H77: 2. Contas a Pagar | I77: MAO DE OBRA | J77: -1602 | K77: -1602 | L77: 0 | M77: Caixa Econômica Federal | N77: 3.2 RADIER | O77: Gerado automaticamente pela importação do extrato. DEB PIX CHAVE Denis Juliano Andrade Souza- - Almoço equipe radiers | P77: Pagamento de Conta a Pagar | Q77: N/D | R77: 181323 | S77: Outros | T77: =_xlfn.XLOOKUP(Tabela1[[#This Row],[Categoria]],CATEGORIAS!$C:$C,CATEGORIAS!$D:$D,"") -> 2.1 Despesas Diretas

Sheet FLUXO REALIZADO
B5: =D5 -> 0 | C5: SALDO INICIAL | D5: 0 | E5: =D8 -> 200000 | F5: =E8 -> 220859.2 | G5: =F8 -> 218934.31 | H5: =G8 -> 214436.92 | I5: =H8 -> 212800.17 | J5: =I8 -> 213000 | K5: =J8 -> 213000 | L5: =K8 -> 165493.59 | ... Q5: =P8 -> 106867.23
B6: =SUM(D6:X6) -> 928534.87 | C6: ENTRADAS | D6: =GETPIVOTDATA("Pago ou Recebido",$C$11,"Data de Crédito ou Pagto (completa)",D12,"Tipo","1. Contas a Receber") -> 200000 | E6: =GETPIVOTDATA("Pago ou Recebido",$C$11,"Data de Crédito ou Pagto (completa)",E12,"Tipo","1. Contas a Receber") -> 31000 | F6: =GETPIVOTDATA("Pago ou Recebido",$C$11,"Data de Crédito ou Pagto (completa)",F12,"Tipo","1. Contas a Receber") -> 15971.55 | G6: =GETPIVOTDATA("Pago ou Recebido",$C$11,"Data de Crédito ou Pagto (completa)",G12,"Tipo","1. Contas a Receber") -> 0 | H6: =GETPIVOTDATA("Pago ou Recebido",$C$11,"Data de Crédito ou Pagto (completa)",H12,"Tipo","1. Contas a Receber") -> 0 | I6: =GETPIVOTDATA("Pago ou Recebido",$C$11,"Data de Crédito ou Pagto (completa)",I12,"Tipo","1. Contas a Receber") -> 199.83 | J6: =GETPIVOTDATA("Pago ou Recebido",$C$11,"Data de Crédito ou Pagto (completa)",J12,"Tipo","1. Contas a Receber") -> 100 | K6: =GETPIVOTDATA("Pago ou Recebido",$C$11,"Data de Crédito ou Pagto (completa)",K12,"Tipo","1. Contas a Receber") -> 317166.99 | ... Q6: =GETPIVOTDATA("Pago ou Recebido",$C$11,"Data de Crédito ou Pagto (completa)",Q12,"Tipo","1. Contas a Receber") -> 0
B7: =SUM(D7:X7) -> -823278.14 | C7: SAÍDAS | D7: =GETPIVOTDATA("Pago ou Recebido",$C$11,"Data de Crédito ou Pagto (completa)",D12,"Tipo","2. Contas a Pagar") -> 0 | E7: =GETPIVOTDATA("Pago ou Recebido",$C$11,"Data de Crédito ou Pagto (completa)",E12,"Tipo","2. Contas a Pagar") -> -10140.8 | F7: =GETPIVOTDATA("Pago ou Recebido",$C$11,"Data de Crédito ou Pagto (completa)",F12,"Tipo","2. Contas a Pagar") -> -17896.44 | G7: =GETPIVOTDATA("Pago ou Recebido",$C$11,"Data de Crédito ou Pagto (completa)",G12,"Tipo","2. Contas a Pagar") -> -4497.39 | H7: =GETPIVOTDATA("Pago ou Recebido",$C$11,"Data de Crédito ou Pagto (completa)",H12,"Tipo","2. Contas a Pagar") -> -1636.75 | I7: =GETPIVOTDATA("Pago ou Recebido",$C$11,"Data de Crédito ou Pagto (completa)",I12,"Tipo","2. Contas a Pagar") -> 0 | J7: =GETPIVOTDATA("Pago ou Recebido",$C$11,"Data de Crédito ou Pagto (completa)",J12,"Tipo","2. Contas a Pagar") -> -100 | K7: =GETPIVOTDATA("Pago ou Recebido",$C$11,"Data de Crédito ou Pagto (completa)",K12,"Tipo","2. Contas a Pagar") -> -364673.4 | ... Q7: =GETPIVOTDATA("Pago ou Recebido",$C$11,"Data de Crédito ou Pagto (completa)",Q12,"Tipo","2. Contas a Pagar") -> -1610.5
B8: =SUM(B5:B7) -> 105256.73 | C8: SALDO FINAL | D8: =SUM(D5:D7) -> 200000 | E8: =SUM(E5:E7) -> 220859.2 | F8: =SUM(F5:F7) -> 218934.31 | G8: =SUM(G5:G7) -> 214436.92 | H8: =SUM(H5:H7) -> 212800.17 | I8: =SUM(I5:I7) -> 213000 | J8: =SUM(J5:J7) -> 213000 | K8: =SUM(K5:K7) -> 165493.59 | ... Q8: =SUM(Q5:Q7) -> 105256.73
C11: Soma de Pago ou Recebido | D11: Rótulos de Coluna
C12: Rótulos de Linha | D12: 46080 | E12: 46083 | F12: 46084 | G12: 46085 | H12: 46087 | I12: 46082 | J12: 46090 | K12: 46091 | L12: 46092 | M12: 46093 | N12: 46094 | O12: 46097 | P12: 46098 | Q12: 46099 | R12: Total Geral
C13: 1. Contas a Receber | D13: 200000 | E13: 31000 | F13: 15971.55 | I13: 199.83 | J13: 100 | K13: 317166.99 | L13: 180000 | O13: 184096.5 | R13: 928534.87
C14: 1.4 Outras Entradas | D14: 200000 | E14: 31000 | F14: 15971.55 | I14: 199.83 | J14: 100 | K14: 100000 | L14: 180000 | O14: 162765 | R14: 690036.38
C15: Empréstimos Bancários | D15: 200000 | E15: 31000 | F15: 15971.55 | I15: 199.83 | J15: 100 | K15: 100000 | L15: 180000 | O15: 162765 | R15: 690036.38
C16: 99 Transferências | K16: 217166.99 | O16: 21331.5 | R16: 238498.49
C17: Entrada de Transferência | K17: 213000 | R17: 213000
C18: Pagamento Devolvido | K18: 4166.99 | O18: 21331.5 | R18: 25498.49
C19: REALIZE GESTAO | K19: 4166.99 | O19: 21331.5 | R19: 25498.49
C20: 2. Contas a Pagar | E20: -10140.8 | F20: -17896.44 | G20: -4497.39 | H20: -1636.75 | J20: -100 | K20: -364673.4 | L20: -7150.12 | M20: -303377.7 | N20: -10549.54 | O20: -89628.5 | P20: -12017 | Q20: -1610.5 | R20: -823278.14
C21: 2.2 Despesas de Vendas e Marketing | E21: -2320 | R21: -2320
C22: Despesas de Viagens | E22: -2320 | R22: -2320
C23: 2.4 Despesas Administrativas | E23: -7820.8 | F23: -17896.44 | G23: -397.39 | H23: -1551 | L23: -5520 | M23: -3360.7 | N23: -5000 | O23: -64000 | R23: -105546.33
C24: Alimentação | F24: -101.8 | G24: -397.39 | H24: -91 | R24: -590.19
C25: Hospedagem | F25: -400 | H25: -1460 | L25: -520 | R25: -2380
C26: Passagens Aéreas | E26: -7820.8 | R26: -7820.8
C27: TRANSPORTE | F27: -1423.09 | R27: -1423.09
C28: ADMINISTRAÇAO | F28: -15971.55 | L28: -2000 | M28: -3360.7 | N28: -5000 | O28: -64000 | R28: -90332.25
C29: Aluguel | L29: -3000 | R29: -3000
C30: 2.5 Despesas Financeiras / Bancos | G30: -4100 | J30: -100 | K30: -77.8 | L30: -30.12 | M30: -17 | N30: -27.79 | O30: -17 | P30: -17 | Q30: -8.5 | R30: -4395.21
C31: Pagamento de Empréstimos | G31: -4100 | J31: -90 | R31: -4190
C32: Tarifas Bancárias | J32: -10 | K32: -77.8 | L32: -30.12 | M32: -17 | N32: -27.79 | O32: -17 | P32: -17 | Q32: -8.5 | R32: -205.21
C33: 2.8 Outras Despesas | H33: -85.75 | R33: -85.75
C34: Distribuição de Lucros | H34: -85.75 | R34: -85.75
C35: ANDRE LUCIANO DE OLIVEIRA SALGADO | H35: -85.75 | R35: -85.75
C36: 2.1 Despesas Diretas | K36: -5000 | L36: -1600 | M36: -300000 | N36: -5521.75 | O36: -4280 | P36: -12000 | Q36: -1602 | R36: -330003.75
C37: MAO DE OBRA | K37: -5000 | L37: -1600 | N37: -3676 | P37: -2000 | Q37: -1602 | R37: -13878
C38: RESTAURANTE | Q38: -1602 | R38: -1602
C39: CHARLES DE FRAGA DOMINGOS | K39: -5000 | P39: -2000 | R39: -7000
C40: ALCIDES BOFF TISATTO | L40: -1600 | R40: -1600
C41: IRMAOS SALVADOR & CIA. LTDA. | N41: -3676 | R41: -3676
C42: FABRICA | M42: -300000 | R42: -300000
C43: PREVENCAO BRASIL | M43: -300000 | R43: -300000
C44: FERRAGEM | N44: -145.75 | R44: -145.75
C45: IRMAOS SALVADOR & CIA. LTDA. | N45: -145.75 | R45: -145.75
C46: MATERIAL | N46: -1700 | R46: -1700
C47: João Pedro da Silva Ribeiro | N47: -1700 | R47: -1700
C48: MADEIRA | O48: -4280 | R48: -4280
C49: IRMAOS SALVADOR & CIA. LTDA. | O49: -4280 | R49: -4280
C50: Agregado | P50: -10000 | R50: -10000
C51: IRMAOS SALVADOR & CIA. LTDA. | P51: -10000 | R51: -10000
C52: 99 Transferências | K52: -359595.6 | O52: -21331.5 | R52: -380927.1
C53: Pagamento Devolvido | K53: -146595.6 | O53: -21331.5 | R53: -167927.1
C54: REALIZE GESTAO | K54: -146595.6 | O54: -21331.5 | R54: -167927.1
C55: Saída de Transferência | K55: -213000 | R55: -213000
C56: Não informado | K56: -213000 | R56: -213000
C57: Total Geral | D57: 200000 | E57: 20859.2 | F57: -1924.89 | G57: -4497.39 | H57: -1636.75 | I57: 199.83 | J57: 0 | K57: -47506.41 | L57: 172849.88 | M57: -303377.7 | N57: -10549.54 | O57: 94468 | P57: -12017 | Q57: -1610.5 | R57: 105256.73

Sheet FLUXO PREVISTO
E1: MÃO DE OBRA - DIA 20 ADIANTAMENTO DE 40% E DIA 05 O RESTANTE
B5: =D5 -> 105256.73 | C5: SALDO INICIAL | D5: ='FLUXO REALIZADO'!B8 -> 105256.73 | E5: =D8 -> 105256.73 | F5: =E8 -> 251785.34 | G5: =F8 -> 226185.34 | H5: =G8 -> 220745.34 | I5: =H8 -> 218245.34 | J5: =I8 -> 209245.34 | K5: =J8 -> 177245.34 | L5: =K8 -> 144610.94 | ... BY5: =BX8 -> 1331952.1
B6: =SUM(D6:BE6) -> 5723267.6 | C6: ENTRADAS | D6: =GETPIVOTDATA("A Pagar ou Receber",$C$11,"Data de Previsão (completa)",D12,"Tipo","1. Contas a Receber") -> 0 | E6: =GETPIVOTDATA("A Pagar ou Receber",$C$11,"Data de Previsão (completa)",E12,"Tipo","1. Contas a Receber") -> 146528.61 | F6: =GETPIVOTDATA("A Pagar ou Receber",$C$11,"Data de Previsão (completa)",F12,"Tipo","1. Contas a Receber") -> 0 | G6: =GETPIVOTDATA("A Pagar ou Receber",$C$11,"Data de Previsão (completa)",G12,"Tipo","1. Contas a Receber") -> 0 | H6: =GETPIVOTDATA("A Pagar ou Receber",$C$11,"Data de Previsão (completa)",H12,"Tipo","1. Contas a Receber") -> 0 | I6: =GETPIVOTDATA("A Pagar ou Receber",$C$11,"Data de Previsão (completa)",I12,"Tipo","1. Contas a Receber") -> 0 | J6: =GETPIVOTDATA("A Pagar ou Receber",$C$11,"Data de Previsão (completa)",J12,"Tipo","1. Contas a Receber") -> 0 | K6: =GETPIVOTDATA("A Pagar ou Receber",$C$11,"Data de Previsão (completa)",K12,"Tipo","1. Contas a Receber") -> 0 | ... BY6: =GETPIVOTDATA("A Pagar ou Receber",$C$11,"Data de Previsão (completa)",BY12,"Tipo","1. Contas a Receber") -> 0
B7: =SUM(D7:BE7) -> -4897666.4 | C7: SAÍDAS | D7: =GETPIVOTDATA("A Pagar ou Receber",$C$11,"Data de Previsão (completa)",D12,"Tipo","2. Contas a Pagar") -> 0 | E7: =GETPIVOTDATA("A Pagar ou Receber",$C$11,"Data de Previsão (completa)",E12,"Tipo","2. Contas a Pagar") -> 0 | F7: =GETPIVOTDATA("A Pagar ou Receber",$C$11,"Data de Previsão (completa)",F12,"Tipo","2. Contas a Pagar") -> -25600 | G7: =GETPIVOTDATA("A Pagar ou Receber",$C$11,"Data de Previsão (completa)",G12,"Tipo","2. Contas a Pagar") -> -5440 | H7: =GETPIVOTDATA("A Pagar ou Receber",$C$11,"Data de Previsão (completa)",H12,"Tipo","2. Contas a Pagar") -> -2500 | I7: =GETPIVOTDATA("A Pagar ou Receber",$C$11,"Data de Previsão (completa)",I12,"Tipo","2. Contas a Pagar") -> -9000 | J7: =GETPIVOTDATA("A Pagar ou Receber",$C$11,"Data de Previsão (completa)",J12,"Tipo","2. Contas a Pagar") -> -32000 | K7: =GETPIVOTDATA("A Pagar ou Receber",$C$11,"Data de Previsão (completa)",K12,"Tipo","2. Contas a Pagar") -> -32634.4 | ... BY7: =GETPIVOTDATA("A Pagar ou Receber",$C$11,"Data de Previsão (completa)",BY12,"Tipo","2. Contas a Pagar") -> -30000
B8: =SUM(B5:B7) -> 930857.9 | C8: SALDO FINAL | D8: =SUM(D5:D7) -> 105256.73 | E8: =SUM(E5:E7) -> 251785.34 | F8: =SUM(F5:F7) -> 226185.34 | G8: =SUM(G5:G7) -> 220745.34 | H8: =SUM(H5:H7) -> 218245.34 | I8: =SUM(I5:I7) -> 209245.34 | J8: =SUM(J5:J7) -> 177245.34 | K8: =SUM(K5:K7) -> 144610.94 | ... BY8: =SUM(BY5:BY7) -> 1301952.1
C11: Soma de A Pagar ou Receber | D11: Rótulos de Coluna
C12: Rótulos de Linha | D12: 46098 | E12: 46099 | F12: 46101 | G12: 46106 | H12: 46108 | I12: 46113 | J12: 46117 | K12: 46118 | L12: 46120 | M12: 46122 | N12: 46123 | O12: 46129 | P12: 46132 | Q12: 46133 | R12: 46136 | S12: 46139 | T12: 46140 | U12: 46142 | V12: 46143 | W12: 46146 | X12: 46148 | Y12: 46150 | Z12: 46152 | AA12: 46153 | AB12: 46154 | AC12: 46159 | AD12: 46160 | AE12: 46162 | AF12: 46163 | AG12: 46164 | AH12: 46167 | AI12: 46168 | AJ12: 46169 | AK12: 46170 | AL12: 46171 | AM12: 46174 | AN12: 46177 | AO12: 46178 | AP12: 46179 | AQ12: 46180 | AR12: 46181 | AS12: 46182 | AT12: 46183 | AU12: 46184 | AV12: 46185 | AW12: 46188 | AX12: 46190 | AY12: 46192 | AZ12: 46193 | BA12: 46195 | BB12: 46196 | BC12: 46199 | BD12: 46200 | BE12: 46201 | BF12: 46202 | BG12: 46204 | BH12: 46206 | BI12: 46207 | BJ12: 46209 | BK12: 46210 | BL12: 46211 | BM12: 46213 | BN12: 46214 | BO12: 46220 | BP12: 46223 | BQ12: 46224 | BR12: 46229 | BS12: 46230 | BT12: 46234 | BU12: 46237 | BV12: 46238 | BW12: 46244 | BX12: 46245 | BY12: 46251 | BZ12: Total Geral
C13: 1. Contas a Receber | E13: 146528.61 | S13: 855077.76 | AA13: 758705.11 | AH13: 1185999.4 | AR13: 1128269.9 | AW13: 64000 | BA13: 1584686.8 | BJ13: 929910.25 | BP13: 602051.82 | BT13: 1000 | BU13: 315298.84 | BZ13: 7571528.5
C14: 1.4 Outras Entradas | E14: 4100 | AW14: 64000 | BT14: 1000 | BZ14: 69100
C15: 99 Transferências | E15: 142428.61 | BZ15: 142428.61
C16: 1.1 Receitas Diretas | S16: 855077.76 | AA16: 758705.11 | AH16: 1185999.4 | AR16: 1128269.9 | BA16: 1584686.8 | BJ16: 929910.25 | BP16: 602051.82 | BU16: 315298.84 | BZ16: 7359999.9
C17: 2. Contas a Pagar | D17: 0 | F17: -25600 | G17: -5440 | H17: -2500 | I17: -9000 | J17: -32000 | K17: -32634.4 | L17: -44876.35 | M17: -26000 | N17: -3250 | O17: -35413.17 | P17: -32500 | Q17: -3900 | R17: -3000 | S17: -6544 | T17: -783508.51 | U17: -23800 | V17: -14266.667 | W17: -10834.047 | X17: -16892.267 | Y17: -58980.28 | Z17: -2000 | AA17: -5495.32 | AB17: -691551.12 | AC17: -49244.404 | AD17: -2867.2 | AE17: -9147.2 | AF17: -7233.3333 | AG17: -8993.7 | AI17: -683761.47 | AJ17: -50063.65 | AK17: -276594.66 | AL17: -14060.608 | AM17: -38233.514 | AN17: -13780.533 | AO17: -73675.14 | AP17: -8025.6 | AQ17: -12438.059 | AR17: -14716.35 | AS17: -590003.74 | AT17: -5250 | AU17: -141633.49 | AV17: -18506.05 | AX17: -31140.42 | AY17: -79935.28 | AZ17: -9147.2 | BB17: -537823.1 | BC17: -55804.8 | BD17: -19006.15 | BE17: -276594.66 | BF17: -7966.8469 | BG17: -134266.67 | BH17: -101824.77 | BI17: -6547.2 | BK17: -161157.01 | BL17: -214716.35 | BM17: -2000 | BN17: -124954.52 | BO17: -76757.78 | BQ17: -105802.08 | BR17: -13622.4 | BS17: -280000 | BT17: -77748.83 | BV17: -51396.577 | BW17: -2000 | BX17: -86405.72 | BY17: -30000 | BZ17: -6374833.2
C18: 2.4 Despesas Administrativas | K18: -26534.4 | M18: -26000 | N18: -3250 | R18: -3000 | T18: -16100 | Z18: -2000 | AA18: -5495.32 | AB18: -72430 | AG18: -3000 | AI18: -13335 | AM18: -16000 | AS18: -44075 | AT18: -5250 | BK18: -29000 | BM18: -2000 | BW18: -2000 | BZ18: -269469.72
C19: TRANSPORTE | K19: -26534.4 | T19: -16100 | AA19: -2245.32 | AB19: -40430 | AI19: -13335 | AS19: -12075 | BZ19: -110719.72
C20: ADMINISTRAÇAO | M20: -26000 | N20: -3250 | R20: -3000 | Z20: -2000 | AA20: -3250 | AB20: -32000 | AG20: -3000 | AM20: -16000 | AS20: -32000 | AT20: -5250 | BK20: -29000 | BM20: -2000 | BW20: -2000 | BZ20: -158750
C21: GUSTAVO CEZAR DE CARVALHO | M21: -10000 | BZ21: -10000
C22: FULLBPO | M22: -2000 | Z22: -2000 | AT22: -2000 | BM22: -2000 | BW22: -2000 | BZ22: -10000
C23: RODRIGO ZULIAN | N23: -3250 | AA23: -3250 | AT23: -3250 | BZ23: -9750
C24: PREVISAO | M24: -14000 | R24: -3000 | AB24: -32000 | AG24: -3000 | AM24: -16000 | AS24: -32000 | BK24: -29000 | BZ24: -129000
C25: 2.5 Despesas Financeiras / Bancos | I25: -9000 | L25: -14716.35 | O25: -30000 | V25: -9600 | Y25: -14716.35 | AC25: -30000 | AJ25: -19006.15 | AM25: -9600 | AR25: -14716.35 | AX25: -30000 | BD25: -19006.15 | BG25: -129600 | BL25: -214716.35 | BO25: -30000 | BS25: -280000 | BY25: -30000 | BZ25: -884677.7
C26: Pagamento de Empréstimos | I26: -9000 | L26: -14716.35 | O26: -30000 | V26: -9600 | Y26: -14716.35 | AC26: -30000 | AJ26: -19006.15 | AM26: -9600 | AR26: -14716.35 | AX26: -30000 | BD26: -19006.15 | BG26: -129600 | BL26: -214716.35 | BO26: -30000 | BS26: -280000 | BY26: -30000 | BZ26: -884677.7
C27: MARCELO DE ANGELO | O27: -30000 | AC27: -30000 | AJ27: -19006.15 | AX27: -30000 | BD27: -19006.15 | BO27: -30000 | BS27: -280000 | BY27: -30000 | BZ27: -468012.3
C28: OITO APOIO ADMINISTRATIVO E LOGISTICO | L28: -14716.35 | Y28: -14716.35 | AR28: -14716.35 | BL28: -214716.35 | BZ28: -258865.4
C29: FM SOLUÇOES | I29: -9000 | V29: -9600 | AM29: -9600 | BG29: -129600 | BZ29: -157800
C30: 2.1 Despesas Diretas | D30: 0 | F30: -25600 | G30: -5440 | H30: -2500 | J30: -32000 | K30: -6100 | L30: -30160 | O30: -5413.17 | P30: -32500 | Q30: -3900 | S30: -6544 | T30: -744443.51 | U30: -23800 | V30: -4666.6667 | W30: -10834.047 | X30: -16892.267 | Y30: -44263.93 | AB30: -602213.62 | AC30: -19244.404 | AD30: -2867.2 | AE30: -9147.2 | AF30: -7233.3333 | AG30: -5993.7 | AI30: -655586.47 | AJ30: -17600 | AK30: -276594.66 | AL30: -14060.608 | AM30: -12633.514 | AN30: -13780.533 | AO30: -73675.14 | AP30: -8025.6 | AQ30: -12438.059 | AS30: -531088.74 | AU30: -141633.49 | AV30: -18506.05 | AX30: -1140.42 | AY30: -79935.28 | AZ30: -9147.2 | BB30: -537823.1 | BC30: -55804.8 | BE30: -276594.66 | BF30: -7966.8469 | BG30: -4666.6667 | BH30: -101824.77 | BI30: -6547.2 | BK30: -132157.01 | BN30: -124954.52 | BO30: -46757.78 | BQ30: -105802.08 | BR30: -13622.4 | BT30: -77748.83 | BV30: -51396.577 | BX30: -86405.72 | BZ30: -5137675.8
C31: MAO DE OBRA | D31: 0 | F31: -25600 | J31: -32000 | K31: -700 | T31: -47941.33 | AB31: -187978.83 | AI31: -217066.97 | AS31: -218198.88 | BB31: -198637.59 | BK31: -91716.2 | BQ31: -83605.58 | BV31: -36522.24 | BZ31: -1139967.6
C32: PREVISAO | F32: -25600 | J32: -32000 | K32: -700 | T32: -47941.33 | AB32: -60778.83 | AI32: -164066.97 | AS32: -112198.88 | BB32: -145637.59 | BK32: -91716.2 | BQ32: -83605.58 | BV32: -36522.24 | BZ32: -800767.62
C33: CHARLES DE FRAGA DOMINGOS | D33: 0 | BZ33: 0
C34: AEV GUINDASTES | AB34: -127200 | AI34: -53000 | AS34: -106000 | BB34: -53000 | BZ34: -339200
C35: FABRICA | L35: -28560 | P35: -23800 | T35: -426356.26 | U35: -23800 | X35: -8866.6667 | AB35: -153922.51 | AF35: -7233.3333 | AI35: -315350.55 | AK35: -241333.33 | AN35: -7233.3333 | AS35: -251543.02 | BB35: -266760.36 | BE35: -241333.33 | BK35: -39508.333 | BZ35: -2035601
C36: PREVISAO | L36: -28560 | P36: -23800 | U36: -23800 | X36: -8866.6667 | AF36: -7233.3333 | AI36: -61906.667 | AN36: -7233.3333 | AS36: -60300 | BB36: -58666.667 | BK36: -7233.3333 | BZ36: -287600
C37: PREVIBRAS / LIDER | T37: -426356.26 | AB37: -153922.51 | AI37: -253443.88 | AK37: -241333.33 | AS37: -191243.02 | BB37: -208093.69 | BE37: -241333.33 | BK37: -32275 | BZ37: -1748001
C38: FERRAGEM | O38: -868.4 | T38: -49648.637 | AB38: -14498.197 | AC38: -868.4 | AI38: -14498.197 | AK38: -35261.33 | AO38: -3836.8 | AU38: -124.8 | AY38: -3836.8 | BE38: -35261.33 | BN38: -124.8 | BZ38: -158827.69
C39: MARCELO DE ANGELO | O39: -868.4 | AC39: -868.4 | BZ39: -1736.8
C40: PREVISAO | AO40: -3836.8 | AU40: -124.8 | AY40: -3836.8 | BN40: -124.8 | BZ40: -7923.2
C41: JM FERRAGENS | T41: -14387.307 | AB41: -14498.197 | AI41: -14498.197 | BZ41: -43383.7
C42: GERDAU | T42: -10000 | AK42: -10000 | BE42: -10000 | BZ42: -30000
C43: HORSTMANN | T43: -25261.33 | AK43: -25261.33 | BE43: -25261.33 | BZ43: -75783.99
C44: MATERIAL | H44: -2500 | AY44: -1076.96 | BB44: -931.48 | BH44: -1076.96 | BK44: -932.48 | BQ44: -3349.66 | BV44: -4727.5 | BZ44: -14595.04
C45: PREVISAO | H45: -2500 | AY45: -1076.96 | BB45: -931.48 | BH45: -1076.96 | BK45: -932.48 | BQ45: -3349.66 | BV45: -4727.5 | BZ45: -14595.04
C46: MADEIRA | K46: -3900 | O46: -2073.92 | Q46: -3900 | AB46: -11551.383 | AC46: -1140.42 | AO46: -1292.16 | AV46: -906.05 | AX46: -1140.42 | AY46: -1292.16 | BO46: -1140.42 | BZ46: -28336.933
C47: MARCELO DE ANGELO | O47: -1140.42 | AC47: -1140.42 | AX47: -1140.42 | BO47: -1140.42 | BZ47: -4561.68
C48: PREVISAO | O48: -933.5 | AB48: -11551.383 | AO48: -1292.16 | AV48: -906.05 | AY48: -1292.16 | BZ48: -15975.253
C49: MADEREIRA LOCAL | K49: -3900 | Q49: -3900 | BZ49: -7800
C50: Tubos e conexoes | T50: -14063.218 | W50: -7966.8469 | AB50: -14063.218 | AG50: -4827.17 | AI50: -14063.218 | AM50: -7966.8469 | AY50: -12104.72 | BF50: -7966.8469 | BO50: -12104.72 | BZ50: -95126.804
C51: PREVISAO | T51: -14063.218 | W51: -7966.8469 | AB51: -14063.218 | AG51: -4827.17 | AI51: -14063.218 | AM51: -7966.8469 | AY51: -12104.72 | BF51: -7966.8469 | BO51: -12104.72 | BZ51: -95126.804
C52: CONCRETO | T52: -168280 | AB52: -168280 | AC52: -16177.664 | AI52: -10645.333 | AL52: -13197.568 | AO52: -15872 | AU52: -13197.568 | AY52: -15872 | BZ52: -421522.13
C53: PREVISAO | T53: -168280 | AB53: -168280 | AI53: -10645.333 | AO53: -15872 | AY53: -15872 | BZ53: -378949.33
C54: REDEMAC | AC54: -16177.664 | AL54: -13197.568 | AU54: -13197.568 | BZ54: -42572.8
C55: RATEIO | O55: -2470.85 | AB55: -1603 | BZ55: -4073.85
C56: PREVISAO | O56: -2470.85 | AB56: -1603 | BZ56: -4073.85
C57: SERVIÇO | G57: -3840 | AB57: -3840 | BZ57: -7680
C58: PREVISAO | G58: -3840 | AB58: -3840 | BZ58: -7680
C59: INSUMO | K59: -1500 | T59: -15819.355 | W59: -2867.2 | Y59: -16088 | AB59: -5159.712 | AC59: -1057.92 | AD59: -2867.2 | AI59: -5159.712 | AL59: -863.04 | AO59: -18955.2 | AU59: -13367.04 | AY59: -1018.88 | BN59: -12504 | BO59: -1018.88 | BZ59: -98246.139
C60: PREVISAO | T60: -12340.825 | Y60: -16088 | AB60: -1681.182 | AI60: -1681.182 | AO60: -16088 | AU60: -12504 | AY60: -1018.88 | BN60: -12504 | BO60: -1018.88 | BZ60: -74924.949
C61: JM FERRAGENS | T61: -3478.53 | AB61: -3478.53 | AI61: -3478.53 | BZ61: -10435.59
C62: REDEMAC | AC62: -1057.92 | AL62: -863.04 | AU62: -863.04 | BZ62: -2784
C63: TILECOL | W63: -2867.2 | AD63: -2867.2 | AO63: -2867.2 | BZ63: -8601.6
C64: SOLDA SUL | K64: -1500 | BZ64: -1500
C65: LOCAÇAO | G65: -1600 | L65: -1600 | P65: -8700 | V65: -4666.6667 | AE65: -2600 | AM65: -4666.6667 | AZ65: -2600 | BG65: -4666.6667 | BQ65: -8700 | BZ65: -39800
C66: PREVISAO | G66: -1600 | L66: -1600 | P66: -8700 | AE66: -2600 | AZ66: -2600 | BQ66: -8700 | BZ66: -25800
C67: CARTAO DE CREDITO | V67: -4666.6667 | AM67: -4666.6667 | BG67: -4666.6667 | BZ67: -14000
C68: Agregado | D68: 0 | T68: -22334.71 | AB68: -22334.71 | AG68: -1166.53 | AO68: -6240 | AY68: -6240 | BZ68: -58315.95
C69: IRMAOS SALVADOR & CIA. LTDA. | D69: 0 | BZ69: 0
C70: PREVISAO | T70: -22334.71 | AB70: -22334.71 | AG70: -1166.53 | AO70: -6240 | AY70: -6240 | BZ70: -58315.95
C71: REVESTIMENTO | Y71: -26239.29 | AO71: -25599.3 | BH71: -21119.3 | BZ71: -72957.89
C72: PREVISAO | Y72: -26239.29 | AO72: -25599.3 | BH72: -21119.3 | BZ72: -72957.89
C73: TELHAS | AB73: -12438.059 | AI73: -22584.896 | AQ73: -12438.059 | AS73: -10146.837 | BB73: -20293.675 | BQ73: -10146.837 | BV73: -10146.837 | BZ73: -98195.2
C74: PREVISAO | AB74: -12438.059 | AI74: -22584.896 | AQ74: -12438.059 | AS74: -10146.837 | BB74: -20293.675 | BQ74: -10146.837 | BV74: -10146.837 | BZ74: -98195.2
C75: TINTAS | Y75: -1936.64 | AI75: -56217.6 | AO75: -1879.68 | BC75: -55804.8 | BH75: -1879.68 | BR75: -13622.4 | BZ75: -131340.8
C76: PREVISAO | Y76: -1936.64 | AI76: -56217.6 | AO76: -1879.68 | BC76: -55804.8 | BH76: -1879.68 | BR76: -13622.4 | BZ76: -131340.8
C77: ESQUADRIA | AU77: -114944.08 | BN77: -112325.72 | BX77: -86405.72 | BZ77: -313675.52
C78: PREVISAO | AU78: -114944.08 | BN78: -112325.72 | BX78: -86405.72 | BZ78: -313675.52
C79: Pre moldado | S79: -6544 | X79: -8025.6 | AB79: -6544 | AE79: -6547.2 | AJ79: -17600 | AN79: -6547.2 | AP79: -8025.6 | AS79: -51200 | AV79: -17600 | AZ79: -6547.2 | BB79: -51200 | BI79: -6547.2 | BZ79: -192928
C80: PREVISAO | S80: -6544 | X80: -8025.6 | AB80: -6544 | AE80: -6547.2 | AJ80: -17600 | AN80: -6547.2 | AP80: -8025.6 | AS80: -51200 | AV80: -17600 | AZ80: -6547.2 | BB80: -51200 | BI80: -6547.2 | BZ80: -192928
C81: LOUÇAS | AY81: -17984.64 | BO81: -17984.64 | BZ81: -35969.28
C82: PREVISAO | AY82: -17984.64 | BO82: -17984.64 | BZ82: -35969.28
C83: METAL | AY83: -6512.32 | BO83: -6512.32 | BZ83: -13024.64
C84: PREVISAO | AY84: -6512.32 | BO84: -6512.32 | BZ84: -13024.64
C85: BANCADA | AY85: -13996.8 | BO85: -7996.8 | BZ85: -21993.6
C86: PREVISAO | AY86: -13996.8 | BO86: -7996.8 | BZ86: -21993.6
C87: ELETRICO | BH87: -77748.83 | BT87: -77748.83 | BZ87: -155497.66
C88: PREVISAO | BH88: -77748.83 | BT88: -77748.83 | BZ88: -155497.66
T89: -22965 | AB89: -16907.5 | AI89: -14840 | AJ89: -13457.5 | AS89: -14840 | BZ89: -83010
C90: Total Geral | D90: 0 | E90: 146528.61 | F90: -25600 | G90: -5440 | H90: -2500 | I90: -9000 | J90: -32000 | K90: -32634.4 | L90: -44876.35 | M90: -26000 | N90: -3250 | O90: -35413.17 | P90: -32500 | Q90: -3900 | R90: -3000 | S90: 848533.76 | T90: -783508.51 | U90: -23800 | V90: -14266.667 | W90: -10834.047 | X90: -16892.267 | Y90: -58980.28 | Z90: -2000 | AA90: 753209.79 | AB90: -691551.12 | AC90: -49244.404 | AD90: -2867.2 | AE90: -9147.2 | AF90: -7233.3333 | AG90: -8993.7 | AH90: 1185999.4 | AI90: -683761.47 | AJ90: -50063.65 | AK90: -276594.66 | AL90: -14060.608 | AM90: -38233.514 | AN90: -13780.533 | AO90: -73675.14 | AP90: -8025.6 | AQ90: -12438.059 | AR90: 1113553.6 | AS90: -590003.74 | AT90: -5250 | AU90: -141633.49 | AV90: -18506.05 | AW90: 64000 | AX90: -31140.42 | AY90: -79935.28 | AZ90: -9147.2 | BA90: 1584686.8 | BB90: -537823.1 | BC90: -55804.8 | BD90: -19006.15 | BE90: -276594.66 | BF90: -7966.8469 | BG90: -134266.67 | BH90: -101824.77 | BI90: -6547.2 | BJ90: 929910.25 | BK90: -161157.01 | BL90: -214716.35 | BM90: -2000 | BN90: -124954.52 | BO90: -76757.78 | BP90: 602051.82 | BQ90: -105802.08 | BR90: -13622.4 | BS90: -280000 | BT90: -76748.83 | BU90: 315298.84 | BV90: -51396.577 | BW90: -2000 | BX90: -86405.72 | BY90: -30000 | BZ90: 1196695.3
