Workbook

Sheet INSTRUCOES
A1: Fluxo de Caixa Diário — instruções rápidas
A3: Projeto | B3: SÃO FRANCISCO DE PAULA - RS | D3: Qtd. casas | E3: 64
A5: 1. | B5: Use a aba BASE_CAIXA como base única para tabela dinâmica e análises.
A6: 2. | B6: Preencha as colunas amarelas: Fornecedor, Lote_Pagto, Documento, Data_Prevista, Data_Realizada e Valor_Realizado.
A7: 3. | B7: As linhas 251–257 e 259–266 foram classificadas como GESTÃO LOCAL.
A8: 4. | B8: As linhas 269–271 foram classificadas como DESPESAS ACESSÓRIAS.
A9: 5. | B9: As linhas 273–277 foram classificadas como CAPITAL DE GIRO.
A10: 6. | B10: A aba FLUXO_DIARIO soma previsto pendente e realizado por dia.
A11: 7. | B11: A aba SAUDE_FLUXO mostra indicadores de suficiência, saldo mínimo e dias críticos.
A14: Amarelo = edição manual | C14: Cinza claro = cálculo
A16: 6. | B16: Nova arquitetura financeira: BASE_CAIXA (gerencial) + AGENDA_BANCARIA (o que deve aparecer no banco) + EXTRATO_IMPORTADO (onde você cola o extrato) + CONCILIACAO (resumo).
A17: 7. | B17: Na BASE_CAIXA, preencha principalmente: Fornecedor, Lote_Pagto, Documento, Forma_Pagamento, Meio_Financeiro, Conta_Origem e Data_Vencimento.
A18: 8. | B18: Para cartão de crédito, a Data_Vencimento deve refletir a data da fatura/parcela; a Data_Compensacao_Prevista é o dia em que você espera enxergar o efeito no extrato/fatura.
A19: 9. | B19: Cole o extrato bruto na aba EXTRATO_IMPORTADO a partir da linha 2. Depois preencha o ID_Concil_Manual com a chave da AGENDA_BANCARIA quando identificar o lançamento.
A20: 10. | B20: A aba CONCILIACAO resume quantos eventos estão conciliados, pendentes, vencidos, divergentes e quantos movimentos do extrato vieram sem previsão.

Sheet BASE_CAIXA
A1: ID | B1: Projeto | C1: Tipo_Fluxo | D1: Grupo | E1: Apropriacao | F1: Tipo | G1: Item | H1: Fornecedor | I1: Lote_Pagto | J1: Documento | K1: Data_Prevista | L1: Data_Realizada | M1: Valor_Realizado | N1: Forma_Pagamento | O1: Meio_Financeiro | P1: Conta_Origem | Q1: Data_Vencimento | R1: Categoria | S1: Conta_Sintetica | T1: Conta_Analitica | U1: Observacoes | V1: Linha_Origem | W1: Quinzena | X1: Periodo_Inicio | Y1: Periodo_Fim | Z1: Valor_Previsto | AA1: Valor_Considerado | AB1: Status | AC1: %_Quinzena | AD1: Valor_Origem_Linha | AE1: Quant_Total_Origem | AF1: Unidade_Origem | AG1: Custo_Unit_Origem | AH1: Info_Origem_Extra | AI1: Aba_Origem | AJ1: Data_Compensacao_Prevista | AK1: Conciliar? | AL1: ID_Concil | AM1: Historico_Padrao_Extrato
A2: 1 | B2: SÃO FRANCISCO DE PAULA - RS | C2: Entrada | D2: RECEITAS | E2: RECEITAS | F2: RECEITA CONTRATUAL | G2: MEDIÇÃO CONTRATUAL | H2: FM SOLUÇÕES EM BEBIDAS | I2: INVEST_01 | K2: 46080 | L2: 2702 | M2: 720000 | N2: PIX | Q2: =IF(K2="","",K2) -> 46080 | R2: MEDIÇÃO CONTRATUAL | S2: Entrada | MEDIÇÃO CONTRATUAL | T2: Entrada | RECEITAS | RECEITA CONTRATUAL | U2: aporte investidor | V2: 283 | W2: Q1 | X2: 46090 | Y2: 46101 | Z2: 720000 | AA2: =IF(M2<>"",M2,Z2) -> 720000 | AB2: =IF(L2<>"","Realizado","Previsto") -> Realizado | AD2: 8079999.9 | AI2: CUSTO CASA E CRONOGRAMA PAGAMEN | AJ2: =IF(Q2<>"",Q2,IF(K2<>"",K2,"")) -> 46080 | AK2: =IF(K2<>"","Sim","") -> Sim | AL2: =IF(A2="","",TEXT(A2,"000000")&"-"&IF(C2="Entrada","CR","DB")) -> 000001-CR | AM2: =IF(A2="","",LEFT(IF(H2<>"",H2,G2)&" | "&G2&" | "&S2,60)) -> FM SOLUÇÕES EM BEBIDAS | MEDIÇÃO CONTRATUAL | Entrada | MEDI
A3: 2 | B3: SÃO FRANCISCO DE PAULA - RS | C3: Saída | D3: DESPESAS ACESSÓRIAS | E3: DESPESAS ACESSÓRIAS | F3: DESPESAS ACESSÓRIAS | G3: CAUÇÃO | K3: 46092 | Q3: =IF(K3="","",K3) -> 46092 | R3: DESPESAS ACESSÓRIAS | S3: Saída | DESPESAS ACESSÓRIAS | T3: Saída | DESPESAS ACESSÓRIAS | DESPESAS ACESSÓRIAS | V3: 270 | W3: Q1 | X3: 46090 | Y3: 46101 | Z3: 64000 | AA3: =IF(M3<>"",M3,Z3) -> 64000 | AB3: =IF(L3<>"","Realizado","Previsto") -> Previsto | AC3: 1 | AD3: 64000 | AF3: mês | AG3: 64000 | AI3: CUSTO CASA E CRONOGRAMA PAGAMEN | AJ3: =IF(Q3<>"",Q3,IF(K3<>"",K3,"")) -> 46092 | AK3: =IF(K3<>"","Sim","") -> Sim | AL3: =IF(A3="","",TEXT(A3,"000000")&"-"&IF(C3="Entrada","CR","DB")) -> 000002-DB | AM3: =IF(A3="","",LEFT(IF(H3<>"",H3,G3)&" | "&G3&" | "&S3,60)) -> CAUÇÃO | CAUÇÃO | Saída | DESPESAS ACESSÓRIAS
A4: 3 | B4: SÃO FRANCISCO DE PAULA - RS | C4: Saída | D4: DESPESAS ACESSÓRIAS | E4: DESPESAS ACESSÓRIAS | F4: DESPESAS ACESSÓRIAS | G4: LOGISTICA GESTÃO VISITA À OBRA | K4: 46090 | Q4: =IF(K4="","",K4) -> 46090 | R4: DESPESAS ACESSÓRIAS | S4: Saída | DESPESAS ACESSÓRIAS | T4: Saída | DESPESAS ACESSÓRIAS | DESPESAS ACESSÓRIAS | V4: 271 | W4: Q1 | X4: 46090 | Y4: 46101 | Z4: 16000 | AA4: =IF(M4<>"",M4,Z4) -> 16000 | AB4: =IF(L4<>"","Realizado","Previsto") -> Previsto | AC4: 0.4 | AD4: 40000 | AF4: mês | AG4: 10000 | AI4: CUSTO CASA E CRONOGRAMA PAGAMEN | AJ4: =IF(Q4<>"",Q4,IF(K4<>"",K4,"")) -> 46090 | AK4: =IF(K4<>"","Sim","") -> Sim | AL4: =IF(A4="","",TEXT(A4,"000000")&"-"&IF(C4="Entrada","CR","DB")) -> 000003-DB | AM4: =IF(A4="","",LEFT(IF(H4<>"",H4,G4)&" | "&G4&" | "&S4,60)) -> LOGISTICA GESTÃO VISITA À OBRA | LOGISTICA GESTÃO VISITA À O
A5: 4 | B5: SÃO FRANCISCO DE PAULA - RS | C5: Saída | D5: DESPESAS ACESSÓRIAS | E5: DESPESAS ACESSÓRIAS | F5: DESPESAS ACESSÓRIAS | G5: SEGURO | K5: 46090 | Q5: =IF(K5="","",K5) -> 46090 | R5: DESPESAS ACESSÓRIAS | S5: Saída | DESPESAS ACESSÓRIAS | T5: Saída | DESPESAS ACESSÓRIAS | DESPESAS ACESSÓRIAS | V5: 269 | W5: Q1 | X5: 46090 | Y5: 46101 | Z5: 16000 | AA5: =IF(M5<>"",M5,Z5) -> 16000 | AB5: =IF(L5<>"","Realizado","Previsto") -> Previsto | AC5: 1 | AD5: 16000 | AF5: mês | AG5: 16000 | AI5: CUSTO CASA E CRONOGRAMA PAGAMEN | AJ5: =IF(Q5<>"",Q5,IF(K5<>"",K5,"")) -> 46090 | AK5: =IF(K5<>"","Sim","") -> Sim | AL5: =IF(A5="","",TEXT(A5,"000000")&"-"&IF(C5="Entrada","CR","DB")) -> 000004-DB | AM5: =IF(A5="","",LEFT(IF(H5<>"",H5,G5)&" | "&G5&" | "&S5,60)) -> SEGURO | SEGURO | Saída | DESPESAS ACESSÓRIAS
A6: 5 | B6: SÃO FRANCISCO DE PAULA - RS | C6: Saída | D6: GESTÃO LOCAL | E6: GESTÃO LOCAL | F6: MATERIAL | G6: Bebedouro | K6: 46092 | Q6: =IF(K6="","",K6) -> 46092 | R6: GESTÃO LOCAL | S6: Saída | GESTÃO LOCAL | T6: Saída | GESTÃO LOCAL | MATERIAL | V6: 257 | W6: Q1 | X6: 46090 | Y6: 46101 | Z6: 2500 | AA6: =IF(M6<>"",M6,Z6) -> 2500 | AB6: =IF(L6<>"","Realizado","Previsto") -> Previsto | AC6: 1 | AD6: 2500 | AF6: unidade | AG6: 2500 | AH6: C origem: MATERIAL | AI6: CUSTO CASA E CRONOGRAMA PAGAMEN | AJ6: =IF(Q6<>"",Q6,IF(K6<>"",K6,"")) -> 46092 | AK6: =IF(K6<>"","Sim","") -> Sim | AL6: =IF(A6="","",TEXT(A6,"000000")&"-"&IF(C6="Entrada","CR","DB")) -> 000005-DB | AM6: =IF(A6="","",LEFT(IF(H6<>"",H6,G6)&" | "&G6&" | "&S6,60)) -> Bebedouro | Bebedouro | Saída | GESTÃO LOCAL
A7: 6 | B7: SÃO FRANCISCO DE PAULA - RS | C7: Saída | D7: GESTÃO LOCAL | E7: GESTÃO LOCAL | F7: MATERIAL | G7: Placa da obra | K7: 46092 | Q7: =IF(K7="","",K7) -> 46092 | R7: GESTÃO LOCAL | S7: Saída | GESTÃO LOCAL | T7: Saída | GESTÃO LOCAL | MATERIAL | V7: 256 | W7: Q1 | X7: 46090 | Y7: 46101 | Z7: 2000 | AA7: =IF(M7<>"",M7,Z7) -> 2000 | AB7: =IF(L7<>"","Realizado","Previsto") -> Previsto | AC7: 1 | AD7: 2000 | AF7: unidade | AG7: 2000 | AH7: C origem: MATERIAL | AI7: CUSTO CASA E CRONOGRAMA PAGAMEN | AJ7: =IF(Q7<>"",Q7,IF(K7<>"",K7,"")) -> 46092 | AK7: =IF(K7<>"","Sim","") -> Sim | AL7: =IF(A7="","",TEXT(A7,"000000")&"-"&IF(C7="Entrada","CR","DB")) -> 000006-DB | AM7: =IF(A7="","",LEFT(IF(H7<>"",H7,G7)&" | "&G7&" | "&S7,60)) -> Placa da obra | Placa da obra | Saída | GESTÃO LOCAL
A8: 7 | B8: SÃO FRANCISCO DE PAULA - RS | C8: Saída | D8: GESTÃO LOCAL | E8: GESTÃO LOCAL | F8: ADMINISTRAÇAO | G8: TOPOGRAFO | K8: 46101 | Q8: =IF(K8="","",K8) -> 46101 | R8: GESTÃO LOCAL | S8: Saída | GESTÃO LOCAL | T8: Saída | GESTÃO LOCAL | ADMINISTRAÇAO | V8: 260 | W8: Q1 | X8: 46090 | Y8: 46101 | Z8: 6000 | AA8: =IF(M8<>"",M8,Z8) -> 6000 | AB8: =IF(L8<>"","Realizado","Previsto") -> Previsto | AC8: 1 | AD8: 6000 | AF8: mês | AG8: 2000 | AH8: C origem: ADMINISTRAÇAO | AI8: CUSTO CASA E CRONOGRAMA PAGAMEN | AJ8: =IF(Q8<>"",Q8,IF(K8<>"",K8,"")) -> 46101 | AK8: =IF(K8<>"","Sim","") -> Sim | AL8: =IF(A8="","",TEXT(A8,"000000")&"-"&IF(C8="Entrada","CR","DB")) -> 000007-DB | AM8: =IF(A8="","",LEFT(IF(H8<>"",H8,G8)&" | "&G8&" | "&S8,60)) -> TOPOGRAFO | TOPOGRAFO | Saída | GESTÃO LOCAL
A9: 8 | B9: SÃO FRANCISCO DE PAULA - RS | C9: Saída | D9: GESTÃO LOCAL | E9: GESTÃO LOCAL | F9: LOCAÇAO | G9: mobilização / desmobilzaçao containers | K9: 46101 | Q9: =IF(K9="","",K9) -> 46101 | R9: GESTÃO LOCAL | S9: Saída | GESTÃO LOCAL | T9: Saída | GESTÃO LOCAL | LOCAÇAO | V9: 253 | W9: Q1 | X9: 46090 | Y9: 46101 | Z9: 6100 | AA9: =IF(M9<>"",M9,Z9) -> 6100 | AB9: =IF(L9<>"","Realizado","Previsto") -> Previsto | AC9: 0.5 | AD9: 12200 | AF9: mês | AG9: 6100 | AH9: C origem: LOCAÇAO | AI9: CUSTO CASA E CRONOGRAMA PAGAMEN | AJ9: =IF(Q9<>"",Q9,IF(K9<>"",K9,"")) -> 46101 | AK9: =IF(K9<>"","Sim","") -> Sim | AL9: =IF(A9="","",TEXT(A9,"000000")&"-"&IF(C9="Entrada","CR","DB")) -> 000008-DB | AM9: =IF(A9="","",LEFT(IF(H9<>"",H9,G9)&" | "&G9&" | "&S9,60)) -> mobilização / desmobilzaçao containers | mobilização / desmo
A10: 9 | B10: SÃO FRANCISCO DE PAULA - RS | C10: Saída | D10: PAREDES (102,5m² de área interna e externa) (44,38² de Laje) | E10: PAREDES COM CONCRETO | F10: FABRICA | G10: contrato industrializaçao paredes | K10: 46101 | Q10: =IF(K10="","",K10) -> 46101 | R10: PAREDES (102,5m² de área interna e externa) (44,38² de Laje) | S10: Saída | PAREDES (102,5m² de área interna e externa) (44,38² de Laje) | T10: Saída | PAREDES COM CONCRETO | FABRICA | U10: 20 | V10: 48 | W10: Q1 | X10: 46090 | Y10: 46101 | Z10: 96000 | AA10: =IF(M10<>"",M10,Z10) -> 96000 | AB10: =IF(L10<>"","Realizado","Previsto") -> Previsto | AC10: 0.3 | AD10: 320000 | AE10: 20 | AF10: unidade | AG10: 16000 | AH10: B origem: PAREDES COM CONCRETO | C origem: FABRICA | AI10: CUSTO CASA E CRONOGRAMA PAGAMEN | AJ10: =IF(Q10<>"",Q10,IF(K10<>"",K10,"")) -> 46101 | AK10: =IF(K10<>"","Sim","") -> Sim | AL10: =IF(A10="","",TEXT(A10,"000000")&"-"&IF(C10="Entrada","CR","DB")) -> 000009-DB | AM10: =IF(A10="","",LEFT(IF(H10<>"",H10,G10)&" | "&G10&" | "&S10,60)) -> contrato industrializaçao paredes | contrato industrializaça
A11: 10 | B11: SÃO FRANCISCO DE PAULA - RS | C11: Saída | D11: PAREDES (102,5m² de área interna e externa) (44,38² de Laje) | E11: PAREDES COM CONCRETO | F11: FABRICA | G11: contrato industrializaçao paredes | K11: 46101 | Q11: =IF(K11="","",K11) -> 46101 | R11: PAREDES (102,5m² de área interna e externa) (44,38² de Laje) | S11: Saída | PAREDES (102,5m² de área interna e externa) (44,38² de Laje) | T11: Saída | PAREDES COM CONCRETO | FABRICA | U11: 20 | V11: 49 | W11: Q1 | X11: 46090 | Y11: 46101 | Z11: 96000 | AA11: =IF(M11<>"",M11,Z11) -> 96000 | AB11: =IF(L11<>"","Realizado","Previsto") -> Previsto | AC11: 0.3 | AD11: 320000 | AE11: 20 | AF11: unidade | AG11: 16000 | AH11: B origem: PAREDES COM CONCRETO | C origem: FABRICA | AI11: CUSTO CASA E CRONOGRAMA PAGAMEN | AJ11: =IF(Q11<>"",Q11,IF(K11<>"",K11,"")) -> 46101 | AK11: =IF(K11<>"","Sim","") -> Sim | AL11: =IF(A11="","",TEXT(A11,"000000")&"-"&IF(C11="Entrada","CR","DB")) -> 000010-DB | AM11: =IF(A11="","",LEFT(IF(H11<>"",H11,G11)&" | "&G11&" | "&S11,60)) -> contrato industrializaçao paredes | contrato industrializaça
A12: 11 | B12: SÃO FRANCISCO DE PAULA - RS | C12: Saída | D12: PAREDES (102,5m² de área interna e externa) (44,38² de Laje) | E12: PAREDES COM CONCRETO | F12: FABRICA | G12: contrato industrializaçao paredes | K12: 46101 | Q12: =IF(K12="","",K12) -> 46101 | R12: PAREDES (102,5m² de área interna e externa) (44,38² de Laje) | S12: Saída | PAREDES (102,5m² de área interna e externa) (44,38² de Laje) | T12: Saída | PAREDES COM CONCRETO | FABRICA | U12: 24 | V12: 50 | W12: Q1 | X12: 46090 | Y12: 46101 | Z12: 115200 | AA12: =IF(M12<>"",M12,Z12) -> 115200 | AB12: =IF(L12<>"","Realizado","Previsto") -> Previsto | AC12: 0.3 | AD12: 384000 | AE12: 24 | AF12: unidade | AG12: 16000 | AH12: B origem: PAREDES COM CONCRETO | C origem: FABRICA | AI12: CUSTO CASA E CRONOGRAMA PAGAMEN | AJ12: =IF(Q12<>"",Q12,IF(K12<>"",K12,"")) -> 46101 | AK12: =IF(K12<>"","Sim","") -> Sim | AL12: =IF(A12="","",TEXT(A12,"000000")&"-"&IF(C12="Entrada","CR","DB")) -> 000011-DB | AM12: =IF(A12="","",LEFT(IF(H12<>"",H12,G12)&" | "&G12&" | "&S12,60)) -> contrato industrializaçao paredes | contrato industrializaça
A13: 12 | B13: SÃO FRANCISCO DE PAULA - RS | C13: Saída | D13: RADIER - 44,38 M² | E13: RADIER | F13: MAO DE OBRA | G13: Mao de obra Terceirizada Radier | K13: 46101 | Q13: =IF(K13="","",K13) -> 46101 | R13: RADIER - 44,38 M² | S13: Saída | RADIER - 44,38 M² | T13: Saída | RADIER | MAO DE OBRA | V13: 43 | W13: Q1 | X13: 46090 | Y13: 46101 | Z13: 24750 | AA13: =IF(M13<>"",M13,Z13) -> 24750 | AB13: =IF(L13<>"","Realizado","Previsto") -> Previsto | AC13: 0.19335938 | AD13: 128000 | AE13: 64 | AF13: vb | AG13: 2000 | AH13: B origem: RADIER | C origem: MAO DE OBRA | AI13: CUSTO CASA E CRONOGRAMA PAGAMEN | AJ13: =IF(Q13<>"",Q13,IF(K13<>"",K13,"")) -> 46101 | AK13: =IF(K13<>"","Sim","") -> Sim | AL13: =IF(A13="","",TEXT(A13,"000000")&"-"&IF(C13="Entrada","CR","DB")) -> 000012-DB | AM13: =IF(A13="","",LEFT(IF(H13<>"",H13,G13)&" | "&G13&" | "&S13,60)) -> Mao de obra Terceirizada Radier | Mao de obra Terceirizada R
A14: 13 | B14: SÃO FRANCISCO DE PAULA - RS | C14: Saída | D14: RADIER - 44,38 M² | E14: RADIER | F14: MADEIRA | G14: ripas de 5cm x 2,7m de 25mm | K14: 46101 | Q14: =IF(K14="","",K14) -> 46101 | R14: RADIER - 44,38 M² | S14: Saída | RADIER - 44,38 M² | T14: Saída | RADIER | MADEIRA | V14: 44 | W14: Q1 | X14: 46090 | Y14: 46101 | Z14: 1689.6 | AA14: =IF(M14<>"",M14,Z14) -> 1689.6 | AB14: =IF(L14<>"","Realizado","Previsto") -> Previsto | AC14: 0.4 | AD14: 4224 | AE14: 704 | AF14: pç | AG14: 6 | AH14: B origem: RADIER | C origem: MADEIRA | AI14: CUSTO CASA E CRONOGRAMA PAGAMEN | AJ14: =IF(Q14<>"",Q14,IF(K14<>"",K14,"")) -> 46101 | AK14: =IF(K14<>"","Sim","") -> Sim | AL14: =IF(A14="","",TEXT(A14,"000000")&"-"&IF(C14="Entrada","CR","DB")) -> 000013-DB | AM14: =IF(A14="","",LEFT(IF(H14<>"",H14,G14)&" | "&G14&" | "&S14,60)) -> ripas de 5cm x 2,7m de 25mm | ripas de 5cm x 2,7m de 25mm |
A15: 14 | B15: SÃO FRANCISCO DE PAULA - RS | C15: Saída | D15: SERVIÇOS | E15: SERVIÇOS | F15: SERVIÇOS | G15: TOTALIZADOR CUSTO GLOBAIS OBRAS - MENSAL | K15: 46101 | Q15: =IF(K15="","",K15) -> 46101 | R15: SERVIÇOS | S15: Saída | SERVIÇOS | T15: Saída | SERVIÇOS | SERVIÇOS | V15: 267 | W15: Q1 | X15: 46090 | Y15: 46101 | Z15: 350239.6 | AA15: =IF(M15<>"",M15,Z15) -> 350239.6 | AB15: =IF(L15<>"","Realizado","Previsto") -> Previsto | AD15: 5780911.4 | AF15: mês | AI15: CUSTO CASA E CRONOGRAMA PAGAMEN | AJ15: =IF(Q15<>"",Q15,IF(K15<>"",K15,"")) -> 46101 | AK15: =IF(K15<>"","Sim","") -> Sim | AL15: =IF(A15="","",TEXT(A15,"000000")&"-"&IF(C15="Entrada","CR","DB")) -> 000014-DB | AM15: =IF(A15="","",LEFT(IF(H15<>"",H15,G15)&" | "&G15&" | "&S15,60)) -> TOTALIZADOR CUSTO GLOBAIS OBRAS - MENSAL | TOTALIZADOR CUSTO
A16: 15 | B16: SÃO FRANCISCO DE PAULA - RS | C16: Saída | D16: CAPITAL DE GIRO | E16: CAPITAL DE GIRO | F16: EMPRÉSTIMOS / CAPITAL DE GIRO | G16: ITAU | K16: 46115 | Q16: =IF(K16="","",K16) -> 46115 | R16: CAPITAL DE GIRO | S16: Saída | CAPITAL DE GIRO | T16: Saída | CAPITAL DE GIRO | EMPRÉSTIMOS / CAPITAL DE GIRO | V16: 273 | W16: Q2 | X16: 46104 | Y16: 46115 | Z16: 19943.37 | AA16: =IF(M16<>"",M16,Z16) -> 19943.37 | AB16: =IF(L16<>"","Realizado","Previsto") -> Previsto | AD16: 307830.11 | AG16: 248 | AH16: C origem: 248000 | AI16: CUSTO CASA E CRONOGRAMA PAGAMEN | AJ16: =IF(Q16<>"",Q16,IF(K16<>"",K16,"")) -> 46115 | AK16: =IF(K16<>"","Sim","") -> Sim | AL16: =IF(A16="","",TEXT(A16,"000000")&"-"&IF(C16="Entrada","CR","DB")) -> 000015-DB | AM16: =IF(A16="","",LEFT(IF(H16<>"",H16,G16)&" | "&G16&" | "&S16,60)) -> ITAU | ITAU | Saída | CAPITAL DE GIRO
A17: 16 | B17: SÃO FRANCISCO DE PAULA - RS | C17: Saída | D17: ESPERAS DE ESGOTO RADIER | E17: ESPERAS DE ESGOTO RADIER | F17: Tubos e conexoes | G17: Anel de vedação esg 100 mm | K17: 46115 | Q17: =IF(K17="","",K17) -> 46115 | R17: ESPERAS DE ESGOTO RADIER | S17: Saída | ESPERAS DE ESGOTO RADIER | T17: Saída | ESPERAS DE ESGOTO RADIER | Tubos e conexoes | V17: 21 | W17: Q2 | X17: 46104 | Y17: 46115 | Z17: 47.872 | AA17: =IF(M17<>"",M17,Z17) -> 47.872 | AB17: =IF(L17<>"","Realizado","Previsto") -> Previsto | AC17: 0.34 | AD17: 140.8 | AE17: 64 | AF17: unidade | AG17: 2.2 | AH17: B origem: ESPERAS DE ESGOTO RADIER | C origem: Tubos e conexoes | AI17: CUSTO CASA E CRONOGRAMA PAGAMEN | AJ17: =IF(Q17<>"",Q17,IF(K17<>"",K17,"")) -> 46115 | AK17: =IF(K17<>"","Sim","") -> Sim | AL17: =IF(A17="","",TEXT(A17,"000000")&"-"&IF(C17="Entrada","CR","DB")) -> 000016-DB | AM17: =IF(A17="","",LEFT(IF(H17<>"",H17,G17)&" | "&G17&" | "&S17,60)) -> Anel de vedação esg 100 mm | Anel de vedação esg 100 mm | Sa
A18: 17 | B18: SÃO FRANCISCO DE PAULA - RS | C18: Saída | D18: ESPERAS DE ESGOTO RADIER | E18: ESPERAS DE ESGOTO RADIER | F18: Tubos e conexoes | G18: Caixa Sifonada com grelha quadrada PVC DN 150x150x50 com junta soldável para ramal de esgoto sanitário | K18: 46115 | Q18: =IF(K18="","",K18) -> 46115 | R18: ESPERAS DE ESGOTO RADIER | S18: Saída | ESPERAS DE ESGOTO RADIER | T18: Saída | ESPERAS DE ESGOTO RADIER | Tubos e conexoes | V18: 19 | W18: Q2 | X18: 46104 | Y18: 46115 | Z18: 696.32 | AA18: =IF(M18<>"",M18,Z18) -> 696.32 | AB18: =IF(L18<>"","Realizado","Previsto") -> Previsto | AC18: 0.34 | AD18: 2048 | AE18: 64 | AF18: unidade | AG18: 32 | AH18: B origem: ESPERAS DE ESGOTO RADIER | C origem: Tubos e conexoes | AI18: CUSTO CASA E CRONOGRAMA PAGAMEN | AJ18: =IF(Q18<>"",Q18,IF(K18<>"",K18,"")) -> 46115 | AK18: =IF(K18<>"","Sim","") -> Sim | AL18: =IF(A18="","",TEXT(A18,"000000")&"-"&IF(C18="Entrada","CR","DB")) -> 000017-DB | AM18: =IF(A18="","",LEFT(IF(H18<>"",H18,G18)&" | "&G18&" | "&S18,60)) -> Caixa Sifonada com grelha quadrada PVC DN 150x150x50 com jun
A19: 18 | B19: SÃO FRANCISCO DE PAULA - RS | C19: Saída | D19: ESPERAS DE ESGOTO RADIER | E19: ESPERAS DE ESGOTO RADIER | F19: Tubos e conexoes | G19: Cola de cano PVC 175g | K19: 46115 | Q19: =IF(K19="","",K19) -> 46115 | R19: ESPERAS DE ESGOTO RADIER | S19: Saída | ESPERAS DE ESGOTO RADIER | T19: Saída | ESPERAS DE ESGOTO RADIER | Tubos e conexoes | V19: 24 | W19: Q2 | X19: 46104 | Y19: 46115 | Z19: 304.4224 | AA19: =IF(M19<>"",M19,Z19) -> 304.4224 | AB19: =IF(L19<>"","Realizado","Previsto") -> Previsto | AC19: 0.34 | AD19: 895.36 | AE19: 64 | AF19: unidade | AG19: 13.99 | AH19: B origem: ESPERAS DE ESGOTO RADIER | C origem: Tubos e conexoes | AI19: CUSTO CASA E CRONOGRAMA PAGAMEN | AJ19: =IF(Q19<>"",Q19,IF(K19<>"",K19,"")) -> 46115 | AK19: =IF(K19<>"","Sim","") -> Sim | AL19: =IF(A19="","",TEXT(A19,"000000")&"-"&IF(C19="Entrada","CR","DB")) -> 000018-DB | AM19: =IF(A19="","",LEFT(IF(H19<>"",H19,G19)&" | "&G19&" | "&S19,60)) -> Cola de cano PVC 175g | Cola de cano PVC 175g | Saída | ESPE
A20: 19 | B20: SÃO FRANCISCO DE PAULA - RS | C20: Saída | D20: ESPERAS DE ESGOTO RADIER | E20: ESPERAS DE ESGOTO RADIER | F20: Tubos e conexoes | G20: Joelho 45º PVC DN 40mm branco rígido para esgoto sanitário predial | K20: 46115 | Q20: =IF(K20="","",K20) -> 46115 | R20: ESPERAS DE ESGOTO RADIER | S20: Saída | ESPERAS DE ESGOTO RADIER | T20: Saída | ESPERAS DE ESGOTO RADIER | Tubos e conexoes | V20: 13 | W20: Q2 | X20: 46104 | Y20: 46115 | Z20: 30.464 | AA20: =IF(M20<>"",M20,Z20) -> 30.464 | AB20: =IF(L20<>"","Realizado","Previsto") -> Previsto | AC20: 0.34 | AD20: 89.6 | AE20: 64 | AF20: unidade | AG20: 1.4 | AH20: B origem: ESPERAS DE ESGOTO RADIER | C origem: Tubos e conexoes | AI20: CUSTO CASA E CRONOGRAMA PAGAMEN | AJ20: =IF(Q20<>"",Q20,IF(K20<>"",K20,"")) -> 46115 | AK20: =IF(K20<>"","Sim","") -> Sim | AL20: =IF(A20="","",TEXT(A20,"000000")&"-"&IF(C20="Entrada","CR","DB")) -> 000019-DB | AM20: =IF(A20="","",LEFT(IF(H20<>"",H20,G20)&" | "&G20&" | "&S20,60)) -> Joelho 45º PVC DN 40mm branco rígido para esgoto sanitário p
A21: 20 | B21: SÃO FRANCISCO DE PAULA - RS | C21: Saída | D21: ESPERAS DE ESGOTO RADIER | E21: ESPERAS DE ESGOTO RADIER | F21: Tubos e conexoes | G21: Joelho 45º PVC DN 50mm branco rígido para esgoto sanitário predial | K21: 46115 | Q21: =IF(K21="","",K21) -> 46115 | R21: ESPERAS DE ESGOTO RADIER | S21: Saída | ESPERAS DE ESGOTO RADIER | T21: Saída | ESPERAS DE ESGOTO RADIER | Tubos e conexoes | V21: 15 | W21: Q2 | X21: 46104 | Y21: 46115 | Z21: 130.56 | AA21: =IF(M21<>"",M21,Z21) -> 130.56 | AB21: =IF(L21<>"","Realizado","Previsto") -> Previsto | AC21: 0.34 | AD21: 384 | AE21: 64 | AF21: unidade | AG21: 6 | AH21: B origem: ESPERAS DE ESGOTO RADIER | C origem: Tubos e conexoes | AI21: CUSTO CASA E CRONOGRAMA PAGAMEN | AJ21: =IF(Q21<>"",Q21,IF(K21<>"",K21,"")) -> 46115 | AK21: =IF(K21<>"","Sim","") -> Sim | AL21: =IF(A21="","",TEXT(A21,"000000")&"-"&IF(C21="Entrada","CR","DB")) -> 000020-DB | AM21: =IF(A21="","",LEFT(IF(H21<>"",H21,G21)&" | "&G21&" | "&S21,60)) -> Joelho 45º PVC DN 50mm branco rígido para esgoto sanitário p
A22: 21 | B22: SÃO FRANCISCO DE PAULA - RS | C22: Saída | D22: ESPERAS DE ESGOTO RADIER | E22: ESPERAS DE ESGOTO RADIER | F22: Tubos e conexoes | G22: Joelho 90º PVC DN 100mm branco rígido para esgoto sanitário predial | K22: 46115 | Q22: =IF(K22="","",K22) -> 46115 | R22: ESPERAS DE ESGOTO RADIER | S22: Saída | ESPERAS DE ESGOTO RADIER | T22: Saída | ESPERAS DE ESGOTO RADIER | Tubos e conexoes | V22: 11 | W22: Q2 | X22: 46104 | Y22: 46115 | Z22: 304.4224 | AA22: =IF(M22<>"",M22,Z22) -> 304.4224 | AB22: =IF(L22<>"","Realizado","Previsto") -> Previsto | AC22: 0.34 | AD22: 895.36 | AE22: 64 | AF22: unidade | AG22: 13.99 | AH22: B origem: ESPERAS DE ESGOTO RADIER | C origem: Tubos e conexoes | AI22: CUSTO CASA E CRONOGRAMA PAGAMEN | AJ22: =IF(Q22<>"",Q22,IF(K22<>"",K22,"")) -> 46115 | AK22: =IF(K22<>"","Sim","") -> Sim | AL22: =IF(A22="","",TEXT(A22,"000000")&"-"&IF(C22="Entrada","CR","DB")) -> 000021-DB | AM22: =IF(A22="","",LEFT(IF(H22<>"",H22,G22)&" | "&G22&" | "&S22,60)) -> Joelho 90º PVC DN 100mm branco rígido para esgoto sanitário
A23: 22 | B23: SÃO FRANCISCO DE PAULA - RS | C23: Saída | D23: ESPERAS DE ESGOTO RADIER | E23: ESPERAS DE ESGOTO RADIER | F23: Tubos e conexoes | G23: Joelho 90º PVC DN 40mm branco rígido para esgoto sanitário predial | K23: 46115 | Q23: =IF(K23="","",K23) -> 46115 | R23: ESPERAS DE ESGOTO RADIER | S23: Saída | ESPERAS DE ESGOTO RADIER | T23: Saída | ESPERAS DE ESGOTO RADIER | Tubos e conexoes | V23: 12 | W23: Q2 | X23: 46104 | Y23: 46115 | Z23: 134.4768 | AA23: =IF(M23<>"",M23,Z23) -> 134.4768 | AB23: =IF(L23<>"","Realizado","Previsto") -> Previsto | AC23: 0.34 | AD23: 395.52 | AE23: 128 | AF23: unidade | AG23: 3.09 | AH23: B origem: ESPERAS DE ESGOTO RADIER | C origem: Tubos e conexoes | AI23: CUSTO CASA E CRONOGRAMA PAGAMEN | AJ23: =IF(Q23<>"",Q23,IF(K23<>"",K23,"")) -> 46115 | AK23: =IF(K23<>"","Sim","") -> Sim | AL23: =IF(A23="","",TEXT(A23,"000000")&"-"&IF(C23="Entrada","CR","DB")) -> 000022-DB | AM23: =IF(A23="","",LEFT(IF(H23<>"",H23,G23)&" | "&G23&" | "&S23,60)) -> Joelho 90º PVC DN 40mm branco rígido para esgoto sanitário p
A24: 23 | B24: SÃO FRANCISCO DE PAULA - RS | C24: Saída | D24: ESPERAS DE ESGOTO RADIER | E24: ESPERAS DE ESGOTO RADIER | F24: Tubos e conexoes | G24: Joelho 90º PVC DN 50mm branco junta elástica para esgoto sanitário | K24: 46115 | Q24: =IF(K24="","",K24) -> 46115 | R24: ESPERAS DE ESGOTO RADIER | S24: Saída | ESPERAS DE ESGOTO RADIER | T24: Saída | ESPERAS DE ESGOTO RADIER | Tubos e conexoes | V24: 14 | W24: Q2 | X24: 46104 | Y24: 46115 | Z24: 746.8032 | AA24: =IF(M24<>"",M24,Z24) -> 746.8032 | AB24: =IF(L24<>"","Realizado","Previsto") -> Previsto | AC24: 0.34 | AD24: 2196.48 | AE24: 384 | AF24: unidade | AG24: 5.72 | AH24: B origem: ESPERAS DE ESGOTO RADIER | C origem: Tubos e conexoes | AI24: CUSTO CASA E CRONOGRAMA PAGAMEN | AJ24: =IF(Q24<>"",Q24,IF(K24<>"",K24,"")) -> 46115 | AK24: =IF(K24<>"","Sim","") -> Sim | AL24: =IF(A24="","",TEXT(A24,"000000")&"-"&IF(C24="Entrada","CR","DB")) -> 000023-DB | AM24: =IF(A24="","",LEFT(IF(H24<>"",H24,G24)&" | "&G24&" | "&S24,60)) -> Joelho 90º PVC DN 50mm branco junta elástica para esgoto san
A25: 24 | B25: SÃO FRANCISCO DE PAULA - RS | C25: Saída | D25: ESPERAS DE ESGOTO RADIER | E25: ESPERAS DE ESGOTO RADIER | F25: Tubos e conexoes | G25: Joelho 90º marrom DN 25mm soldável para água fria | K25: 46115 | Q25: =IF(K25="","",K25) -> 46115 | R25: ESPERAS DE ESGOTO RADIER | S25: Saída | ESPERAS DE ESGOTO RADIER | T25: Saída | ESPERAS DE ESGOTO RADIER | Tubos e conexoes | V25: 25 | W25: Q2 | X25: 46104 | Y25: 46115 | Z25: 41.344 | AA25: =IF(M25<>"",M25,Z25) -> 41.344 | AB25: =IF(L25<>"","Realizado","Previsto") -> Previsto | AC25: 0.34 | AD25: 121.6 | AE25: 128 | AF25: unidade | AG25: 0.95 | AH25: B origem: ESPERAS DE ESGOTO RADIER | C origem: Tubos e conexoes | AI25: CUSTO CASA E CRONOGRAMA PAGAMEN | AJ25: =IF(Q25<>"",Q25,IF(K25<>"",K25,"")) -> 46115 | AK25: =IF(K25<>"","Sim","") -> Sim | AL25: =IF(A25="","",TEXT(A25,"000000")&"-"&IF(C25="Entrada","CR","DB")) -> 000024-DB | AM25: =IF(A25="","",LEFT(IF(H25<>"",H25,G25)&" | "&G25&" | "&S25,60)) -> Joelho 90º marrom DN 25mm soldável para água fria | Joelho 9
A26: 25 | B26: SÃO FRANCISCO DE PAULA - RS | C26: Saída | D26: ESPERAS DE ESGOTO RADIER | E26: ESPERAS DE ESGOTO RADIER | F26: Tubos e conexoes | G26: Junção de Redução invertica PVC DN 100x50mm branco rígido para esgoto sanitário predial | K26: 46115 | Q26: =IF(K26="","",K26) -> 46115 | R26: ESPERAS DE ESGOTO RADIER | S26: Saída | ESPERAS DE ESGOTO RADIER | T26: Saída | ESPERAS DE ESGOTO RADIER | Tubos e conexoes | V26: 17 | W26: Q2 | X26: 46104 | Y26: 46115 | Z26: 469.1456 | AA26: =IF(M26<>"",M26,Z26) -> 469.1456 | AB26: =IF(L26<>"","Realizado","Previsto") -> Previsto | AC26: 0.34 | AD26: 1379.84 | AE26: 64 | AF26: unidade | AG26: 21.56 | AH26: B origem: ESPERAS DE ESGOTO RADIER | C origem: Tubos e conexoes | AI26: CUSTO CASA E CRONOGRAMA PAGAMEN | AJ26: =IF(Q26<>"",Q26,IF(K26<>"",K26,"")) -> 46115 | AK26: =IF(K26<>"","Sim","") -> Sim | AL26: =IF(A26="","",TEXT(A26,"000000")&"-"&IF(C26="Entrada","CR","DB")) -> 000025-DB | AM26: =IF(A26="","",LEFT(IF(H26<>"",H26,G26)&" | "&G26&" | "&S26,60)) -> Junção de Redução invertica PVC DN 100x50mm branco rígido pa
A27: 26 | B27: SÃO FRANCISCO DE PAULA - RS | C27: Saída | D27: ESPERAS DE ESGOTO RADIER | E27: ESPERAS DE ESGOTO RADIER | F27: Tubos e conexoes | G27: Junção simples PVC DN 50x50mm branco rígido para esgoto sanitário predial | K27: 46115 | Q27: =IF(K27="","",K27) -> 46115 | R27: ESPERAS DE ESGOTO RADIER | S27: Saída | ESPERAS DE ESGOTO RADIER | T27: Saída | ESPERAS DE ESGOTO RADIER | Tubos e conexoes | V27: 16 | W27: Q2 | X27: 46104 | Y27: 46115 | Z27: 391.2448 | AA27: =IF(M27<>"",M27,Z27) -> 391.2448 | AB27: =IF(L27<>"","Realizado","Previsto") -> Previsto | AC27: 0.34 | AD27: 1150.72 | AE27: 64 | AF27: unidade | AG27: 17.98 | AH27: B origem: ESPERAS DE ESGOTO RADIER | C origem: Tubos e conexoes | AI27: CUSTO CASA E CRONOGRAMA PAGAMEN | AJ27: =IF(Q27<>"",Q27,IF(K27<>"",K27,"")) -> 46115 | AK27: =IF(K27<>"","Sim","") -> Sim | AL27: =IF(A27="","",TEXT(A27,"000000")&"-"&IF(C27="Entrada","CR","DB")) -> 000026-DB | AM27: =IF(A27="","",LEFT(IF(H27<>"",H27,G27)&" | "&G27&" | "&S27,60)) -> Junção simples PVC DN 50x50mm branco rígido para esgoto sani
A28: 27 | B28: SÃO FRANCISCO DE PAULA - RS | C28: Saída | D28: ESPERAS DE ESGOTO RADIER | E28: ESPERAS DE ESGOTO RADIER | F28: Tubos e conexoes | G28: Lixa ferro p/cano pvc 100 | K28: 46115 | Q28: =IF(K28="","",K28) -> 46115 | R28: ESPERAS DE ESGOTO RADIER | S28: Saída | ESPERAS DE ESGOTO RADIER | T28: Saída | ESPERAS DE ESGOTO RADIER | Tubos e conexoes | V28: 22 | W28: Q2 | X28: 46104 | Y28: 46115 | Z28: 36.7744 | AA28: =IF(M28<>"",M28,Z28) -> 36.7744 | AB28: =IF(L28<>"","Realizado","Previsto") -> Previsto | AC28: 0.34 | AD28: 108.16 | AE28: 64 | AF28: unidade | AG28: 1.69 | AH28: B origem: ESPERAS DE ESGOTO RADIER | C origem: Tubos e conexoes | AI28: CUSTO CASA E CRONOGRAMA PAGAMEN | AJ28: =IF(Q28<>"",Q28,IF(K28<>"",K28,"")) -> 46115 | AK28: =IF(K28<>"","Sim","") -> Sim | AL28: =IF(A28="","",TEXT(A28,"000000")&"-"&IF(C28="Entrada","CR","DB")) -> 000027-DB | AM28: =IF(A28="","",LEFT(IF(H28<>"",H28,G28)&" | "&G28&" | "&S28,60)) -> Lixa ferro p/cano pvc 100 | Lixa ferro p/cano pvc 100 | Saíd
... A36: 35 | B36: SÃO FRANCISCO DE PAULA - RS | C36: Saída | D36: ESPERAS DE ESGOTO RADIER | E36: ESPERAS DE ESGOTO RADIER | F36: Tubos e conexoes | G36: Tubo PVC DN 75mm branco rígido para esgoto sanitário | K36: 46115 | Q36: =IF(K36="","",K36) -> 46115 | R36: ESPERAS DE ESGOTO RADIER | S36: Saída | ESPERAS DE ESGOTO RADIER | T36: Saída | ESPERAS DE ESGOTO RADIER | Tubos e conexoes | V36: 9 | W36: Q2 | X36: 46104 | Y36: 46115 | Z36: 82.40512 | AA36: =IF(M36<>"",M36,Z36) -> 82.40512 | AB36: =IF(L36<>"","Realizado","Previsto") -> Previsto | AC36: 0.34 | AD36: 242.368 | AE36: 22.4 | AF36: m | AG36: 10.82 | AH36: B origem: ESPERAS DE ESGOTO RADIER | C origem: Tubos e conexoes | AI36: CUSTO CASA E CRONOGRAMA PAGAMEN | AJ36: =IF(Q36<>"",Q36,IF(K36<>"",K36,"")) -> 46115 | AK36: =IF(K36<>"","Sim","") -> Sim | AL36: =IF(A36="","",TEXT(A36,"000000")&"-"&IF(C36="Entrada","CR","DB")) -> 000035-DB | AM36: =IF(A36="","",LEFT(IF(H36<>"",H36,G36)&" | "&G36&" | "&S36,60)) -> Tubo PVC DN 75mm branco rígido para esgoto sanitário | Tubo
A37: 36 | B37: SÃO FRANCISCO DE PAULA - RS | C37: Saída | D37: GESTÃO LOCAL | E37: GESTÃO LOCAL | F37: ADMINISTRAÇAO | G37: ALMOXARIFADO | K37: 46115 | Q37: =IF(K37="","",K37) -> 46115 | R37: GESTÃO LOCAL | S37: Saída | GESTÃO LOCAL | T37: Saída | GESTÃO LOCAL | ADMINISTRAÇAO | V37: 264 | W37: Q2 | X37: 46104 | Y37: 46115 | Z37: 7500 | AA37: =IF(M37<>"",M37,Z37) -> 7500 | AB37: =IF(L37<>"","Realizado","Previsto") -> Previsto | AC37: 0.25 | AD37: 30000 | AG37: 7500 | AH37: C origem: ADMINISTRAÇAO | AI37: CUSTO CASA E CRONOGRAMA PAGAMEN | AJ37: =IF(Q37<>"",Q37,IF(K37<>"",K37,"")) -> 46115 | AK37: =IF(K37<>"","Sim","") -> Sim | AL37: =IF(A37="","",TEXT(A37,"000000")&"-"&IF(C37="Entrada","CR","DB")) -> 000036-DB | AM37: =IF(A37="","",LEFT(IF(H37<>"",H37,G37)&" | "&G37&" | "&S37,60)) -> ALMOXARIFADO | ALMOXARIFADO | Saída | GESTÃO LOCAL
A38: 37 | B38: SÃO FRANCISCO DE PAULA - RS | C38: Saída | D38: GESTÃO LOCAL | E38: GESTÃO LOCAL | F38: ADMINISTRAÇAO | G38: Alojamento Arbnb (mestre, engenheiro. Tecnico) | K38: 46115 | Q38: =IF(K38="","",K38) -> 46115 | R38: GESTÃO LOCAL | S38: Saída | GESTÃO LOCAL | T38: Saída | GESTÃO LOCAL | ADMINISTRAÇAO | V38: 265 | W38: Q2 | X38: 46104 | Y38: 46115 | Z38: 3500 | AA38: =IF(M38<>"",M38,Z38) -> 3500 | AB38: =IF(L38<>"","Realizado","Previsto") -> Previsto | AC38: 0.25 | AD38: 14000 | AF38: mês | AG38: 3500 | AH38: C origem: ADMINISTRAÇAO | AI38: CUSTO CASA E CRONOGRAMA PAGAMEN | AJ38: =IF(Q38<>"",Q38,IF(K38<>"",K38,"")) -> 46115 | AK38: =IF(K38<>"","Sim","") -> Sim | AL38: =IF(A38="","",TEXT(A38,"000000")&"-"&IF(C38="Entrada","CR","DB")) -> 000037-DB | AM38: =IF(A38="","",LEFT(IF(H38<>"",H38,G38)&" | "&G38&" | "&S38,60)) -> Alojamento Arbnb (mestre, engenheiro. Tecnico) | Alojamento
A39: 38 | B39: SÃO FRANCISCO DE PAULA - RS | C39: Saída | D39: GESTÃO LOCAL | E39: GESTÃO LOCAL | F39: LOCAÇAO | G39: Aluguel container Banheiro | K39: 46115 | Q39: =IF(K39="","",K39) -> 46115 | R39: GESTÃO LOCAL | S39: Saída | GESTÃO LOCAL | T39: Saída | GESTÃO LOCAL | LOCAÇAO | V39: 252 | W39: Q2 | X39: 46104 | Y39: 46115 | Z39: 1140 | AA39: =IF(M39<>"",M39,Z39) -> 1140 | AB39: =IF(L39<>"","Realizado","Previsto") -> Previsto | AC39: 0.25 | AD39: 4560 | AF39: mês | AG39: 1140 | AH39: C origem: LOCAÇAO | AI39: CUSTO CASA E CRONOGRAMA PAGAMEN | AJ39: =IF(Q39<>"",Q39,IF(K39<>"",K39,"")) -> 46115 | AK39: =IF(K39<>"","Sim","") -> Sim | AL39: =IF(A39="","",TEXT(A39,"000000")&"-"&IF(C39="Entrada","CR","DB")) -> 000038-DB | AM39: =IF(A39="","",LEFT(IF(H39<>"",H39,G39)&" | "&G39&" | "&S39,60)) -> Aluguel container Banheiro | Aluguel container Banheiro | Sa
A40: 39 | B40: SÃO FRANCISCO DE PAULA - RS | C40: Saída | D40: GESTÃO LOCAL | E40: GESTÃO LOCAL | F40: LOCAÇAO | G40: Aluguel container almoxarifado | K40: 46115 | Q40: =IF(K40="","",K40) -> 46115 | R40: GESTÃO LOCAL | S40: Saída | GESTÃO LOCAL | T40: Saída | GESTÃO LOCAL | LOCAÇAO | V40: 254 | W40: Q2 | X40: 46104 | Y40: 46115 | Z40: 400 | AA40: =IF(M40<>"",M40,Z40) -> 400 | AB40: =IF(L40<>"","Realizado","Previsto") -> Previsto | AC40: 0.25 | AD40: 1600 | AF40: mês | AG40: 400 | AH40: C origem: LOCAÇAO | AI40: CUSTO CASA E CRONOGRAMA PAGAMEN | AJ40: =IF(Q40<>"",Q40,IF(K40<>"",K40,"")) -> 46115 | AK40: =IF(K40<>"","Sim","") -> Sim | AL40: =IF(A40="","",TEXT(A40,"000000")&"-"&IF(C40="Entrada","CR","DB")) -> 000039-DB | AM40: =IF(A40="","",LEFT(IF(H40<>"",H40,G40)&" | "&G40&" | "&S40,60)) -> Aluguel container almoxarifado | Aluguel container almoxarif
A41: 40 | B41: SÃO FRANCISCO DE PAULA - RS | C41: Saída | D41: GESTÃO LOCAL | E41: GESTÃO LOCAL | F41: LOCAÇAO | G41: Aluguel container escritorio | K41: 46115 | Q41: =IF(K41="","",K41) -> 46115 | R41: GESTÃO LOCAL | S41: Saída | GESTÃO LOCAL | T41: Saída | GESTÃO LOCAL | LOCAÇAO | V41: 255 | W41: Q2 | X41: 46104 | Y41: 46115 | Z41: 900 | AA41: =IF(M41<>"",M41,Z41) -> 900 | AB41: =IF(L41<>"","Realizado","Previsto") -> Previsto | AC41: 0.25 | AD41: 3600 | AF41: mês | AG41: 900 | AH41: C origem: LOCAÇAO | AI41: CUSTO CASA E CRONOGRAMA PAGAMEN | AJ41: =IF(Q41<>"",Q41,IF(K41<>"",K41,"")) -> 46115 | AK41: =IF(K41<>"","Sim","") -> Sim | AL41: =IF(A41="","",TEXT(A41,"000000")&"-"&IF(C41="Entrada","CR","DB")) -> 000040-DB | AM41: =IF(A41="","",LEFT(IF(H41<>"",H41,G41)&" | "&G41&" | "&S41,60)) -> Aluguel container escritorio | Aluguel container escritorio
A42: 41 | B42: SÃO FRANCISCO DE PAULA - RS | C42: Saída | D42: GESTÃO LOCAL | E42: GESTÃO LOCAL | F42: ADMINISTRAÇAO | G42: COMPRADOR | K42: 46115 | Q42: =IF(K42="","",K42) -> 46115 | R42: GESTÃO LOCAL | S42: Saída | GESTÃO LOCAL | T42: Saída | GESTÃO LOCAL | ADMINISTRAÇAO | U42: pra obra de 50 casa considera apenas encarregado | V42: 262 | W42: Q2 | X42: 46104 | Y42: 46115 | Z42: 3000 | AA42: =IF(M42<>"",M42,Z42) -> 3000 | AB42: =IF(L42<>"","Realizado","Previsto") -> Previsto | AC42: 0.25 | AD42: 12000 | AF42: mês | AG42: 3000 | AH42: C origem: ADMINISTRAÇAO | AI42: CUSTO CASA E CRONOGRAMA PAGAMEN | AJ42: =IF(Q42<>"",Q42,IF(K42<>"",K42,"")) -> 46115 | AK42: =IF(K42<>"","Sim","") -> Sim | AL42: =IF(A42="","",TEXT(A42,"000000")&"-"&IF(C42="Entrada","CR","DB")) -> 000041-DB | AM42: =IF(A42="","",LEFT(IF(H42<>"",H42,G42)&" | "&G42&" | "&S42,60)) -> COMPRADOR | COMPRADOR | Saída | GESTÃO LOCAL
A43: 42 | B43: SÃO FRANCISCO DE PAULA - RS | C43: Saída | D43: GESTÃO LOCAL | E43: GESTÃO LOCAL | F43: ADMINISTRAÇAO | G43: ENGENHEIRO RESIDENTE - ( rateado em 3 canteiros) carro incluso | K43: 46115 | Q43: =IF(K43="","",K43) -> 46115 | R43: GESTÃO LOCAL | S43: Saída | GESTÃO LOCAL | T43: Saída | GESTÃO LOCAL | ADMINISTRAÇAO | V43: 259 | W43: Q2 | X43: 46104 | Y43: 46115 | Z43: 10000 | AA43: =IF(M43<>"",M43,Z43) -> 10000 | AB43: =IF(L43<>"","Realizado","Previsto") -> Previsto | AC43: 0.25 | AD43: 40000 | AF43: mês | AG43: 10000 | AH43: C origem: ADMINISTRAÇAO | AI43: CUSTO CASA E CRONOGRAMA PAGAMEN | AJ43: =IF(Q43<>"",Q43,IF(K43<>"",K43,"")) -> 46115 | AK43: =IF(K43<>"","Sim","") -> Sim | AL43: =IF(A43="","",TEXT(A43,"000000")&"-"&IF(C43="Entrada","CR","DB")) -> 000042-DB | AM43: =IF(A43="","",LEFT(IF(H43<>"",H43,G43)&" | "&G43&" | "&S43,60)) -> ENGENHEIRO RESIDENTE - ( rateado em 3 canteiros) carro inclu
A44: 43 | B44: SÃO FRANCISCO DE PAULA - RS | C44: Saída | D44: RADIER - 44,38 M² | E44: RADIER | F44: FERRAGEM | G44: Arame Recozido bwg 18 | K44: 46115 | Q44: =IF(K44="","",K44) -> 46115 | R44: RADIER - 44,38 M² | S44: Saída | RADIER - 44,38 M² | T44: Saída | RADIER | FERRAGEM | V44: 36 | W44: Q2 | X44: 46104 | Y44: 46115 | Z44: 192 | AA44: =IF(M44<>"",M44,Z44) -> 192 | AB44: =IF(L44<>"","Realizado","Previsto") -> Previsto | AC44: 0.5 | AD44: 384 | AE44: 32 | AF44: kg | AG44: 12 | AH44: B origem: RADIER | C origem: FERRAGEM | AI44: CUSTO CASA E CRONOGRAMA PAGAMEN | AJ44: =IF(Q44<>"",Q44,IF(K44<>"",K44,"")) -> 46115 | AK44: =IF(K44<>"","Sim","") -> Sim | AL44: =IF(A44="","",TEXT(A44,"000000")&"-"&IF(C44="Entrada","CR","DB")) -> 000043-DB | AM44: =IF(A44="","",LEFT(IF(H44<>"",H44,G44)&" | "&G44&" | "&S44,60)) -> Arame Recozido bwg 18 | Arame Recozido bwg 18 | Saída | RADI
A45: 44 | B45: SÃO FRANCISCO DE PAULA - RS | C45: Saída | D45: RADIER - 44,38 M² | E45: RADIER | F45: FERRAGEM | G45: Aço - Tela Q-138 - 5.0 c/10 - (245 x 600 cm) (frete de 300 + ipi de 133 incluido | K45: 46115 | Q45: =IF(K45="","",K45) -> 46115 | R45: RADIER - 44,38 M² | S45: Saída | RADIER - 44,38 M² | T45: Saída | RADIER | FERRAGEM | V45: 34 | W45: Q2 | X45: 46104 | Y45: 46115 | Z45: 40821.76 | AA45: =IF(M45<>"",M45,Z45) -> 40821.76 | AB45: =IF(L45<>"","Realizado","Previsto") -> Previsto | AC45: 0.34 | AD45: 120064 | AE45: 512 | AF45: telas | AG45: 234.5 | AH45: B origem: RADIER | C origem: FERRAGEM | AI45: CUSTO CASA E CRONOGRAMA PAGAMEN | AJ45: =IF(Q45<>"",Q45,IF(K45<>"",K45,"")) -> 46115 | AK45: =IF(K45<>"","Sim","") -> Sim | AL45: =IF(A45="","",TEXT(A45,"000000")&"-"&IF(C45="Entrada","CR","DB")) -> 000044-DB | AM45: =IF(A45="","",LEFT(IF(H45<>"",H45,G45)&" | "&G45&" | "&S45,60)) -> Aço - Tela Q-138 - 5.0 c/10 - (245 x 600 cm) (frete de 300
A46: 45 | B46: SÃO FRANCISCO DE PAULA - RS | C46: Saída | D46: RADIER - 44,38 M² | E46: RADIER | F46: CONCRETO | G46: Bomba de concreto ( Taxa divide 1 casa e 1 radier ) | K46: 46115 | Q46: =IF(K46="","",K46) -> 46115 | R46: RADIER - 44,38 M² | S46: Saída | RADIER - 44,38 M² | T46: Saída | RADIER | CONCRETO | U46: 21 DIAS: uma diaria de bomba faz 3 radies por dia | V46: 30 | W46: Q2 | X46: 46104 | Y46: 46115 | Z46: 4400 | AA46: =IF(M46<>"",M46,Z46) -> 4400 | AB46: =IF(L46<>"","Realizado","Previsto") -> Previsto | AC46: 0.25 | AD46: 17600 | AE46: 8 | AF46: vb | AG46: 2200 | AH46: B origem: RADIER | C origem: CONCRETO | AI46: CUSTO CASA E CRONOGRAMA PAGAMEN | AJ46: =IF(Q46<>"",Q46,IF(K46<>"",K46,"")) -> 46115 | AK46: =IF(K46<>"","Sim","") -> Sim | AL46: =IF(A46="","",TEXT(A46,"000000")&"-"&IF(C46="Entrada","CR","DB")) -> 000045-DB | AM46: =IF(A46="","",LEFT(IF(H46<>"",H46,G46)&" | "&G46&" | "&S46,60)) -> Bomba de concreto ( Taxa divide 1 casa e 1 radier ) | Bomba
A47: 46 | B47: SÃO FRANCISCO DE PAULA - RS | C47: Saída | D47: RADIER - 44,38 M² | E47: RADIER | F47: Agregado | G47: Brita graduada (lastro para nivelamento) - 10 cm esp.; 15% penetração no solo | K47: 46115 | Q47: =IF(K47="","",K47) -> 46115 | R47: RADIER - 44,38 M² | S47: Saída | RADIER - 44,38 M² | T47: Saída | RADIER | Agregado | U47: 30/60 dias | V47: 31 | W47: Q2 | X47: 46104 | Y47: 46115 | Z47: 16921.486 | AA47: =IF(M47<>"",M47,Z47) -> 16921.486 | AB47: =IF(L47<>"","Realizado","Previsto") -> Previsto | AC47: 0.5 | AD47: 33842.973 | AE47: 371.9008 | AF47: m³ | AG47: 91 | AH47: B origem: RADIER | C origem: Agregado | AI47: CUSTO CASA E CRONOGRAMA PAGAMEN | AJ47: =IF(Q47<>"",Q47,IF(K47<>"",K47,"")) -> 46115 | AK47: =IF(K47<>"","Sim","") -> Sim | AL47: =IF(A47="","",TEXT(A47,"000000")&"-"&IF(C47="Entrada","CR","DB")) -> 000046-DB | AM47: =IF(A47="","",LEFT(IF(H47<>"",H47,G47)&" | "&G47&" | "&S47,60)) -> Brita graduada (lastro para nivelamento) - 10 cm esp.; 15% p
A48: 47 | B48: SÃO FRANCISCO DE PAULA - RS | C48: Saída | D48: RADIER - 44,38 M² | E48: RADIER | F48: INSUMO | G48: Cimento PortlanD CP IV 32 para limpeza da bomba | K48: 46115 | Q48: =IF(K48="","",K48) -> 46115 | R48: RADIER - 44,38 M² | S48: Saída | RADIER - 44,38 M² | T48: Saída | RADIER | INSUMO | V48: 37 | W48: Q2 | X48: 46104 | Y48: 46115 | Z48: 261.33333 | AA48: =IF(M48<>"",M48,Z48) -> 261.33333 | AB48: =IF(L48<>"","Realizado","Previsto") -> Previsto | AC48: 0.5 | AD48: 522.66667 | AE48: 10.666667 | AF48: kg | AG48: 49 | AH48: B origem: RADIER | C origem: INSUMO | AI48: CUSTO CASA E CRONOGRAMA PAGAMEN | AJ48: =IF(Q48<>"",Q48,IF(K48<>"",K48,"")) -> 46115 | AK48: =IF(K48<>"","Sim","") -> Sim | AL48: =IF(A48="","",TEXT(A48,"000000")&"-"&IF(C48="Entrada","CR","DB")) -> 000047-DB | AM48: =IF(A48="","",LEFT(IF(H48<>"",H48,G48)&" | "&G48&" | "&S48,60)) -> Cimento PortlanD CP IV 32 para limpeza da bomba | Cimento Po
A49: 48 | B49: SÃO FRANCISCO DE PAULA - RS | C49: Saída | D49: RADIER - 44,38 M² | E49: RADIER | F49: CONCRETO | G49: Concreto Usinado fck - 25 Mpa ( Com perda de 10%) - SEM IMPERMEABILIZANTE - 140 +- 30 slump | K49: 46115 | Q49: =IF(K49="","",K49) -> 46115 | R49: RADIER - 44,38 M² | S49: Saída | RADIER - 44,38 M² | T49: Saída | RADIER | CONCRETO | U49: 21 DIAS | V49: 29 | W49: Q2 | X49: 46104 | Y49: 46115 | Z49: 79635.2 | AA49: =IF(M49<>"",M49,Z49) -> 79635.2 | AB49: =IF(L49<>"","Realizado","Previsto") -> Previsto | AC49: 0.25 | AD49: 318540.8 | AE49: 512 | AF49: m³ | AG49: 622.15 | AH49: B origem: RADIER | C origem: CONCRETO | AI49: CUSTO CASA E CRONOGRAMA PAGAMEN | AJ49: =IF(Q49<>"",Q49,IF(K49<>"",K49,"")) -> 46115 | AK49: =IF(K49<>"","Sim","") -> Sim | AL49: =IF(A49="","",TEXT(A49,"000000")&"-"&IF(C49="Entrada","CR","DB")) -> 000048-DB | AM49: =IF(A49="","",LEFT(IF(H49<>"",H49,G49)&" | "&G49&" | "&S49,60)) -> Concreto Usinado fck - 25 Mpa ( Com perda de 10%) - SEM IMPE
A50: 49 | B50: SÃO FRANCISCO DE PAULA - RS | C50: Saída | D50: RADIER - 44,38 M² | E50: RADIER | F50: INSUMO | G50: Desmoldante TECNOMOR | K50: 46115 | Q50: =IF(K50="","",K50) -> 46115 | R50: RADIER - 44,38 M² | S50: Saída | RADIER - 44,38 M² | T50: Saída | RADIER | INSUMO | V50: 38 | W50: Q2 | X50: 46104 | Y50: 46115 | Z50: 1248 | AA50: =IF(M50<>"",M50,Z50) -> 1248 | AB50: =IF(L50<>"","Realizado","Previsto") -> Previsto | AC50: 0.5 | AD50: 2496 | AE50: 96 | AF50: litros | AG50: 26 | AH50: B origem: RADIER | C origem: INSUMO | AI50: CUSTO CASA E CRONOGRAMA PAGAMEN | AJ50: =IF(Q50<>"",Q50,IF(K50<>"",K50,"")) -> 46115 | AK50: =IF(K50<>"","Sim","") -> Sim | AL50: =IF(A50="","",TEXT(A50,"000000")&"-"&IF(C50="Entrada","CR","DB")) -> 000049-DB | AM50: =IF(A50="","",LEFT(IF(H50<>"",H50,G50)&" | "&G50&" | "&S50,60)) -> Desmoldante TECNOMOR | Desmoldante TECNOMOR | Saída | RADIER
A51: 50 | B51: SÃO FRANCISCO DE PAULA - RS | C51: Saída | D51: RADIER - 44,38 M² | E51: RADIER | F51: SERVIÇO | G51: Ensaio compreesão corpo prova | K51: 46115 | Q51: =IF(K51="","",K51) -> 46115 | R51: RADIER - 44,38 M² | S51: Saída | RADIER - 44,38 M² | T51: Saída | RADIER | SERVIÇO | V51: 35 | W51: Q2 | X51: 46104 | Y51: 46115 | Z51: 2240 | AA51: =IF(M51<>"",M51,Z51) -> 2240 | AB51: =IF(L51<>"","Realizado","Previsto") -> Previsto | AC51: 0.5 | AD51: 4480 | AE51: 64 | AF51: unidade | AG51: 70 | AH51: B origem: RADIER | C origem: SERVIÇO | AI51: CUSTO CASA E CRONOGRAMA PAGAMEN | AJ51: =IF(Q51<>"",Q51,IF(K51<>"",K51,"")) -> 46115 | AK51: =IF(K51<>"","Sim","") -> Sim | AL51: =IF(A51="","",TEXT(A51,"000000")&"-"&IF(C51="Entrada","CR","DB")) -> 000050-DB | AM51: =IF(A51="","",LEFT(IF(H51<>"",H51,G51)&" | "&G51&" | "&S51,60)) -> Ensaio compreesão corpo prova | Ensaio compreesão corpo prov
A52: 51 | B52: SÃO FRANCISCO DE PAULA - RS | C52: Saída | D52: RADIER - 44,38 M² | E52: RADIER | F52: INSUMO | G52: Espaçador tipo centopeia - 5 unid. por m² - 50 mm | K52: 46115 | Q52: =IF(K52="","",K52) -> 46115 | R52: RADIER - 44,38 M² | S52: Saída | RADIER - 44,38 M² | T52: Saída | RADIER | INSUMO | V52: 33 | W52: Q2 | X52: 46104 | Y52: 46115 | Z52: 8320 | AA52: =IF(M52<>"",M52,Z52) -> 8320 | AB52: =IF(L52<>"","Realizado","Previsto") -> Previsto | AC52: 0.5 | AD52: 16640 | AE52: 16640 | AF52: unidade | AG52: 1 | AH52: B origem: RADIER | C origem: INSUMO | AI52: CUSTO CASA E CRONOGRAMA PAGAMEN | AJ52: =IF(Q52<>"",Q52,IF(K52<>"",K52,"")) -> 46115 | AK52: =IF(K52<>"","Sim","") -> Sim | AL52: =IF(A52="","",TEXT(A52,"000000")&"-"&IF(C52="Entrada","CR","DB")) -> 000051-DB | AM52: =IF(A52="","",LEFT(IF(H52<>"",H52,G52)&" | "&G52&" | "&S52,60)) -> Espaçador tipo centopeia - 5 unid. por m² - 50 mm | Espaçado
A53: 52 | B53: SÃO FRANCISCO DE PAULA - RS | C53: Saída | D53: RADIER - 44,38 M² | E53: RADIER | F53: RATEIO | G53: Forma para Radier - chapa de compensado naval plastificado 14mm | K53: 46115 | Q53: =IF(K53="","",K53) -> 46115 | R53: RADIER - 44,38 M² | S53: Saída | RADIER - 44,38 M² | T53: Saída | RADIER | RATEIO | V53: 40 | W53: Q2 | X53: 46104 | Y53: 46115 | Z53: 2419.2 | AA53: =IF(M53<>"",M53,Z53) -> 2419.2 | AB53: =IF(L53<>"","Realizado","Previsto") -> Previsto | AC53: 0.5 | AD53: 4838.4 | AE53: 35 | AF53: unidade | AG53: 138.24 | AH53: B origem: RADIER | C origem: RATEIO | AI53: CUSTO CASA E CRONOGRAMA PAGAMEN | AJ53: =IF(Q53<>"",Q53,IF(K53<>"",K53,"")) -> 46115 | AK53: =IF(K53<>"","Sim","") -> Sim | AL53: =IF(A53="","",TEXT(A53,"000000")&"-"&IF(C53="Entrada","CR","DB")) -> 000052-DB | AM53: =IF(A53="","",LEFT(IF(H53<>"",H53,G53)&" | "&G53&" | "&S53,60)) -> Forma para Radier - chapa de compensado naval plastificado 1
A54: 53 | B54: SÃO FRANCISCO DE PAULA - RS | C54: Saída | D54: RADIER - 44,38 M² | E54: RADIER | F54: RATEIO | G54: Forma para Radier - tabua pinus 25mm para montagem do gabarito 2,70 m x 15cm | K54: 46115 | Q54: =IF(K54="","",K54) -> 46115 | R54: RADIER - 44,38 M² | S54: Saída | RADIER - 44,38 M² | T54: Saída | RADIER | RATEIO | V54: 41 | W54: Q2 | X54: 46104 | Y54: 46115 | Z54: 1364 | AA54: =IF(M54<>"",M54,Z54) -> 1364 | AB54: =IF(L54<>"","Realizado","Previsto") -> Previsto | AC54: 0.5 | AD54: 2728 | AE54: 176 | AF54: unidade | AG54: 15.5 | AH54: B origem: RADIER | C origem: RATEIO | AI54: CUSTO CASA E CRONOGRAMA PAGAMEN | AJ54: =IF(Q54<>"",Q54,IF(K54<>"",K54,"")) -> 46115 | AK54: =IF(K54<>"","Sim","") -> Sim | AL54: =IF(A54="","",TEXT(A54,"000000")&"-"&IF(C54="Entrada","CR","DB")) -> 000053-DB | AM54: =IF(A54="","",LEFT(IF(H54<>"",H54,G54)&" | "&G54&" | "&S54,60)) -> Forma para Radier - tabua pinus 25mm para montagem do gabari
A55: 54 | B55: SÃO FRANCISCO DE PAULA - RS | C55: Saída | D55: RADIER - 44,38 M² | E55: RADIER | F55: INSUMO | G55: Lona 150 micras | K55: 46115 | Q55: =IF(K55="","",K55) -> 46115 | R55: RADIER - 44,38 M² | S55: Saída | RADIER - 44,38 M² | T55: Saída | RADIER | INSUMO | V55: 32 | W55: Q2 | X55: 46104 | Y55: 46115 | Z55: 4409.6 | AA55: =IF(M55<>"",M55,Z55) -> 4409.6 | AB55: =IF(L55<>"","Realizado","Previsto") -> Previsto | AC55: 0.5 | AD55: 8819.2 | AE55: 3392 | AF55: m² | AG55: 2.6 | AH55: B origem: RADIER | C origem: INSUMO | AI55: CUSTO CASA E CRONOGRAMA PAGAMEN | AJ55: =IF(Q55<>"",Q55,IF(K55<>"",K55,"")) -> 46115 | AK55: =IF(K55<>"","Sim","") -> Sim | AL55: =IF(A55="","",TEXT(A55,"000000")&"-"&IF(C55="Entrada","CR","DB")) -> 000054-DB | AM55: =IF(A55="","",LEFT(IF(H55<>"",H55,G55)&" | "&G55&" | "&S55,60)) -> Lona 150 micras | Lona 150 micras | Saída | RADIER - 44,38 M
A56: 55 | B56: SÃO FRANCISCO DE PAULA - RS | C56: Saída | D56: RADIER - 44,38 M² | E56: RADIER | F56: MAO DE OBRA | G56: Mao de obra Terceirizada Radier | K56: 46115 | Q56: =IF(K56="","",K56) -> 46115 | R56: RADIER - 44,38 M² | S56: Saída | RADIER - 44,38 M² | T56: Saída | RADIER | MAO DE OBRA | V56: 43 | W56: Q2 | X56: 46104 | Y56: 46115 | Z56: 41271.499 | AA56: =IF(M56<>"",M56,Z56) -> 41271.499 | AB56: =IF(L56<>"","Realizado","Previsto") -> Previsto | AC56: 0.32243359 | AD56: 128000 | AE56: 64 | AF56: vb | AG56: 2000 | AH56: B origem: RADIER | C origem: MAO DE OBRA | AI56: CUSTO CASA E CRONOGRAMA PAGAMEN | AJ56: =IF(Q56<>"",Q56,IF(K56<>"",K56,"")) -> 46115 | AK56: =IF(K56<>"","Sim","") -> Sim | AL56: =IF(A56="","",TEXT(A56,"000000")&"-"&IF(C56="Entrada","CR","DB")) -> 000055-DB | AM56: =IF(A56="","",LEFT(IF(H56<>"",H56,G56)&" | "&G56&" | "&S56,60)) -> Mao de obra Terceirizada Radier | Mao de obra Terceirizada R
A57: 56 | B57: SÃO FRANCISCO DE PAULA - RS | C57: Saída | D57: RADIER - 44,38 M² | E57: RADIER | F57: LOCAÇAO | G57: Placa vibratoria reversivél CR5 | K57: 46115 | Q57: =IF(K57="","",K57) -> 46115 | R57: RADIER - 44,38 M² | S57: Saída | RADIER - 44,38 M² | T57: Saída | RADIER | LOCAÇAO | V57: 42 | W57: Q2 | X57: 46104 | Y57: 46115 | Z57: 1600 | AA57: =IF(M57<>"",M57,Z57) -> 1600 | AB57: =IF(L57<>"","Realizado","Previsto") -> Previsto | AC57: 0.5 | AD57: 3200 | AE57: 21.333333 | AF57: dia | AG57: 150 | AH57: B origem: RADIER | C origem: LOCAÇAO | AI57: CUSTO CASA E CRONOGRAMA PAGAMEN | AJ57: =IF(Q57<>"",Q57,IF(K57<>"",K57,"")) -> 46115 | AK57: =IF(K57<>"","Sim","") -> Sim | AL57: =IF(A57="","",TEXT(A57,"000000")&"-"&IF(C57="Entrada","CR","DB")) -> 000056-DB | AM57: =IF(A57="","",LEFT(IF(H57<>"",H57,G57)&" | "&G57&" | "&S57,60)) -> Placa vibratoria reversivél CR5 | Placa vibratoria reversivé
A58: 57 | B58: SÃO FRANCISCO DE PAULA - RS | C58: Saída | D58: RADIER - 44,38 M² | E58: RADIER | F58: FERRAGEM | G58: Prego 17 x 27 cabeça dupla | K58: 46115 | Q58: =IF(K58="","",K58) -> 46115 | R58: RADIER - 44,38 M² | S58: Saída | RADIER - 44,38 M² | T58: Saída | RADIER | FERRAGEM | V58: 46 | W58: Q2 | X58: 46104 | Y58: 46115 | Z58: 917.5 | AA58: =IF(M58<>"",M58,Z58) -> 917.5 | AB58: =IF(L58<>"","Realizado","Previsto") -> Previsto | AC58: 0.5 | AD58: 1835 | AE58: 140 | AF58: kg | AG58: 13.107143 | AH58: B origem: RADIER | C origem: FERRAGEM | AI58: CUSTO CASA E CRONOGRAMA PAGAMEN | AJ58: =IF(Q58<>"",Q58,IF(K58<>"",K58,"")) -> 46115 | AK58: =IF(K58<>"","Sim","") -> Sim | AL58: =IF(A58="","",TEXT(A58,"000000")&"-"&IF(C58="Entrada","CR","DB")) -> 000057-DB | AM58: =IF(A58="","",LEFT(IF(H58<>"",H58,G58)&" | "&G58&" | "&S58,60)) -> Prego 17 x 27 cabeça dupla | Prego 17 x 27 cabeça dupla | Sa
A59: 58 | B59: SÃO FRANCISCO DE PAULA - RS | C59: Saída | D59: RADIER - 44,38 M² | E59: RADIER | F59: RATEIO | G59: impermeabilizante para lateral das chapas de compensado (link no grupo) | K59: 46115 | Q59: =IF(K59="","",K59) -> 46115 | R59: RADIER - 44,38 M² | S59: Saída | RADIER - 44,38 M² | T59: Saída | RADIER | RATEIO | V59: 39 | W59: Q2 | X59: 46104 | Y59: 46115 | Z59: 57 | AA59: =IF(M59<>"",M59,Z59) -> 57 | AB59: =IF(L59<>"","Realizado","Previsto") -> Previsto | AC59: 0.5 | AD59: 114 | AE59: 2 | AF59: unidade | AG59: 57 | AH59: B origem: RADIER | C origem: RATEIO | AI59: CUSTO CASA E CRONOGRAMA PAGAMEN | AJ59: =IF(Q59<>"",Q59,IF(K59<>"",K59,"")) -> 46115 | AK59: =IF(K59<>"","Sim","") -> Sim | AL59: =IF(A59="","",TEXT(A59,"000000")&"-"&IF(C59="Entrada","CR","DB")) -> 000058-DB | AM59: =IF(A59="","",LEFT(IF(H59<>"",H59,G59)&" | "&G59&" | "&S59,60)) -> impermeabilizante para lateral das chapas de compensado (lin
A60: 59 | B60: SÃO FRANCISCO DE PAULA - RS | C60: Saída | D60: RADIER - 44,38 M² | E60: RADIER | F60: MADEIRA | G60: ripas de 5cm x 2,7m de 25mm | K60: 46115 | Q60: =IF(K60="","",K60) -> 46115 | R60: RADIER - 44,38 M² | S60: Saída | RADIER - 44,38 M² | T60: Saída | RADIER | MADEIRA | V60: 44 | W60: Q2 | X60: 46104 | Y60: 46115 | Z60: 1267.2 | AA60: =IF(M60<>"",M60,Z60) -> 1267.2 | AB60: =IF(L60<>"","Realizado","Previsto") -> Previsto | AC60: 0.3 | AD60: 4224 | AE60: 704 | AF60: pç | AG60: 6 | AH60: B origem: RADIER | C origem: MADEIRA | AI60: CUSTO CASA E CRONOGRAMA PAGAMEN | AJ60: =IF(Q60<>"",Q60,IF(K60<>"",K60,"")) -> 46115 | AK60: =IF(K60<>"","Sim","") -> Sim | AL60: =IF(A60="","",TEXT(A60,"000000")&"-"&IF(C60="Entrada","CR","DB")) -> 000059-DB | AM60: =IF(A60="","",LEFT(IF(H60<>"",H60,G60)&" | "&G60&" | "&S60,60)) -> ripas de 5cm x 2,7m de 25mm | ripas de 5cm x 2,7m de 25mm |
A61: 60 | B61: SÃO FRANCISCO DE PAULA - RS | C61: Saída | D61: SERVIÇOS | E61: SERVIÇOS | F61: SERVIÇOS | G61: TOTALIZADOR CUSTO GLOBAIS OBRAS - MENSAL | K61: 46115 | Q61: =IF(K61="","",K61) -> 46115 | R61: SERVIÇOS | S61: Saída | SERVIÇOS | T61: Saída | SERVIÇOS | SERVIÇOS | V61: 267 | W61: Q2 | X61: 46104 | Y61: 46115 | Z61: 240223.45 | AA61: =IF(M61<>"",M61,Z61) -> 240223.45 | AB61: =IF(L61<>"","Realizado","Previsto") -> Previsto | AD61: 5780911.4 | AF61: mês | AI61: CUSTO CASA E CRONOGRAMA PAGAMEN | AJ61: =IF(Q61<>"",Q61,IF(K61<>"",K61,"")) -> 46115 | AK61: =IF(K61<>"","Sim","") -> Sim | AL61: =IF(A61="","",TEXT(A61,"000000")&"-"&IF(C61="Entrada","CR","DB")) -> 000060-DB | AM61: =IF(A61="","",LEFT(IF(H61<>"",H61,G61)&" | "&G61&" | "&S61,60)) -> TOTALIZADOR CUSTO GLOBAIS OBRAS - MENSAL | TOTALIZADOR CUSTO
A62: 61 | B62: SÃO FRANCISCO DE PAULA - RS | C62: Entrada | D62: RECEITAS | E62: RECEITAS | F62: RECEITA CONTRATUAL | G62: MEDIÇÃO CONTRATUAL | K62: 46129 | Q62: =IF(K62="","",K62) -> 46129 | R62: MEDIÇÃO CONTRATUAL | S62: Entrada | MEDIÇÃO CONTRATUAL | T62: Entrada | RECEITAS | RECEITA CONTRATUAL | V62: 283 | W62: Q3 | X62: 46118 | Y62: 46129 | Z62: 855077.76 | AA62: =IF(M62<>"",M62,Z62) -> 855077.76 | AB62: =IF(L62<>"","Realizado","Previsto") -> Previsto | AD62: 8079999.9 | AI62: CUSTO CASA E CRONOGRAMA PAGAMEN | AJ62: =IF(Q62<>"",Q62,IF(K62<>"",K62,"")) -> 46129 | AK62: =IF(K62<>"","Sim","") -> Sim | AL62: =IF(A62="","",TEXT(A62,"000000")&"-"&IF(C62="Entrada","CR","DB")) -> 000061-CR | AM62: =IF(A62="","",LEFT(IF(H62<>"",H62,G62)&" | "&G62&" | "&S62,60)) -> MEDIÇÃO CONTRATUAL | MEDIÇÃO CONTRATUAL | Entrada | MEDIÇÃO
A63: 62 | B63: SÃO FRANCISCO DE PAULA - RS | C63: Saída | D63: AZULEJOS | E63: AZULEJOS | F63: MAO DE OBRA | G63: Mao de obra terceirizada assentamento Azulejo | K63: 46129 | Q63: =IF(K63="","",K63) -> 46129 | R63: AZULEJOS | S63: Saída | AZULEJOS | T63: Saída | AZULEJOS | MAO DE OBRA | U63: Faturamento para 45 dias após boletim fiscalizaçao | V63: 115 | W63: Q3 | X63: 46118 | Y63: 46129 | Z63: 7510.992 | AA63: =IF(M63<>"",M63,Z63) -> 7510.992 | AB63: =IF(L63<>"","Realizado","Previsto") -> Previsto | AC63: 0.0937 | AD63: 80160 | AE63: 1603.2 | AF63: m² | AG63: 50 | AH63: B origem: AZULEJOS | C origem: MAO DE OBRA | AI63: CUSTO CASA E CRONOGRAMA PAGAMEN | AJ63: =IF(Q63<>"",Q63,IF(K63<>"",K63,"")) -> 46129 | AK63: =IF(K63<>"","Sim","") -> Sim | AL63: =IF(A63="","",TEXT(A63,"000000")&"-"&IF(C63="Entrada","CR","DB")) -> 000062-DB | AM63: =IF(A63="","",LEFT(IF(H63<>"",H63,G63)&" | "&G63&" | "&S63,60)) -> Mao de obra terceirizada assentamento Azulejo | Mao de obra
A64: 63 | B64: SÃO FRANCISCO DE PAULA - RS | C64: Saída | D64: CAIXAS DE INSPEÇÃO E GORDURA | E64: CAIXAS DE INSPEÇÃO E GORDURA | F64: MAO DE OBRA | G64: MO Terceirizada Caixas de inspecao e gordura | K64: 46129 | Q64: =IF(K64="","",K64) -> 46129 | R64: CAIXAS DE INSPEÇÃO E GORDURA | S64: Saída | CAIXAS DE INSPEÇÃO E GORDURA | T64: Saída | CAIXAS DE INSPEÇÃO E GORDURA | MAO DE OBRA | U64: Faturamento para 45 dias após boletim fiscalizaçao | V64: 101 | W64: Q3 | X64: 46118 | Y64: 46129 | Z64: 4917.376 | AA64: =IF(M64<>"",M64,Z64) -> 4917.376 | AB64: =IF(L64<>"","Realizado","Previsto") -> Previsto | AC64: 0.0937 | AD64: 52480 | AE64: 64 | AF64: vb | AG64: 820 | AH64: B origem: CAIXAS DE INSPEÇÃO E GORDURA | C origem: MAO DE OBRA | AI64: CUSTO CASA E CRONOGRAMA PAGAMEN | AJ64: =IF(Q64<>"",Q64,IF(K64<>"",K64,"")) -> 46129 | AK64: =IF(K64<>"","Sim","") -> Sim | AL64: =IF(A64="","",TEXT(A64,"000000")&"-"&IF(C64="Entrada","CR","DB")) -> 000063-DB | AM64: =IF(A64="","",LEFT(IF(H64<>"",H64,G64)&" | "&G64&" | "&S64,60)) -> MO Terceirizada Caixas de inspecao e gordura | MO Terceiriza
A65: 64 | B65: SÃO FRANCISCO DE PAULA - RS | C65: Saída | D65: CAPITAL DE GIRO | E65: CAPITAL DE GIRO | F65: EMPRÉSTIMOS / CAPITAL DE GIRO | G65: CARTAO CREDITO SUCOPIRA | K65: 46129 | Q65: =IF(K65="","",K65) -> 46129 | R65: CAPITAL DE GIRO | S65: Saída | CAPITAL DE GIRO | T65: Saída | CAPITAL DE GIRO | EMPRÉSTIMOS / CAPITAL DE GIRO | V65: 274 | W65: Q3 | X65: 46118 | Y65: 46129 | Z65: 21190 | AA65: =IF(M65<>"",M65,Z65) -> 21190 | AB65: =IF(L65<>"","Realizado","Previsto") -> Previsto | AD65: 211900 | AH65: C origem: 163000 | AI65: CUSTO CASA E CRONOGRAMA PAGAMEN | AJ65: =IF(Q65<>"",Q65,IF(K65<>"",K65,"")) -> 46129 | AK65: =IF(K65<>"","Sim","") -> Sim | AL65: =IF(A65="","",TEXT(A65,"000000")&"-"&IF(C65="Entrada","CR","DB")) -> 000064-DB | AM65: =IF(A65="","",LEFT(IF(H65<>"",H65,G65)&" | "&G65&" | "&S65,60)) -> CARTAO CREDITO SUCOPIRA | CARTAO CREDITO SUCOPIRA | Saída |
A66: 65 | B66: SÃO FRANCISCO DE PAULA - RS | C66: Saída | D66: CAPITAL DE GIRO | E66: CAPITAL DE GIRO | F66: EMPRÉSTIMOS / CAPITAL DE GIRO | G66: EMPRESTIMO BRADESCO | K66: 46129 | Q66: =IF(K66="","",K66) -> 46129 | R66: CAPITAL DE GIRO | S66: Saída | CAPITAL DE GIRO | T66: Saída | CAPITAL DE GIRO | EMPRÉSTIMOS / CAPITAL DE GIRO | V66: 276 | W66: Q3 | X66: 46118 | Y66: 46129 | Z66: 14716.35 | AA66: =IF(M66<>"",M66,Z66) -> 14716.35 | AB66: =IF(L66<>"","Realizado","Previsto") -> Previsto | AD66: 244149.05 | AH66: C origem: 200000 | AI66: CUSTO CASA E CRONOGRAMA PAGAMEN | AJ66: =IF(Q66<>"",Q66,IF(K66<>"",K66,"")) -> 46129 | AK66: =IF(K66<>"","Sim","") -> Sim | AL66: =IF(A66="","",TEXT(A66,"000000")&"-"&IF(C66="Entrada","CR","DB")) -> 000065-DB | AM66: =IF(A66="","",LEFT(IF(H66<>"",H66,G66)&" | "&G66&" | "&S66,60)) -> EMPRESTIMO BRADESCO | EMPRESTIMO BRADESCO | Saída | CAPITAL
A67: 66 | B67: SÃO FRANCISCO DE PAULA - RS | C67: Saída | D67: CAPITAL DE GIRO | E67: CAPITAL DE GIRO | F67: EMPRÉSTIMOS / CAPITAL DE GIRO | G67: EMPRÉSTIMO EXTRA | K67: 46129 | Q67: =IF(K67="","",K67) -> 46129 | R67: CAPITAL DE GIRO | S67: Saída | CAPITAL DE GIRO | T67: Saída | CAPITAL DE GIRO | EMPRÉSTIMOS / CAPITAL DE GIRO | V67: 277 | W67: Q3 | X67: 46118 | Y67: 46129 | Z67: 7670 | AA67: =IF(M67<>"",M67,Z67) -> 7670 | AB67: =IF(L67<>"","Realizado","Previsto") -> Previsto | AD67: 76700 | AH67: C origem: 59000 | AI67: CUSTO CASA E CRONOGRAMA PAGAMEN | AJ67: =IF(Q67<>"",Q67,IF(K67<>"",K67,"")) -> 46129 | AK67: =IF(K67<>"","Sim","") -> Sim | AL67: =IF(A67="","",TEXT(A67,"000000")&"-"&IF(C67="Entrada","CR","DB")) -> 000066-DB | AM67: =IF(A67="","",LEFT(IF(H67<>"",H67,G67)&" | "&G67&" | "&S67,60)) -> EMPRÉSTIMO EXTRA | EMPRÉSTIMO EXTRA | Saída | CAPITAL DE GIR
A68: 67 | B68: SÃO FRANCISCO DE PAULA - RS | C68: Saída | D68: CAPITAL DE GIRO | E68: CAPITAL DE GIRO | F68: EMPRÉSTIMOS / CAPITAL DE GIRO | G68: NUBANK | K68: 46129 | Q68: =IF(K68="","",K68) -> 46129 | R68: CAPITAL DE GIRO | S68: Saída | CAPITAL DE GIRO | T68: Saída | CAPITAL DE GIRO | EMPRÉSTIMOS / CAPITAL DE GIRO | V68: 275 | W68: Q3 | X68: 46118 | Y68: 46129 | Z68: 4906.58 | AA68: =IF(M68<>"",M68,Z68) -> 4906.58 | AB68: =IF(L68<>"","Realizado","Previsto") -> Previsto | AD68: 62266.45 | AH68: C origem: 50000 | AI68: CUSTO CASA E CRONOGRAMA PAGAMEN | AJ68: =IF(Q68<>"",Q68,IF(K68<>"",K68,"")) -> 46129 | AK68: =IF(K68<>"","Sim","") -> Sim | AL68: =IF(A68="","",TEXT(A68,"000000")&"-"&IF(C68="Entrada","CR","DB")) -> 000067-DB | AM68: =IF(A68="","",LEFT(IF(H68<>"",H68,G68)&" | "&G68&" | "&S68,60)) -> NUBANK | NUBANK | Saída | CAPITAL DE GIRO
A69: 68 | B69: SÃO FRANCISCO DE PAULA - RS | C69: Saída | D69: COBERTURA | E69: COBERTURA | F69: MAO DE OBRA | G69: Mao de obra terceirizada montagem e telhamento | K69: 46129 | Q69: =IF(K69="","",K69) -> 46129 | R69: COBERTURA | S69: Saída | COBERTURA | T69: Saída | COBERTURA | MAO DE OBRA | U69: Faturamento para 45 dias após boletim fiscalizaçao | V69: 107 | W69: Q3 | X69: 46118 | Y69: 46129 | Z69: 9295.04 | AA69: =IF(M69<>"",M69,Z69) -> 9295.04 | AB69: =IF(L69<>"","Realizado","Previsto") -> Previsto | AC69: 0.0937 | AD69: 99200 | AE69: 64 | AF69: vb | AG69: 1550 | AH69: B origem: COBERTURA | C origem: MAO DE OBRA | AI69: CUSTO CASA E CRONOGRAMA PAGAMEN | AJ69: =IF(Q69<>"",Q69,IF(K69<>"",K69,"")) -> 46129 | AK69: =IF(K69<>"","Sim","") -> Sim | AL69: =IF(A69="","",TEXT(A69,"000000")&"-"&IF(C69="Entrada","CR","DB")) -> 000068-DB | AM69: =IF(A69="","",LEFT(IF(H69<>"",H69,G69)&" | "&G69&" | "&S69,60)) -> Mao de obra terceirizada montagem e telhamento | Mao de obra
A70: 69 | B70: SÃO FRANCISCO DE PAULA - RS | C70: Saída | D70: DESPESAS ACESSÓRIAS | E70: DESPESAS ACESSÓRIAS | F70: DESPESAS ACESSÓRIAS | G70: LOGISTICA GESTÃO VISITA À OBRA | K70: 46129 | Q70: =IF(K70="","",K70) -> 46129 | R70: DESPESAS ACESSÓRIAS | S70: Saída | DESPESAS ACESSÓRIAS | T70: Saída | DESPESAS ACESSÓRIAS | DESPESAS ACESSÓRIAS | V70: 271 | W70: Q3 | X70: 46118 | Y70: 46129 | Z70: 8000 | AA70: =IF(M70<>"",M70,Z70) -> 8000 | AB70: =IF(L70<>"","Realizado","Previsto") -> Previsto | AC70: 0.2 | AD70: 40000 | AF70: mês | AG70: 10000 | AI70: CUSTO CASA E CRONOGRAMA PAGAMEN | AJ70: =IF(Q70<>"",Q70,IF(K70<>"",K70,"")) -> 46129 | AK70: =IF(K70<>"","Sim","") -> Sim | AL70: =IF(A70="","",TEXT(A70,"000000")&"-"&IF(C70="Entrada","CR","DB")) -> 000069-DB | AM70: =IF(A70="","",LEFT(IF(H70<>"",H70,G70)&" | "&G70&" | "&S70,60)) -> LOGISTICA GESTÃO VISITA À OBRA | LOGISTICA GESTÃO VISITA À O
A71: 70 | B71: SÃO FRANCISCO DE PAULA - RS | C71: Saída | D71: EMASSAMENTO INTERNO | E71: MASSA NIVELADORA | F71: MAO DE OBRA | G71: Mao de obra terceirizada Emassamento e lixamento interno paredes e teto | K71: 46129 | Q71: =IF(K71="","",K71) -> 46129 | R71: EMASSAMENTO INTERNO | S71: Saída | EMASSAMENTO INTERNO | T71: Saída | MASSA NIVELADORA | MAO DE OBRA | U71: Faturamento para 45 dias após boletim fiscalizaçao | V71: 156 | W71: Q3 | X71: 46118 | Y71: 46129 | Z71: 6426.6506 | AA71: =IF(M71<>"",M71,Z71) -> 6426.6506 | AB71: =IF(L71<>"","Realizado","Previsto") -> Previsto | AC71: 0.0937 | AD71: 68587.52 | AE71: 8573.44 | AF71: m² | AG71: 8 | AH71: B origem: MASSA NIVELADORA | C origem: MAO DE OBRA | AI71: CUSTO CASA E CRONOGRAMA PAGAMEN | AJ71: =IF(Q71<>"",Q71,IF(K71<>"",K71,"")) -> 46129 | AK71: =IF(K71<>"","Sim","") -> Sim | AL71: =IF(A71="","",TEXT(A71,"000000")&"-"&IF(C71="Entrada","CR","DB")) -> 000070-DB | AM71: =IF(A71="","",LEFT(IF(H71<>"",H71,G71)&" | "&G71&" | "&S71,60)) -> Mao de obra terceirizada Emassamento e lixamento interno pa
A72: 71 | B72: SÃO FRANCISCO DE PAULA - RS | C72: Saída | D72: GESTÃO LOCAL | E72: GESTÃO LOCAL | F72: ADMINISTRAÇAO | G72: TECNICO SEGURANÇA TRABALHO - ( rateado em 3 canteiros) carro incluso | K72: 46129 | Q72: =IF(K72="","",K72) -> 46129 | R72: GESTÃO LOCAL | S72: Saída | GESTÃO LOCAL | T72: Saída | GESTÃO LOCAL | ADMINISTRAÇAO | V72: 263 | W72: Q3 | X72: 46118 | Y72: 46129 | Z72: 3000 | AA72: =IF(M72<>"",M72,Z72) -> 3000 | AB72: =IF(L72<>"","Realizado","Previsto") -> Previsto | AC72: 0.25 | AD72: 12000 | AF72: mês | AG72: 3000 | AH72: C origem: ADMINISTRAÇAO | AI72: CUSTO CASA E CRONOGRAMA PAGAMEN | AJ72: =IF(Q72<>"",Q72,IF(K72<>"",K72,"")) -> 46129 | AK72: =IF(K72<>"","Sim","") -> Sim | AL72: =IF(A72="","",TEXT(A72,"000000")&"-"&IF(C72="Entrada","CR","DB")) -> 000071-DB | AM72: =IF(A72="","",LEFT(IF(H72<>"",H72,G72)&" | "&G72&" | "&S72,60)) -> TECNICO SEGURANÇA TRABALHO - ( rateado em 3 canteiros) carro
A73: 72 | B73: SÃO FRANCISCO DE PAULA - RS | C73: Saída | D73: IMPERMEABILIZAÇÃO | E73: IMPERMEABILIZAÇAO INTERNA | F73: MAO DE OBRA | G73: Mao de obra Impermeabilização de áreas úmidas | K73: 46129 | Q73: =IF(K73="","",K73) -> 46129 | R73: IMPERMEABILIZAÇÃO | S73: Saída | IMPERMEABILIZAÇÃO | T73: Saída | IMPERMEABILIZAÇAO INTERNA | MAO DE OBRA | U73: Faturamento para 45 dias após boletim fiscalizaçao | V73: 73 | W73: Q3 | X73: 46118 | Y73: 46129 | Z73: 2518.656 | AA73: =IF(M73<>"",M73,Z73) -> 2518.656 | AB73: =IF(L73<>"","Realizado","Previsto") -> Previsto | AC73: 0.0937 | AD73: 26880 | AE73: 64 | AF73: vb | AG73: 420 | AH73: B origem: IMPERMEABILIZAÇAO INTERNA | C origem: MAO DE OBRA | AI73: CUSTO CASA E CRONOGRAMA PAGAMEN | AJ73: =IF(Q73<>"",Q73,IF(K73<>"",K73,"")) -> 46129 | AK73: =IF(K73<>"","Sim","") -> Sim | AL73: =IF(A73="","",TEXT(A73,"000000")&"-"&IF(C73="Entrada","CR","DB")) -> 000072-DB | AM73: =IF(A73="","",LEFT(IF(H73<>"",H73,G73)&" | "&G73&" | "&S73,60)) -> Mao de obra Impermeabilização de áreas úmidas | Mao de obra
A74: 73 | B74: SÃO FRANCISCO DE PAULA - RS | C74: Saída | D74: PAREDES (102,5m² de área interna e externa) (44,38² de Laje) | E74: PAREDES COM CONCRETO | F74: MAO DE OBRA | G74: Montagem de paredes pré-moldadas (içamento, prumo, alinhamento e escoramento com grauteamento) – até 35 t | K74: 46129 | Q74: =IF(K74="","",K74) -> 46129 | R74: PAREDES (102,5m² de área interna e externa) (44,38² de Laje) | S74: Saída | PAREDES (102,5m² de área interna e externa) (44,38² de Laje) | T74: Saída | PAREDES COM CONCRETO | MAO DE OBRA | U74: 45 dias após boletim fiscalizaçao | V74: 58 | W74: Q3 | X74: 46118 | Y74: 46129 | Z74: 14991.964 | AA74: =IF(M74<>"",M74,Z74) -> 14991.964 | AB74: =IF(L74<>"","Realizado","Previsto") -> Previsto | AC74: 0.0937 | AD74: 159999.62 | AE74: 896 | AF74: m³ | AG74: 178.571 | AH74: B origem: PAREDES COM CONCRETO | C origem: MAO DE OBRA | AI74: CUSTO CASA E CRONOGRAMA PAGAMEN | AJ74: =IF(Q74<>"",Q74,IF(K74<>"",K74,"")) -> 46129 | AK74: =IF(K74<>"","Sim","") -> Sim | AL74: =IF(A74="","",TEXT(A74,"000000")&"-"&IF(C74="Entrada","CR","DB")) -> 000073-DB | AM74: =IF(A74="","",LEFT(IF(H74<>"",H74,G74)&" | "&G74&" | "&S74,60)) -> Montagem de paredes pré-moldadas (içamento, prumo, alinhamen
A75: 74 | B75: SÃO FRANCISCO DE PAULA - RS | C75: Saída | D75: PAREDES (102,5m² de área interna e externa) (44,38² de Laje) | E75: PAREDES COM CONCRETO | F75: FABRICA | G75: contrato industrializaçao paredes | K75: 46129 | Q75: =IF(K75="","",K75) -> 46129 | R75: PAREDES (102,5m² de área interna e externa) (44,38² de Laje) | S75: Saída | PAREDES (102,5m² de área interna e externa) (44,38² de Laje) | T75: Saída | PAREDES COM CONCRETO | FABRICA | U75: 20 | V75: 48 | W75: Q3 | X75: 46118 | Y75: 46129 | Z75: 74656 | AA75: =IF(M75<>"",M75,Z75) -> 74656 | AB75: =IF(L75<>"","Realizado","Previsto") -> Previsto | AC75: 0.2333 | AD75: 320000 | AE75: 20 | AF75: unidade | AG75: 16000 | AH75: B origem: PAREDES COM CONCRETO | C origem: FABRICA | AI75: CUSTO CASA E CRONOGRAMA PAGAMEN | AJ75: =IF(Q75<>"",Q75,IF(K75<>"",K75,"")) -> 46129 | AK75: =IF(K75<>"","Sim","") -> Sim | AL75: =IF(A75="","",TEXT(A75,"000000")&"-"&IF(C75="Entrada","CR","DB")) -> 000074-DB | AM75: =IF(A75="","",LEFT(IF(H75<>"",H75,G75)&" | "&G75&" | "&S75,60)) -> contrato industrializaçao paredes | contrato industrializaça
A76: 75 | B76: SÃO FRANCISCO DE PAULA - RS | C76: Saída | D76: PAREDES (102,5m² de área interna e externa) (44,38² de Laje) | E76: PAREDES COM CONCRETO | F76: FABRICA | G76: contrato industrializaçao paredes | K76: 46129 | Q76: =IF(K76="","",K76) -> 46129 | R76: PAREDES (102,5m² de área interna e externa) (44,38² de Laje) | S76: Saída | PAREDES (102,5m² de área interna e externa) (44,38² de Laje) | T76: Saída | PAREDES COM CONCRETO | FABRICA | U76: 20 | V76: 49 | W76: Q3 | X76: 46118 | Y76: 46129 | Z76: 74656 | AA76: =IF(M76<>"",M76,Z76) -> 74656 | AB76: =IF(L76<>"","Realizado","Previsto") -> Previsto | AC76: 0.2333 | AD76: 320000 | AE76: 20 | AF76: unidade | AG76: 16000 | AH76: B origem: PAREDES COM CONCRETO | C origem: FABRICA | AI76: CUSTO CASA E CRONOGRAMA PAGAMEN | AJ76: =IF(Q76<>"",Q76,IF(K76<>"",K76,"")) -> 46129 | AK76: =IF(K76<>"","Sim","") -> Sim | AL76: =IF(A76="","",TEXT(A76,"000000")&"-"&IF(C76="Entrada","CR","DB")) -> 000075-DB | AM76: =IF(A76="","",LEFT(IF(H76<>"",H76,G76)&" | "&G76&" | "&S76,60)) -> contrato industrializaçao paredes | contrato industrializaça
A77: 76 | B77: SÃO FRANCISCO DE PAULA - RS | C77: Saída | D77: PAREDES (102,5m² de área interna e externa) (44,38² de Laje) | E77: PAREDES COM CONCRETO | F77: FABRICA | G77: contrato industrializaçao paredes | K77: 46129 | Q77: =IF(K77="","",K77) -> 46129 | R77: PAREDES (102,5m² de área interna e externa) (44,38² de Laje) | S77: Saída | PAREDES (102,5m² de área interna e externa) (44,38² de Laje) | T77: Saída | PAREDES COM CONCRETO | FABRICA | U77: 24 | V77: 50 | W77: Q3 | X77: 46118 | Y77: 46129 | Z77: 89587.2 | AA77: =IF(M77<>"",M77,Z77) -> 89587.2 | AB77: =IF(L77<>"","Realizado","Previsto") -> Previsto | AC77: 0.2333 | AD77: 384000 | AE77: 24 | AF77: unidade | AG77: 16000 | AH77: B origem: PAREDES COM CONCRETO | C origem: FABRICA | AI77: CUSTO CASA E CRONOGRAMA PAGAMEN | AJ77: =IF(Q77<>"",Q77,IF(K77<>"",K77,"")) -> 46129 | AK77: =IF(K77<>"","Sim","") -> Sim | AL77: =IF(A77="","",TEXT(A77,"000000")&"-"&IF(C77="Entrada","CR","DB")) -> 000076-DB | AM77: =IF(A77="","",LEFT(IF(H77<>"",H77,G77)&" | "&G77&" | "&S77,60)) -> contrato industrializaçao paredes | contrato industrializaça
A78: 77 | B78: SÃO FRANCISCO DE PAULA - RS | C78: Saída | D78: PAREDES (102,5m² de área interna e externa) (44,38² de Laje) | E78: PAREDES COM CONCRETO | F78: FABRICA | G78: material CIMENTO : KIT Parede e Laje - FOB na Fabrica | K78: 46129 | Q78: =IF(K78="","",K78) -> 46129 | R78: PAREDES (102,5m² de área interna e externa) (44,38² de Laje) | S78: Saída | PAREDES (102,5m² de área interna e externa) (44,38² de Laje) | T78: Saída | PAREDES COM CONCRETO | FABRICA | U78: 20 | V78: 54 | W78: Q3 | X78: 46118 | Y78: 46129 | Z78: 38381.901 | AA78: =IF(M78<>"",M78,Z78) -> 38381.901 | AB78: =IF(L78<>"","Realizado","Previsto") -> Previsto | AC78: 0.20689655 | AD78: 185512.52 | AE78: 20 | AF78: unidade | AG78: 9275.626 | AH78: B origem: PAREDES COM CONCRETO | C origem: FABRICA | AI78: CUSTO CASA E CRONOGRAMA PAGAMEN | AJ78: =IF(Q78<>"",Q78,IF(K78<>"",K78,"")) -> 46129 | AK78: =IF(K78<>"","Sim","") -> Sim | AL78: =IF(A78="","",TEXT(A78,"000000")&"-"&IF(C78="Entrada","CR","DB")) -> 000077-DB | AM78: =IF(A78="","",LEFT(IF(H78<>"",H78,G78)&" | "&G78&" | "&S78,60)) -> material CIMENTO : KIT Parede e Laje - FOB na Fabrica | mate
A79: 78 | B79: SÃO FRANCISCO DE PAULA - RS | C79: Saída | D79: PAREDES (102,5m² de área interna e externa) (44,38² de Laje) | E79: PAREDES COM CONCRETO | F79: FABRICA | G79: material CIMENTO : KIT Parede e Laje - FOB na Fabrica | K79: 46129 | Q79: =IF(K79="","",K79) -> 46129 | R79: PAREDES (102,5m² de área interna e externa) (44,38² de Laje) | S79: Saída | PAREDES (102,5m² de área interna e externa) (44,38² de Laje) | T79: Saída | PAREDES COM CONCRETO | FABRICA | U79: 20 | V79: 55 | W79: Q3 | X79: 46118 | Y79: 46129 | Z79: 38381.901 | AA79: =IF(M79<>"",M79,Z79) -> 38381.901 | AB79: =IF(L79<>"","Realizado","Previsto") -> Previsto | AC79: 0.20689655 | AD79: 185512.52 | AE79: 20 | AF79: unidade | AG79: 9275.626 | AH79: B origem: PAREDES COM CONCRETO | C origem: FABRICA | AI79: CUSTO CASA E CRONOGRAMA PAGAMEN | AJ79: =IF(Q79<>"",Q79,IF(K79<>"",K79,"")) -> 46129 | AK79: =IF(K79<>"","Sim","") -> Sim | AL79: =IF(A79="","",TEXT(A79,"000000")&"-"&IF(C79="Entrada","CR","DB")) -> 000078-DB | AM79: =IF(A79="","",LEFT(IF(H79<>"",H79,G79)&" | "&G79&" | "&S79,60)) -> material CIMENTO : KIT Parede e Laje - FOB na Fabrica | mate
A80: 79 | B80: SÃO FRANCISCO DE PAULA - RS | C80: Saída | D80: PAREDES (102,5m² de área interna e externa) (44,38² de Laje) | E80: PAREDES COM CONCRETO | F80: FABRICA | G80: material CIMENTO : KIT Parede e Laje - FOB na Fabrica | K80: 46129 | Q80: =IF(K80="","",K80) -> 46129 | R80: PAREDES (102,5m² de área interna e externa) (44,38² de Laje) | S80: Saída | PAREDES (102,5m² de área interna e externa) (44,38² de Laje) | T80: Saída | PAREDES COM CONCRETO | FABRICA | U80: 24 | V80: 56 | W80: Q3 | X80: 46118 | Y80: 46129 | Z80: 46058.281 | AA80: =IF(M80<>"",M80,Z80) -> 46058.281 | AB80: =IF(L80<>"","Realizado","Previsto") -> Previsto | AC80: 0.20689655 | AD80: 222615.02 | AE80: 24 | AF80: unidade | AG80: 9275.626 | AH80: B origem: PAREDES COM CONCRETO | C origem: FABRICA | AI80: CUSTO CASA E CRONOGRAMA PAGAMEN | AJ80: =IF(Q80<>"",Q80,IF(K80<>"",K80,"")) -> 46129 | AK80: =IF(K80<>"","Sim","") -> Sim | AL80: =IF(A80="","",TEXT(A80,"000000")&"-"&IF(C80="Entrada","CR","DB")) -> 000079-DB | AM80: =IF(A80="","",LEFT(IF(H80<>"",H80,G80)&" | "&G80&" | "&S80,60)) -> material CIMENTO : KIT Parede e Laje - FOB na Fabrica | mate
A81: 80 | B81: SÃO FRANCISCO DE PAULA - RS | C81: Saída | D81: PAREDES (102,5m² de área interna e externa) (44,38² de Laje) | E81: PAREDES COM CONCRETO | F81: FABRICA | G81: material FERRO: KIT Parede e Laje - FOB na Fabrica | K81: 46129 | Q81: =IF(K81="","",K81) -> 46129 | R81: PAREDES (102,5m² de área interna e externa) (44,38² de Laje) | S81: Saída | PAREDES (102,5m² de área interna e externa) (44,38² de Laje) | T81: Saída | PAREDES COM CONCRETO | FABRICA | U81: 20 | V81: 51 | W81: Q3 | X81: 46118 | Y81: 46129 | Z81: 19437.767 | AA81: =IF(M81<>"",M81,Z81) -> 19437.767 | AB81: =IF(L81<>"","Realizado","Previsto") -> Previsto | AC81: 0.14453204 | AD81: 134487.6 | AE81: 20 | AF81: unidade | AG81: 6724.38 | AH81: B origem: PAREDES COM CONCRETO | C origem: FABRICA | AI81: CUSTO CASA E CRONOGRAMA PAGAMEN | AJ81: =IF(Q81<>"",Q81,IF(K81<>"",K81,"")) -> 46129 | AK81: =IF(K81<>"","Sim","") -> Sim | AL81: =IF(A81="","",TEXT(A81,"000000")&"-"&IF(C81="Entrada","CR","DB")) -> 000080-DB | AM81: =IF(A81="","",LEFT(IF(H81<>"",H81,G81)&" | "&G81&" | "&S81,60)) -> material FERRO: KIT Parede e Laje - FOB na Fabrica | materia
A82: 81 | B82: SÃO FRANCISCO DE PAULA - RS | C82: Saída | D82: PAREDES (102,5m² de área interna e externa) (44,38² de Laje) | E82: PAREDES COM CONCRETO | F82: FABRICA | G82: material FERRO: KIT Parede e Laje - FOB na Fabrica | K82: 46129 | Q82: =IF(K82="","",K82) -> 46129 | R82: PAREDES (102,5m² de área interna e externa) (44,38² de Laje) | S82: Saída | PAREDES (102,5m² de área interna e externa) (44,38² de Laje) | T82: Saída | PAREDES COM CONCRETO | FABRICA | U82: 20 | V82: 52 | W82: Q3 | X82: 46118 | Y82: 46129 | Z82: 19437.767 | AA82: =IF(M82<>"",M82,Z82) -> 19437.767 | AB82: =IF(L82<>"","Realizado","Previsto") -> Previsto | AC82: 0.14453204 | AD82: 134487.6 | AE82: 20 | AF82: unidade | AG82: 6724.38 | AH82: B origem: PAREDES COM CONCRETO | C origem: FABRICA | AI82: CUSTO CASA E CRONOGRAMA PAGAMEN | AJ82: =IF(Q82<>"",Q82,IF(K82<>"",K82,"")) -> 46129 | AK82: =IF(K82<>"","Sim","") -> Sim | AL82: =IF(A82="","",TEXT(A82,"000000")&"-"&IF(C82="Entrada","CR","DB")) -> 000081-DB | AM82: =IF(A82="","",LEFT(IF(H82<>"",H82,G82)&" | "&G82&" | "&S82,60)) -> material FERRO: KIT Parede e Laje - FOB na Fabrica | materia
A83: 82 | B83: SÃO FRANCISCO DE PAULA - RS | C83: Saída | D83: PAREDES (102,5m² de área interna e externa) (44,38² de Laje) | E83: PAREDES COM CONCRETO | F83: FABRICA | G83: material FERRO: KIT Parede e Laje - FOB na Fabrica | K83: 46129 | Q83: =IF(K83="","",K83) -> 46129 | R83: PAREDES (102,5m² de área interna e externa) (44,38² de Laje) | S83: Saída | PAREDES (102,5m² de área interna e externa) (44,38² de Laje) | T83: Saída | PAREDES COM CONCRETO | FABRICA | U83: 24 | V83: 53 | W83: Q3 | X83: 46118 | Y83: 46129 | Z83: 23325.321 | AA83: =IF(M83<>"",M83,Z83) -> 23325.321 | AB83: =IF(L83<>"","Realizado","Previsto") -> Previsto | AC83: 0.14453204 | AD83: 161385.12 | AE83: 24 | AF83: unidade | AG83: 6724.38 | AH83: B origem: PAREDES COM CONCRETO | C origem: FABRICA | AI83: CUSTO CASA E CRONOGRAMA PAGAMEN | AJ83: =IF(Q83<>"",Q83,IF(K83<>"",K83,"")) -> 46129 | AK83: =IF(K83<>"","Sim","") -> Sim | AL83: =IF(A83="","",TEXT(A83,"000000")&"-"&IF(C83="Entrada","CR","DB")) -> 000082-DB | AM83: =IF(A83="","",LEFT(IF(H83<>"",H83,G83)&" | "&G83&" | "&S83,60)) -> material FERRO: KIT Parede e Laje - FOB na Fabrica | materia
A84: 83 | B84: SÃO FRANCISCO DE PAULA - RS | C84: Saída | D84: PISO E RODAPÉ | E84: PISO E RODAPÉ | F84: MAO DE OBRA | G84: Mao de obra terceirizada assentamento Ceramica | K84: 46129 | Q84: =IF(K84="","",K84) -> 46129 | R84: PISO E RODAPÉ | S84: Saída | PISO E RODAPÉ | T84: Saída | PISO E RODAPÉ | MAO DE OBRA | U84: Faturamento para 45 dias após boletim fiscalizaçao | V84: 121 | W84: Q3 | X84: 46118 | Y84: 46129 | Z84: 8462.6842 | AA84: =IF(M84<>"",M84,Z84) -> 8462.6842 | AB84: =IF(L84<>"","Realizado","Previsto") -> Previsto | AC84: 0.0937 | AD84: 90316.8 | AE84: 2580.48 | AF84: m² | AG84: 35 | AH84: B origem: PISO E RODAPÉ | C origem: MAO DE OBRA | AI84: CUSTO CASA E CRONOGRAMA PAGAMEN | AJ84: =IF(Q84<>"",Q84,IF(K84<>"",K84,"")) -> 46129 | AK84: =IF(K84<>"","Sim","") -> Sim | AL84: =IF(A84="","",TEXT(A84,"000000")&"-"&IF(C84="Entrada","CR","DB")) -> 000083-DB | AM84: =IF(A84="","",LEFT(IF(H84<>"",H84,G84)&" | "&G84&" | "&S84,60)) -> Mao de obra terceirizada assentamento Ceramica | Mao de obra
... A87: 86 | B87: SÃO FRANCISCO DE PAULA - RS | C87: Saída | D87: RADIER - 44,38 M² | E87: RADIER | F87: CONCRETO | G87: Concreto Usinado fck - 25 Mpa ( Com perda de 10%) - SEM IMPERMEABILIZANTE - 140 +- 30 slump | K87: 46129 | Q87: =IF(K87="","",K87) -> 46129 | R87: RADIER - 44,38 M² | S87: Saída | RADIER - 44,38 M² | T87: Saída | RADIER | CONCRETO | U87: 21 DIAS | V87: 29 | W87: Q3 | X87: 46118 | Y87: 46129 | Z87: 79635.2 | AA87: =IF(M87<>"",M87,Z87) -> 79635.2 | AB87: =IF(L87<>"","Realizado","Previsto") -> Previsto | AC87: 0.25 | AD87: 318540.8 | AE87: 512 | AF87: m³ | AG87: 622.15 | AH87: B origem: RADIER | C origem: CONCRETO | AI87: CUSTO CASA E CRONOGRAMA PAGAMEN | AJ87: =IF(Q87<>"",Q87,IF(K87<>"",K87,"")) -> 46129 | AK87: =IF(K87<>"","Sim","") -> Sim | AL87: =IF(A87="","",TEXT(A87,"000000")&"-"&IF(C87="Entrada","CR","DB")) -> 000086-DB | AM87: =IF(A87="","",LEFT(IF(H87<>"",H87,G87)&" | "&G87&" | "&S87,60)) -> Concreto Usinado fck - 25 Mpa ( Com perda de 10%) - SEM IMPE
A88: 87 | B88: SÃO FRANCISCO DE PAULA - RS | C88: Saída | D88: RADIER - 44,38 M² | E88: RADIER | F88: SERVIÇO | G88: Ensaio compreesão corpo prova | K88: 46129 | Q88: =IF(K88="","",K88) -> 46129 | R88: RADIER - 44,38 M² | S88: Saída | RADIER - 44,38 M² | T88: Saída | RADIER | SERVIÇO | V88: 35 | W88: Q3 | X88: 46118 | Y88: 46129 | Z88: 2240 | AA88: =IF(M88<>"",M88,Z88) -> 2240 | AB88: =IF(L88<>"","Realizado","Previsto") -> Previsto | AC88: 0.5 | AD88: 4480 | AE88: 64 | AF88: unidade | AG88: 70 | AH88: B origem: RADIER | C origem: SERVIÇO | AI88: CUSTO CASA E CRONOGRAMA PAGAMEN | AJ88: =IF(Q88<>"",Q88,IF(K88<>"",K88,"")) -> 46129 | AK88: =IF(K88<>"","Sim","") -> Sim | AL88: =IF(A88="","",TEXT(A88,"000000")&"-"&IF(C88="Entrada","CR","DB")) -> 000087-DB | AM88: =IF(A88="","",LEFT(IF(H88<>"",H88,G88)&" | "&G88&" | "&S88,60)) -> Ensaio compreesão corpo prova | Ensaio compreesão corpo prov
A89: 88 | B89: SÃO FRANCISCO DE PAULA - RS | C89: Saída | D89: RADIER - 44,38 M² | E89: RADIER | F89: MADEIRA | G89: ripas de 5cm x 2,7m de 25mm | K89: 46129 | Q89: =IF(K89="","",K89) -> 46129 | R89: RADIER - 44,38 M² | S89: Saída | RADIER - 44,38 M² | T89: Saída | RADIER | MADEIRA | V89: 44 | W89: Q3 | X89: 46118 | Y89: 46129 | Z89: 1267.2 | AA89: =IF(M89<>"",M89,Z89) -> 1267.2 | AB89: =IF(L89<>"","Realizado","Previsto") -> Previsto | AC89: 0.3 | AD89: 4224 | AE89: 704 | AF89: pç | AG89: 6 | AH89: B origem: RADIER | C origem: MADEIRA | AI89: CUSTO CASA E CRONOGRAMA PAGAMEN | AJ89: =IF(Q89<>"",Q89,IF(K89<>"",K89,"")) -> 46129 | AK89: =IF(K89<>"","Sim","") -> Sim | AL89: =IF(A89="","",TEXT(A89,"000000")&"-"&IF(C89="Entrada","CR","DB")) -> 000088-DB | AM89: =IF(A89="","",LEFT(IF(H89<>"",H89,G89)&" | "&G89&" | "&S89,60)) -> ripas de 5cm x 2,7m de 25mm | ripas de 5cm x 2,7m de 25mm |
A90: 89 | B90: SÃO FRANCISCO DE PAULA - RS | C90: Saída | D90: SERVIÇOS | E90: SERVIÇOS | F90: SERVIÇOS | G90: TOTALIZADOR CUSTO GLOBAIS OBRAS - MENSAL | K90: 46129 | Q90: =IF(K90="","",K90) -> 46129 | R90: SERVIÇOS | S90: Saída | SERVIÇOS | T90: Saída | SERVIÇOS | SERVIÇOS | V90: 267 | W90: Q3 | X90: 46118 | Y90: 46129 | Z90: 590384.72 | AA90: =IF(M90<>"",M90,Z90) -> 590384.72 | AB90: =IF(L90<>"","Realizado","Previsto") -> Previsto | AD90: 5780911.4 | AF90: mês | AI90: CUSTO CASA E CRONOGRAMA PAGAMEN | AJ90: =IF(Q90<>"",Q90,IF(K90<>"",K90,"")) -> 46129 | AK90: =IF(K90<>"","Sim","") -> Sim | AL90: =IF(A90="","",TEXT(A90,"000000")&"-"&IF(C90="Entrada","CR","DB")) -> 000089-DB | AM90: =IF(A90="","",LEFT(IF(H90<>"",H90,G90)&" | "&G90&" | "&S90,60)) -> TOTALIZADOR CUSTO GLOBAIS OBRAS - MENSAL | TOTALIZADOR CUSTO
A91: 90 | B91: SÃO FRANCISCO DE PAULA - RS | C91: Saída | D91: SOLEIRAS | E91: PINGADEIRAS E SOLEIRAS | F91: MAO DE OBRA | G91: Assentamento Soleira em basalto 0,84 x 0,125 x 0,02 - cozinha | K91: 46129 | Q91: =IF(K91="","",K91) -> 46129 | R91: SOLEIRAS | S91: Saída | SOLEIRAS | T91: Saída | PINGADEIRAS E SOLEIRAS | MAO DE OBRA | U91: Faturamento para 45 dias após boletim fiscalizaçao | V91: 128 | W91: Q3 | X91: 46118 | Y91: 46129 | Z91: 299.84 | AA91: =IF(M91<>"",M91,Z91) -> 299.84 | AB91: =IF(L91<>"","Realizado","Previsto") -> Previsto | AC91: 0.0937 | AD91: 3200 | AE91: 64 | AF91: unidade | AG91: 50 | AH91: B origem: PINGADEIRAS E SOLEIRAS | C origem: MAO DE OBRA | AI91: CUSTO CASA E CRONOGRAMA PAGAMEN | AJ91: =IF(Q91<>"",Q91,IF(K91<>"",K91,"")) -> 46129 | AK91: =IF(K91<>"","Sim","") -> Sim | AL91: =IF(A91="","",TEXT(A91,"000000")&"-"&IF(C91="Entrada","CR","DB")) -> 000090-DB | AM91: =IF(A91="","",LEFT(IF(H91<>"",H91,G91)&" | "&G91&" | "&S91,60)) -> Assentamento Soleira em basalto 0,84 x 0,125 x 0,02 - cozin
A92: 91 | B92: SÃO FRANCISCO DE PAULA - RS | C92: Saída | D92: SOLEIRAS | E92: PINGADEIRAS E SOLEIRAS | F92: MAO DE OBRA | G92: Assentamento Soleira em basalto 0,94 x 0,125 x 0,02 - entrada | K92: 46129 | Q92: =IF(K92="","",K92) -> 46129 | R92: SOLEIRAS | S92: Saída | SOLEIRAS | T92: Saída | PINGADEIRAS E SOLEIRAS | MAO DE OBRA | U92: Faturamento para 45 dias após boletim fiscalizaçao | V92: 127 | W92: Q3 | X92: 46118 | Y92: 46129 | Z92: 299.84 | AA92: =IF(M92<>"",M92,Z92) -> 299.84 | AB92: =IF(L92<>"","Realizado","Previsto") -> Previsto | AC92: 0.0937 | AD92: 3200 | AE92: 64 | AF92: unidade | AG92: 50 | AH92: B origem: PINGADEIRAS E SOLEIRAS | C origem: MAO DE OBRA | AI92: CUSTO CASA E CRONOGRAMA PAGAMEN | AJ92: =IF(Q92<>"",Q92,IF(K92<>"",K92,"")) -> 46129 | AK92: =IF(K92<>"","Sim","") -> Sim | AL92: =IF(A92="","",TEXT(A92,"000000")&"-"&IF(C92="Entrada","CR","DB")) -> 000091-DB | AM92: =IF(A92="","",LEFT(IF(H92<>"",H92,G92)&" | "&G92&" | "&S92,60)) -> Assentamento Soleira em basalto 0,94 x 0,125 x 0,02 - entra
A93: 92 | B93: SÃO FRANCISCO DE PAULA - RS | C93: Saída | D93: TEXTURA EXTERNA NA COR | E93: PINTURA EXT. | F93: MAO DE OBRA | G93: Mao de obra terceirizada Textura externa | K93: 46129 | Q93: =IF(K93="","",K93) -> 46129 | R93: TEXTURA EXTERNA NA COR | S93: Saída | TEXTURA EXTERNA NA COR | T93: Saída | PINTURA EXT. | MAO DE OBRA | U93: Faturamento para 45 dias após boletim fiscalizaçao | V93: 163 | W93: Q3 | X93: 46118 | Y93: 46129 | Z93: 4275.6584 | AA93: =IF(M93<>"",M93,Z93) -> 4275.6584 | AB93: =IF(L93<>"","Realizado","Previsto") -> Previsto | AC93: 0.0937 | AD93: 45631.36 | AE93: 5564.8 | AF93: m² | AG93: 8.2 | AH93: B origem: PINTURA EXT. | C origem: MAO DE OBRA | AI93: CUSTO CASA E CRONOGRAMA PAGAMEN | AJ93: =IF(Q93<>"",Q93,IF(K93<>"",K93,"")) -> 46129 | AK93: =IF(K93<>"","Sim","") -> Sim | AL93: =IF(A93="","",TEXT(A93,"000000")&"-"&IF(C93="Entrada","CR","DB")) -> 000092-DB | AM93: =IF(A93="","",LEFT(IF(H93<>"",H93,G93)&" | "&G93&" | "&S93,60)) -> Mao de obra terceirizada Textura externa | Mao de obra terce
A94: 93 | B94: SÃO FRANCISCO DE PAULA - RS | C94: Entrada | D94: RECEITAS | E94: RECEITAS | F94: RECEITA CONTRATUAL | G94: MEDIÇÃO CONTRATUAL | K94: 46143 | Q94: =IF(K94="","",K94) -> 46143 | R94: MEDIÇÃO CONTRATUAL | S94: Entrada | MEDIÇÃO CONTRATUAL | T94: Entrada | RECEITAS | RECEITA CONTRATUAL | V94: 283 | W94: Q4 | X94: 46132 | Y94: 46143 | Z94: 758705.11 | AA94: =IF(M94<>"",M94,Z94) -> 758705.11 | AB94: =IF(L94<>"","Realizado","Previsto") -> Previsto | AD94: 8079999.9 | AI94: CUSTO CASA E CRONOGRAMA PAGAMEN | AJ94: =IF(Q94<>"",Q94,IF(K94<>"",K94,"")) -> 46143 | AK94: =IF(K94<>"","Sim","") -> Sim | AL94: =IF(A94="","",TEXT(A94,"000000")&"-"&IF(C94="Entrada","CR","DB")) -> 000093-CR | AM94: =IF(A94="","",LEFT(IF(H94<>"",H94,G94)&" | "&G94&" | "&S94,60)) -> MEDIÇÃO CONTRATUAL | MEDIÇÃO CONTRATUAL | Entrada | MEDIÇÃO
A95: 94 | B95: SÃO FRANCISCO DE PAULA - RS | C95: Saída | D95: AZULEJOS | E95: AZULEJOS | F95: INSUMO | G95: Argamassa colante AC I - Saco 20 Kg | K95: 46143 | Q95: =IF(K95="","",K95) -> 46143 | R95: AZULEJOS | S95: Saída | AZULEJOS | T95: Saída | AZULEJOS | INSUMO | U95: cartão | V95: 114 | W95: Q4 | X95: 46132 | Y95: 46143 | Z95: 4345.6 | AA95: =IF(M95<>"",M95,Z95) -> 4345.6 | AB95: =IF(L95<>"","Realizado","Previsto") -> Previsto | AC95: 0.5 | AD95: 8691.2 | AE95: 640 | AF95: Sc | AG95: 13.58 | AH95: B origem: AZULEJOS | C origem: INSUMO | AI95: CUSTO CASA E CRONOGRAMA PAGAMEN | AJ95: =IF(Q95<>"",Q95,IF(K95<>"",K95,"")) -> 46143 | AK95: =IF(K95<>"","Sim","") -> Sim | AL95: =IF(A95="","",TEXT(A95,"000000")&"-"&IF(C95="Entrada","CR","DB")) -> 000094-DB | AM95: =IF(A95="","",LEFT(IF(H95<>"",H95,G95)&" | "&G95&" | "&S95,60)) -> Argamassa colante AC I - Saco 20 Kg | Argamassa colante AC I
A96: 95 | B96: SÃO FRANCISCO DE PAULA - RS | C96: Saída | D96: AZULEJOS | E96: AZULEJOS | F96: INSUMO | G96: Espaçador cruzeta - 5mm (pacote com 100 unid) | K96: 46143 | Q96: =IF(K96="","",K96) -> 46143 | R96: AZULEJOS | S96: Saída | AZULEJOS | T96: Saída | AZULEJOS | INSUMO | U96: cartão | V96: 112 | W96: Q4 | X96: 46132 | Y96: 46143 | Z96: 134.4 | AA96: =IF(M96<>"",M96,Z96) -> 134.4 | AB96: =IF(L96<>"","Realizado","Previsto") -> Previsto | AC96: 0.5 | AD96: 268.8 | AE96: 64 | AF96: un | AG96: 4.2 | AH96: B origem: AZULEJOS | C origem: INSUMO | AI96: CUSTO CASA E CRONOGRAMA PAGAMEN | AJ96: =IF(Q96<>"",Q96,IF(K96<>"",K96,"")) -> 46143 | AK96: =IF(K96<>"","Sim","") -> Sim | AL96: =IF(A96="","",TEXT(A96,"000000")&"-"&IF(C96="Entrada","CR","DB")) -> 000095-DB | AM96: =IF(A96="","",LEFT(IF(H96<>"",H96,G96)&" | "&G96&" | "&S96,60)) -> Espaçador cruzeta - 5mm (pacote com 100 unid) | Espaçador cr
A97: 96 | B97: SÃO FRANCISCO DE PAULA - RS | C97: Saída | D97: AZULEJOS | E97: AZULEJOS | F97: MAO DE OBRA | G97: Mao de obra terceirizada assentamento Azulejo | K97: 46143 | Q97: =IF(K97="","",K97) -> 46143 | R97: AZULEJOS | S97: Saída | AZULEJOS | T97: Saída | AZULEJOS | MAO DE OBRA | U97: Faturamento para 45 dias após boletim fiscalizaçao | V97: 115 | W97: Q4 | X97: 46132 | Y97: 46143 | Z97: 7519.008 | AA97: =IF(M97<>"",M97,Z97) -> 7519.008 | AB97: =IF(L97<>"","Realizado","Previsto") -> Previsto | AC97: 0.0938 | AD97: 80160 | AE97: 1603.2 | AF97: m² | AG97: 50 | AH97: B origem: AZULEJOS | C origem: MAO DE OBRA | AI97: CUSTO CASA E CRONOGRAMA PAGAMEN | AJ97: =IF(Q97<>"",Q97,IF(K97<>"",K97,"")) -> 46143 | AK97: =IF(K97<>"","Sim","") -> Sim | AL97: =IF(A97="","",TEXT(A97,"000000")&"-"&IF(C97="Entrada","CR","DB")) -> 000096-DB | AM97: =IF(A97="","",LEFT(IF(H97<>"",H97,G97)&" | "&G97&" | "&S97,60)) -> Mao de obra terceirizada assentamento Azulejo | Mao de obra
A98: 97 | B98: SÃO FRANCISCO DE PAULA - RS | C98: Saída | D98: AZULEJOS | E98: AZULEJOS | F98: INSUMO | G98: Rejunte cimenticio | K98: 46143 | Q98: =IF(K98="","",K98) -> 46143 | R98: AZULEJOS | S98: Saída | AZULEJOS | T98: Saída | AZULEJOS | INSUMO | U98: cartão | V98: 113 | W98: Q4 | X98: 46132 | Y98: 46143 | Z98: 1104 | AA98: =IF(M98<>"",M98,Z98) -> 1104 | AB98: =IF(L98<>"","Realizado","Previsto") -> Previsto | AC98: 0.5 | AD98: 2208 | AE98: 320 | AF98: kg | AG98: 6.9 | AH98: B origem: AZULEJOS | C origem: INSUMO | AI98: CUSTO CASA E CRONOGRAMA PAGAMEN | AJ98: =IF(Q98<>"",Q98,IF(K98<>"",K98,"")) -> 46143 | AK98: =IF(K98<>"","Sim","") -> Sim | AL98: =IF(A98="","",TEXT(A98,"000000")&"-"&IF(C98="Entrada","CR","DB")) -> 000097-DB | AM98: =IF(A98="","",LEFT(IF(H98<>"",H98,G98)&" | "&G98&" | "&S98,60)) -> Rejunte cimenticio | Rejunte cimenticio | Saída | AZULEJOS
A99: 98 | B99: SÃO FRANCISCO DE PAULA - RS | C99: Saída | D99: AZULEJOS | E99: AZULEJOS | F99: REVESTIMENTO | G99: Revestimento Cerâmico PEI II - 20 X 20, cor, (perda 10%) | K99: 46143 | Q99: =IF(K99="","",K99) -> 46143 | R99: AZULEJOS | S99: Saída | AZULEJOS | T99: Saída | AZULEJOS | REVESTIMENTO | U99: cartão | V99: 111 | W99: Q4 | X99: 46132 | Y99: 46143 | Z99: 8072.416 | AA99: =IF(M99<>"",M99,Z99) -> 8072.416 | AB99: =IF(L99<>"","Realizado","Previsto") -> Previsto | AC99: 0.34 | AD99: 23742.4 | AE99: 1249.6 | AF99: m² | AG99: 19 | AH99: B origem: AZULEJOS | C origem: REVESTIMENTO | AI99: CUSTO CASA E CRONOGRAMA PAGAMEN | AJ99: =IF(Q99<>"",Q99,IF(K99<>"",K99,"")) -> 46143 | AK99: =IF(K99<>"","Sim","") -> Sim | AL99: =IF(A99="","",TEXT(A99,"000000")&"-"&IF(C99="Entrada","CR","DB")) -> 000098-DB | AM99: =IF(A99="","",LEFT(IF(H99<>"",H99,G99)&" | "&G99&" | "&S99,60)) -> Revestimento Cerâmico PEI II - 20 X 20, cor, (perda 10%) |
A100: 99 | B100: SÃO FRANCISCO DE PAULA - RS | C100: Saída | D100: CAIXA D'ÁGUA E BARRILETES | E100: BARRILETE E RESERV. | F100: Tubos e conexoes | G100: Adaptador soldável flange 25mm 3/4 | K100: 46143 | Q100: =IF(K100="","",K100) -> 46143 | R100: CAIXA D'ÁGUA E BARRILETES | S100: Saída | CAIXA D'ÁGUA E BARRILETES | T100: Saída | BARRILETE E RESERV. | Tubos e conexoes | U100: 28/56/84 | V100: 79 | W100: Q4 | X100: 46132 | Y100: 46143 | Z100: 293.76 | AA100: =IF(M100<>"",M100,Z100) -> 293.76 | AB100: =IF(L100<>"","Realizado","Previsto") -> Previsto | AC100: 0.34 | AD100: 864 | AE100: 64 | AF100: peça | AG100: 13.5 | AH100: B origem: BARRILETE E RESERV. | C origem: Tubos e conexoes | AI100: CUSTO CASA E CRONOGRAMA PAGAMEN | AJ100: =IF(Q100<>"",Q100,IF(K100<>"",K100,"")) -> 46143 | AK100: =IF(K100<>"","Sim","") -> Sim | AL100: =IF(A100="","",TEXT(A100,"000000")&"-"&IF(C100="Entrada","CR","DB")) -> 000099-DB | AM100: =IF(A100="","",LEFT(IF(H100<>"",H100,G100)&" | "&G100&" | "&S100,60)) -> Adaptador soldável flange 25mm 3/4 | Adaptador soldável flan
A101: 100 | B101: SÃO FRANCISCO DE PAULA - RS | C101: Saída | D101: CAIXA D'ÁGUA E BARRILETES | E101: BARRILETE E RESERV. | F101: Tubos e conexoes | G101: Adaptador soldável flange 32 mm | K101: 46143 | Q101: =IF(K101="","",K101) -> 46143 | R101: CAIXA D'ÁGUA E BARRILETES | S101: Saída | CAIXA D'ÁGUA E BARRILETES | T101: Saída | BARRILETE E RESERV. | Tubos e conexoes | U101: 28/56/84 | V101: 82 | W101: Q4 | X101: 46132 | Y101: 46143 | Z101: 572.0704 | AA101: =IF(M101<>"",M101,Z101) -> 572.0704 | AB101: =IF(L101<>"","Realizado","Previsto") -> Previsto | AC101: 0.34 | AD101: 1682.56 | AE101: 64 | AF101: peça | AG101: 26.29 | AH101: B origem: BARRILETE E RESERV. | C origem: Tubos e conexoes | AI101: CUSTO CASA E CRONOGRAMA PAGAMEN | AJ101: =IF(Q101<>"",Q101,IF(K101<>"",K101,"")) -> 46143 | AK101: =IF(K101<>"","Sim","") -> Sim | AL101: =IF(A101="","",TEXT(A101,"000000")&"-"&IF(C101="Entrada","CR","DB")) -> 000100-DB | AM101: =IF(A101="","",LEFT(IF(H101<>"",H101,G101)&" | "&G101&" | "&S101,60)) -> Adaptador soldável flange 32 mm | Adaptador soldável flange
A102: 101 | B102: SÃO FRANCISCO DE PAULA - RS | C102: Saída | D102: CAIXA D'ÁGUA E BARRILETES | E102: BARRILETE E RESERV. | F102: Tubos e conexoes | G102: Bucha de redução soldável curta 32mm x 25mm | K102: 46143 | Q102: =IF(K102="","",K102) -> 46143 | R102: CAIXA D'ÁGUA E BARRILETES | S102: Saída | CAIXA D'ÁGUA E BARRILETES | T102: Saída | BARRILETE E RESERV. | Tubos e conexoes | U102: 28/56/84 | V102: 85 | W102: Q4 | X102: 46132 | Y102: 46143 | Z102: 34.816 | AA102: =IF(M102<>"",M102,Z102) -> 34.816 | AB102: =IF(L102<>"","Realizado","Previsto") -> Previsto | AC102: 0.34 | AD102: 102.4 | AE102: 64 | AF102: peça | AG102: 1.6 | AH102: B origem: BARRILETE E RESERV. | C origem: Tubos e conexoes | AI102: CUSTO CASA E CRONOGRAMA PAGAMEN | AJ102: =IF(Q102<>"",Q102,IF(K102<>"",K102,"")) -> 46143 | AK102: =IF(K102<>"","Sim","") -> Sim | AL102: =IF(A102="","",TEXT(A102,"000000")&"-"&IF(C102="Entrada","CR","DB")) -> 000101-DB | AM102: =IF(A102="","",LEFT(IF(H102<>"",H102,G102)&" | "&G102&" | "&S102,60)) -> Bucha de redução soldável curta 32mm x 25mm | Bucha de reduç
A103: 102 | B103: SÃO FRANCISCO DE PAULA - RS | C103: Saída | D103: CAIXA D'ÁGUA E BARRILETES | E103: BARRILETE E RESERV. | F103: Tubos e conexoes | G103: Caixa D'Água Polietileno 500 Litros - FORTLEV | K103: 46143 | Q103: =IF(K103="","",K103) -> 46143 | R103: CAIXA D'ÁGUA E BARRILETES | S103: Saída | CAIXA D'ÁGUA E BARRILETES | T103: Saída | BARRILETE E RESERV. | Tubos e conexoes | U103: 28/56/84 | V103: 87 | W103: Q4 | X103: 46132 | Y103: 46143 | Z103: 5220.224 | AA103: =IF(M103<>"",M103,Z103) -> 5220.224 | AB103: =IF(L103<>"","Realizado","Previsto") -> Previsto | AC103: 0.34 | AD103: 15353.6 | AE103: 64 | AF103: unidade | AG103: 239.9 | AH103: B origem: BARRILETE E RESERV. | C origem: Tubos e conexoes | AI103: CUSTO CASA E CRONOGRAMA PAGAMEN | AJ103: =IF(Q103<>"",Q103,IF(K103<>"",K103,"")) -> 46143 | AK103: =IF(K103<>"","Sim","") -> Sim | AL103: =IF(A103="","",TEXT(A103,"000000")&"-"&IF(C103="Entrada","CR","DB")) -> 000102-DB | AM103: =IF(A103="","",LEFT(IF(H103<>"",H103,G103)&" | "&G103&" | "&S103,60)) -> Caixa D'Água Polietileno 500 Litros - FORTLEV | Caixa D'Água
A104: 103 | B104: SÃO FRANCISCO DE PAULA - RS | C104: Saída | D104: CAIXA D'ÁGUA E BARRILETES | E104: BARRILETE E RESERV. | F104: Tubos e conexoes | G104: Cola Pincel 175 g | K104: 46143 | Q104: =IF(K104="","",K104) -> 46143 | R104: CAIXA D'ÁGUA E BARRILETES | S104: Saída | CAIXA D'ÁGUA E BARRILETES | T104: Saída | BARRILETE E RESERV. | Tubos e conexoes | U104: 28/56/84 | V104: 86 | W104: Q4 | X104: 46132 | Y104: 46143 | Z104: 97.2672 | AA104: =IF(M104<>"",M104,Z104) -> 97.2672 | AB104: =IF(L104<>"","Realizado","Previsto") -> Previsto | AC104: 0.34 | AD104: 286.08 | AE104: 19.2 | AF104: unidade | AG104: 14.9 | AH104: B origem: BARRILETE E RESERV. | C origem: Tubos e conexoes | AI104: CUSTO CASA E CRONOGRAMA PAGAMEN | AJ104: =IF(Q104<>"",Q104,IF(K104<>"",K104,"")) -> 46143 | AK104: =IF(K104<>"","Sim","") -> Sim | AL104: =IF(A104="","",TEXT(A104,"000000")&"-"&IF(C104="Entrada","CR","DB")) -> 000103-DB | AM104: =IF(A104="","",LEFT(IF(H104<>"",H104,G104)&" | "&G104&" | "&S104,60)) -> Cola Pincel 175 g | Cola Pincel 175 g | Saída | CAIXA D'ÁGUA
A105: 104 | B105: SÃO FRANCISCO DE PAULA - RS | C105: Saída | D105: CAIXA D'ÁGUA E BARRILETES | E105: BARRILETE E RESERV. | F105: Tubos e conexoes | G105: Curva 90° Soldável 25mm | K105: 46143 | Q105: =IF(K105="","",K105) -> 46143 | R105: CAIXA D'ÁGUA E BARRILETES | S105: Saída | CAIXA D'ÁGUA E BARRILETES | T105: Saída | BARRILETE E RESERV. | Tubos e conexoes | U105: 28/56/84 | V105: 76 | W105: Q4 | X105: 46132 | Y105: 46143 | Z105: 71.1552 | AA105: =IF(M105<>"",M105,Z105) -> 71.1552 | AB105: =IF(L105<>"","Realizado","Previsto") -> Previsto | AC105: 0.34 | AD105: 209.28 | AE105: 64 | AF105: peça | AG105: 3.27 | AH105: B origem: BARRILETE E RESERV. | C origem: Tubos e conexoes | AI105: CUSTO CASA E CRONOGRAMA PAGAMEN | AJ105: =IF(Q105<>"",Q105,IF(K105<>"",K105,"")) -> 46143 | AK105: =IF(K105<>"","Sim","") -> Sim | AL105: =IF(A105="","",TEXT(A105,"000000")&"-"&IF(C105="Entrada","CR","DB")) -> 000104-DB | AM105: =IF(A105="","",LEFT(IF(H105<>"",H105,G105)&" | "&G105&" | "&S105,60)) -> Curva 90° Soldável 25mm | Curva 90° Soldável 25mm | Saída |
A106: 105 | B106: SÃO FRANCISCO DE PAULA - RS | C106: Saída | D106: CAIXA D'ÁGUA E BARRILETES | E106: BARRILETE E RESERV. | F106: Tubos e conexoes | G106: Joelho 90 soldavel 25 mm, PVC marrom, água fria | K106: 46143 | Q106: =IF(K106="","",K106) -> 46143 | R106: CAIXA D'ÁGUA E BARRILETES | S106: Saída | CAIXA D'ÁGUA E BARRILETES | T106: Saída | BARRILETE E RESERV. | Tubos e conexoes | U106: 28/56/84 | V106: 77 | W106: Q4 | X106: 46132 | Y106: 46143 | Z106: 104.448 | AA106: =IF(M106<>"",M106,Z106) -> 104.448 | AB106: =IF(L106<>"","Realizado","Previsto") -> Previsto | AC106: 0.34 | AD106: 307.2 | AE106: 384 | AF106: peça | AG106: 0.8 | AH106: B origem: BARRILETE E RESERV. | C origem: Tubos e conexoes | AI106: CUSTO CASA E CRONOGRAMA PAGAMEN | AJ106: =IF(Q106<>"",Q106,IF(K106<>"",K106,"")) -> 46143 | AK106: =IF(K106<>"","Sim","") -> Sim | AL106: =IF(A106="","",TEXT(A106,"000000")&"-"&IF(C106="Entrada","CR","DB")) -> 000105-DB | AM106: =IF(A106="","",LEFT(IF(H106<>"",H106,G106)&" | "&G106&" | "&S106,60)) -> Joelho 90 soldavel 25 mm, PVC marrom, água fria | Joelho 90
... A116: 115 | B116: SÃO FRANCISCO DE PAULA - RS | C116: Saída | D116: CAIXAS DE INSPEÇÃO E GORDURA | E116: CAIXAS DE INSPEÇÃO E GORDURA | F116: MAO DE OBRA | G116: MO Terceirizada Caixas de inspecao e gordura | K116: 46143 | Q116: =IF(K116="","",K116) -> 46143 | R116: CAIXAS DE INSPEÇÃO E GORDURA | S116: Saída | CAIXAS DE INSPEÇÃO E GORDURA | T116: Saída | CAIXAS DE INSPEÇÃO E GORDURA | MAO DE OBRA | U116: Faturamento para 45 dias após boletim fiscalizaçao | V116: 101 | W116: Q4 | X116: 46132 | Y116: 46143 | Z116: 4922.624 | AA116: =IF(M116<>"",M116,Z116) -> 4922.624 | AB116: =IF(L116<>"","Realizado","Previsto") -> Previsto | AC116: 0.0938 | AD116: 52480 | AE116: 64 | AF116: vb | AG116: 820 | AH116: B origem: CAIXAS DE INSPEÇÃO E GORDURA | C origem: MAO DE OBRA | AI116: CUSTO CASA E CRONOGRAMA PAGAMEN | AJ116: =IF(Q116<>"",Q116,IF(K116<>"",K116,"")) -> 46143 | AK116: =IF(K116<>"","Sim","") -> Sim | AL116: =IF(A116="","",TEXT(A116,"000000")&"-"&IF(C116="Entrada","CR","DB")) -> 000115-DB | AM116: =IF(A116="","",LEFT(IF(H116<>"",H116,G116)&" | "&G116&" | "&S116,60)) -> MO Terceirizada Caixas de inspecao e gordura | MO Terceiriza
A117: 116 | B117: SÃO FRANCISCO DE PAULA - RS | C117: Saída | D117: CAPITAL DE GIRO | E117: CAPITAL DE GIRO | F117: EMPRÉSTIMOS / CAPITAL DE GIRO | G117: CARTAO CREDITO SUCOPIRA | K117: 46143 | Q117: =IF(K117="","",K117) -> 46143 | R117: CAPITAL DE GIRO | S117: Saída | CAPITAL DE GIRO | T117: Saída | CAPITAL DE GIRO | EMPRÉSTIMOS / CAPITAL DE GIRO | V117: 274 | W117: Q4 | X117: 46132 | Y117: 46143 | Z117: 21190 | AA117: =IF(M117<>"",M117,Z117) -> 21190 | AB117: =IF(L117<>"","Realizado","Previsto") -> Previsto | AD117: 211900 | AH117: C origem: 163000 | AI117: CUSTO CASA E CRONOGRAMA PAGAMEN | AJ117: =IF(Q117<>"",Q117,IF(K117<>"",K117,"")) -> 46143 | AK117: =IF(K117<>"","Sim","") -> Sim | AL117: =IF(A117="","",TEXT(A117,"000000")&"-"&IF(C117="Entrada","CR","DB")) -> 000116-DB | AM117: =IF(A117="","",LEFT(IF(H117<>"",H117,G117)&" | "&G117&" | "&S117,60)) -> CARTAO CREDITO SUCOPIRA | CARTAO CREDITO SUCOPIRA | Saída |
A118: 117 | B118: SÃO FRANCISCO DE PAULA - RS | C118: Saída | D118: CAPITAL DE GIRO | E118: CAPITAL DE GIRO | F118: EMPRÉSTIMOS / CAPITAL DE GIRO | G118: EMPRÉSTIMO EXTRA | K118: 46143 | Q118: =IF(K118="","",K118) -> 46143 | R118: CAPITAL DE GIRO | S118: Saída | CAPITAL DE GIRO | T118: Saída | CAPITAL DE GIRO | EMPRÉSTIMOS / CAPITAL DE GIRO | V118: 277 | W118: Q4 | X118: 46132 | Y118: 46143 | Z118: 7670 | AA118: =IF(M118<>"",M118,Z118) -> 7670 | AB118: =IF(L118<>"","Realizado","Previsto") -> Previsto | AD118: 76700 | AH118: C origem: 59000 | AI118: CUSTO CASA E CRONOGRAMA PAGAMEN | AJ118: =IF(Q118<>"",Q118,IF(K118<>"",K118,"")) -> 46143 | AK118: =IF(K118<>"","Sim","") -> Sim | AL118: =IF(A118="","",TEXT(A118,"000000")&"-"&IF(C118="Entrada","CR","DB")) -> 000117-DB | AM118: =IF(A118="","",LEFT(IF(H118<>"",H118,G118)&" | "&G118&" | "&S118,60)) -> EMPRÉSTIMO EXTRA | EMPRÉSTIMO EXTRA | Saída | CAPITAL DE GIR
...

Sheet FLUXO_DIARIO
A1: Fluxo de Caixa Diário (previsto pendente + realizado)
A2: Previsto entra apenas enquanto o lançamento estiver sem Data_Realizada; depois disso ele migra para o realizado.
A3: Saldo inicial de caixa | B3: 720000 | D3: Início | E3: 46090 | F3: Fim | G3: 46287
A5: Data | B5: Entradas_Previstas_Pendentes | C5: Saidas_Previstas_Pendentes | D5: Entradas_Realizadas | E5: Saidas_Realizadas | F5: Movimento_Liquido_Dia | G5: Saldo_Acumulado | H5: Observacao
A6: 46090 | B6: =SUMIFS(BASE_CAIXA!$Z$2:$Z$643,BASE_CAIXA!$C$2:$C$643,"Entrada",BASE_CAIXA!$K$2:$K$643,A6,BASE_CAIXA!$L$2:$L$643,"") -> 0 | C6: =SUMIFS(BASE_CAIXA!$Z$2:$Z$643,BASE_CAIXA!$C$2:$C$643,"Saída",BASE_CAIXA!$K$2:$K$643,A6,BASE_CAIXA!$L$2:$L$643,"") -> 32000 | D6: =SUMIFS(BASE_CAIXA!$AA$2:$AA$643,BASE_CAIXA!$C$2:$C$643,"Entrada",BASE_CAIXA!$L$2:$L$643,A6) -> 0 | E6: =SUMIFS(BASE_CAIXA!$AA$2:$AA$643,BASE_CAIXA!$C$2:$C$643,"Saída",BASE_CAIXA!$L$2:$L$643,A6) -> 0 | F6: =B6-C6+D6-E6 -> -32000 | G6: =$B$3+F6 -> 688000
A7: 46091 | B7: =SUMIFS(BASE_CAIXA!$Z$2:$Z$643,BASE_CAIXA!$C$2:$C$643,"Entrada",BASE_CAIXA!$K$2:$K$643,A7,BASE_CAIXA!$L$2:$L$643,"") -> 0 | C7: =SUMIFS(BASE_CAIXA!$Z$2:$Z$643,BASE_CAIXA!$C$2:$C$643,"Saída",BASE_CAIXA!$K$2:$K$643,A7,BASE_CAIXA!$L$2:$L$643,"") -> 0 | D7: =SUMIFS(BASE_CAIXA!$AA$2:$AA$643,BASE_CAIXA!$C$2:$C$643,"Entrada",BASE_CAIXA!$L$2:$L$643,A7) -> 0 | E7: =SUMIFS(BASE_CAIXA!$AA$2:$AA$643,BASE_CAIXA!$C$2:$C$643,"Saída",BASE_CAIXA!$L$2:$L$643,A7) -> 0 | F7: =B7-C7+D7-E7 -> 0 | G7: =G6+F7 -> 688000
A8: 46092 | B8: =SUMIFS(BASE_CAIXA!$Z$2:$Z$643,BASE_CAIXA!$C$2:$C$643,"Entrada",BASE_CAIXA!$K$2:$K$643,A8,BASE_CAIXA!$L$2:$L$643,"") -> 0 | C8: =SUMIFS(BASE_CAIXA!$Z$2:$Z$643,BASE_CAIXA!$C$2:$C$643,"Saída",BASE_CAIXA!$K$2:$K$643,A8,BASE_CAIXA!$L$2:$L$643,"") -> 68500 | D8: =SUMIFS(BASE_CAIXA!$AA$2:$AA$643,BASE_CAIXA!$C$2:$C$643,"Entrada",BASE_CAIXA!$L$2:$L$643,A8) -> 0 | E8: =SUMIFS(BASE_CAIXA!$AA$2:$AA$643,BASE_CAIXA!$C$2:$C$643,"Saída",BASE_CAIXA!$L$2:$L$643,A8) -> 0 | F8: =B8-C8+D8-E8 -> -68500 | G8: =G7+F8 -> 619500
A9: 46093 | B9: =SUMIFS(BASE_CAIXA!$Z$2:$Z$643,BASE_CAIXA!$C$2:$C$643,"Entrada",BASE_CAIXA!$K$2:$K$643,A9,BASE_CAIXA!$L$2:$L$643,"") -> 0 | C9: =SUMIFS(BASE_CAIXA!$Z$2:$Z$643,BASE_CAIXA!$C$2:$C$643,"Saída",BASE_CAIXA!$K$2:$K$643,A9,BASE_CAIXA!$L$2:$L$643,"") -> 0 | D9: =SUMIFS(BASE_CAIXA!$AA$2:$AA$643,BASE_CAIXA!$C$2:$C$643,"Entrada",BASE_CAIXA!$L$2:$L$643,A9) -> 0 | E9: =SUMIFS(BASE_CAIXA!$AA$2:$AA$643,BASE_CAIXA!$C$2:$C$643,"Saída",BASE_CAIXA!$L$2:$L$643,A9) -> 0 | F9: =B9-C9+D9-E9 -> 0 | G9: =G8+F9 -> 619500
A10: 46094 | B10: =SUMIFS(BASE_CAIXA!$Z$2:$Z$643,BASE_CAIXA!$C$2:$C$643,"Entrada",BASE_CAIXA!$K$2:$K$643,A10,BASE_CAIXA!$L$2:$L$643,"") -> 0 | C10: =SUMIFS(BASE_CAIXA!$Z$2:$Z$643,BASE_CAIXA!$C$2:$C$643,"Saída",BASE_CAIXA!$K$2:$K$643,A10,BASE_CAIXA!$L$2:$L$643,"") -> 0 | D10: =SUMIFS(BASE_CAIXA!$AA$2:$AA$643,BASE_CAIXA!$C$2:$C$643,"Entrada",BASE_CAIXA!$L$2:$L$643,A10) -> 0 | E10: =SUMIFS(BASE_CAIXA!$AA$2:$AA$643,BASE_CAIXA!$C$2:$C$643,"Saída",BASE_CAIXA!$L$2:$L$643,A10) -> 0 | F10: =B10-C10+D10-E10 -> 0 | G10: =G9+F10 -> 619500
A11: 46095 | B11: =SUMIFS(BASE_CAIXA!$Z$2:$Z$643,BASE_CAIXA!$C$2:$C$643,"Entrada",BASE_CAIXA!$K$2:$K$643,A11,BASE_CAIXA!$L$2:$L$643,"") -> 0 | C11: =SUMIFS(BASE_CAIXA!$Z$2:$Z$643,BASE_CAIXA!$C$2:$C$643,"Saída",BASE_CAIXA!$K$2:$K$643,A11,BASE_CAIXA!$L$2:$L$643,"") -> 0 | D11: =SUMIFS(BASE_CAIXA!$AA$2:$AA$643,BASE_CAIXA!$C$2:$C$643,"Entrada",BASE_CAIXA!$L$2:$L$643,A11) -> 0 | E11: =SUMIFS(BASE_CAIXA!$AA$2:$AA$643,BASE_CAIXA!$C$2:$C$643,"Saída",BASE_CAIXA!$L$2:$L$643,A11) -> 0 | F11: =B11-C11+D11-E11 -> 0 | G11: =G10+F11 -> 619500
A12: 46096 | B12: =SUMIFS(BASE_CAIXA!$Z$2:$Z$643,BASE_CAIXA!$C$2:$C$643,"Entrada",BASE_CAIXA!$K$2:$K$643,A12,BASE_CAIXA!$L$2:$L$643,"") -> 0 | C12: =SUMIFS(BASE_CAIXA!$Z$2:$Z$643,BASE_CAIXA!$C$2:$C$643,"Saída",BASE_CAIXA!$K$2:$K$643,A12,BASE_CAIXA!$L$2:$L$643,"") -> 0 | D12: =SUMIFS(BASE_CAIXA!$AA$2:$AA$643,BASE_CAIXA!$C$2:$C$643,"Entrada",BASE_CAIXA!$L$2:$L$643,A12) -> 0 | E12: =SUMIFS(BASE_CAIXA!$AA$2:$AA$643,BASE_CAIXA!$C$2:$C$643,"Saída",BASE_CAIXA!$L$2:$L$643,A12) -> 0 | F12: =B12-C12+D12-E12 -> 0 | G12: =G11+F12 -> 619500
A13: 46097 | B13: =SUMIFS(BASE_CAIXA!$Z$2:$Z$643,BASE_CAIXA!$C$2:$C$643,"Entrada",BASE_CAIXA!$K$2:$K$643,A13,BASE_CAIXA!$L$2:$L$643,"") -> 0 | C13: =SUMIFS(BASE_CAIXA!$Z$2:$Z$643,BASE_CAIXA!$C$2:$C$643,"Saída",BASE_CAIXA!$K$2:$K$643,A13,BASE_CAIXA!$L$2:$L$643,"") -> 0 | D13: =SUMIFS(BASE_CAIXA!$AA$2:$AA$643,BASE_CAIXA!$C$2:$C$643,"Entrada",BASE_CAIXA!$L$2:$L$643,A13) -> 0 | E13: =SUMIFS(BASE_CAIXA!$AA$2:$AA$643,BASE_CAIXA!$C$2:$C$643,"Saída",BASE_CAIXA!$L$2:$L$643,A13) -> 0 | F13: =B13-C13+D13-E13 -> 0 | G13: =G12+F13 -> 619500
A14: 46098 | B14: =SUMIFS(BASE_CAIXA!$Z$2:$Z$643,BASE_CAIXA!$C$2:$C$643,"Entrada",BASE_CAIXA!$K$2:$K$643,A14,BASE_CAIXA!$L$2:$L$643,"") -> 0 | C14: =SUMIFS(BASE_CAIXA!$Z$2:$Z$643,BASE_CAIXA!$C$2:$C$643,"Saída",BASE_CAIXA!$K$2:$K$643,A14,BASE_CAIXA!$L$2:$L$643,"") -> 0 | D14: =SUMIFS(BASE_CAIXA!$AA$2:$AA$643,BASE_CAIXA!$C$2:$C$643,"Entrada",BASE_CAIXA!$L$2:$L$643,A14) -> 0 | E14: =SUMIFS(BASE_CAIXA!$AA$2:$AA$643,BASE_CAIXA!$C$2:$C$643,"Saída",BASE_CAIXA!$L$2:$L$643,A14) -> 0 | F14: =B14-C14+D14-E14 -> 0 | G14: =G13+F14 -> 619500
A15: 46099 | B15: =SUMIFS(BASE_CAIXA!$Z$2:$Z$643,BASE_CAIXA!$C$2:$C$643,"Entrada",BASE_CAIXA!$K$2:$K$643,A15,BASE_CAIXA!$L$2:$L$643,"") -> 0 | C15: =SUMIFS(BASE_CAIXA!$Z$2:$Z$643,BASE_CAIXA!$C$2:$C$643,"Saída",BASE_CAIXA!$K$2:$K$643,A15,BASE_CAIXA!$L$2:$L$643,"") -> 0 | D15: =SUMIFS(BASE_CAIXA!$AA$2:$AA$643,BASE_CAIXA!$C$2:$C$643,"Entrada",BASE_CAIXA!$L$2:$L$643,A15) -> 0 | E15: =SUMIFS(BASE_CAIXA!$AA$2:$AA$643,BASE_CAIXA!$C$2:$C$643,"Saída",BASE_CAIXA!$L$2:$L$643,A15) -> 0 | F15: =B15-C15+D15-E15 -> 0 | G15: =G14+F15 -> 619500
A16: 46100 | B16: =SUMIFS(BASE_CAIXA!$Z$2:$Z$643,BASE_CAIXA!$C$2:$C$643,"Entrada",BASE_CAIXA!$K$2:$K$643,A16,BASE_CAIXA!$L$2:$L$643,"") -> 0 | C16: =SUMIFS(BASE_CAIXA!$Z$2:$Z$643,BASE_CAIXA!$C$2:$C$643,"Saída",BASE_CAIXA!$K$2:$K$643,A16,BASE_CAIXA!$L$2:$L$643,"") -> 0 | D16: =SUMIFS(BASE_CAIXA!$AA$2:$AA$643,BASE_CAIXA!$C$2:$C$643,"Entrada",BASE_CAIXA!$L$2:$L$643,A16) -> 0 | E16: =SUMIFS(BASE_CAIXA!$AA$2:$AA$643,BASE_CAIXA!$C$2:$C$643,"Saída",BASE_CAIXA!$L$2:$L$643,A16) -> 0 | F16: =B16-C16+D16-E16 -> 0 | G16: =G15+F16 -> 619500
A17: 46101 | B17: =SUMIFS(BASE_CAIXA!$Z$2:$Z$643,BASE_CAIXA!$C$2:$C$643,"Entrada",BASE_CAIXA!$K$2:$K$643,A17,BASE_CAIXA!$L$2:$L$643,"") -> 0 | C17: =SUMIFS(BASE_CAIXA!$Z$2:$Z$643,BASE_CAIXA!$C$2:$C$643,"Saída",BASE_CAIXA!$K$2:$K$643,A17,BASE_CAIXA!$L$2:$L$643,"") -> 695979.2 | D17: =SUMIFS(BASE_CAIXA!$AA$2:$AA$643,BASE_CAIXA!$C$2:$C$643,"Entrada",BASE_CAIXA!$L$2:$L$643,A17) -> 0 | E17: =SUMIFS(BASE_CAIXA!$AA$2:$AA$643,BASE_CAIXA!$C$2:$C$643,"Saída",BASE_CAIXA!$L$2:$L$643,A17) -> 0 | F17: =B17-C17+D17-E17 -> -695979.2 | G17: =G16+F17 -> -76479.2
A18: 46102 | B18: =SUMIFS(BASE_CAIXA!$Z$2:$Z$643,BASE_CAIXA!$C$2:$C$643,"Entrada",BASE_CAIXA!$K$2:$K$643,A18,BASE_CAIXA!$L$2:$L$643,"") -> 0 | C18: =SUMIFS(BASE_CAIXA!$Z$2:$Z$643,BASE_CAIXA!$C$2:$C$643,"Saída",BASE_CAIXA!$K$2:$K$643,A18,BASE_CAIXA!$L$2:$L$643,"") -> 0 | D18: =SUMIFS(BASE_CAIXA!$AA$2:$AA$643,BASE_CAIXA!$C$2:$C$643,"Entrada",BASE_CAIXA!$L$2:$L$643,A18) -> 0 | E18: =SUMIFS(BASE_CAIXA!$AA$2:$AA$643,BASE_CAIXA!$C$2:$C$643,"Saída",BASE_CAIXA!$L$2:$L$643,A18) -> 0 | F18: =B18-C18+D18-E18 -> 0 | G18: =G17+F18 -> -76479.2
... A203: 46287 | B203: =SUMIFS(BASE_CAIXA!$Z$2:$Z$643,BASE_CAIXA!$C$2:$C$643,"Entrada",BASE_CAIXA!$K$2:$K$643,A203,BASE_CAIXA!$L$2:$L$643,"") -> 0 | C203: =SUMIFS(BASE_CAIXA!$Z$2:$Z$643,BASE_CAIXA!$C$2:$C$643,"Saída",BASE_CAIXA!$K$2:$K$643,A203,BASE_CAIXA!$L$2:$L$643,"") -> 0 | D203: =SUMIFS(BASE_CAIXA!$AA$2:$AA$643,BASE_CAIXA!$C$2:$C$643,"Entrada",BASE_CAIXA!$L$2:$L$643,A203) -> 0 | E203: =SUMIFS(BASE_CAIXA!$AA$2:$AA$643,BASE_CAIXA!$C$2:$C$643,"Saída",BASE_CAIXA!$L$2:$L$643,A203) -> 0 | F203: =B203-C203+D203-E203 -> 0 | G203: =G202+F203 -> -4504668.4
A204: TOTAL | B204: =SUM(B6:B203) -> 7359999.9 | C204: =SUM(C6:C203) -> 12584668 | D204: =SUM(D6:D203) -> 0 | E204: =SUM(E6:E203) -> 0 | F204: =SUM(F6:F203) -> -5224668.4 | G204: =G203 -> -4504668.4

Sheet SAUDE_FLUXO
A1: Saúde do Fluxo de Caixa
A3: Indicador | B3: Valor | D3: Observação
A4: Saldo inicial | B4: =FLUXO_DIARIO!B3 -> 720000 | D4: Preenchimento manual
A5: Entradas previstas pendentes | B5: =SUM(FLUXO_DIARIO!B6:B203) -> 7359999.9 | D5: Ainda não realizadas
A6: Saídas previstas pendentes | B6: =SUM(FLUXO_DIARIO!C6:C203) -> 12584668 | D6: Ainda não realizadas
A7: Entradas realizadas | B7: =SUM(FLUXO_DIARIO!D6:D203) -> 0 | D7: Baixadas na base
A8: Saídas realizadas | B8: =SUM(FLUXO_DIARIO!E6:E203) -> 0 | D8: Baixadas na base
A9: Caixa final projetado | B9: =FLUXO_DIARIO!G203 -> -4504668.4 | D9: Saldo ao fim do horizonte
A10: Pior saldo projetado | B10: =MIN(FLUXO_DIARIO!G6:G203) -> -4504668.4 | D10: Menor saldo acumulado
A11: Data do pior saldo | B11: =INDEX(FLUXO_DIARIO!A6:A203,MATCH(MIN(FLUXO_DIARIO!G6:G203),FLUXO_DIARIO!G6:G203,0)) -> 46227 | D11: Quando o caixa fica mais pressionado
A12: Dias com saldo negativo | B12: =COUNTIF(FLUXO_DIARIO!G6:G203,"<0") -> 187 | D12: Dias em que o caixa projetado fica abaixo de zero
A13: Cobertura de entradas vs saídas | B13: =IFERROR((SUM(FLUXO_DIARIO!B6:B203)+SUM(FLUXO_DIARIO!D6:D203))/(SUM(FLUXO_DIARIO!C6:C203)+SUM(FLUXO_DIARIO!E6:E203)),0) -> 0.58483861 | D13: Acima de 1,0x é mais confortável
A16: Data | B16: Entradas Totais do Dia | C16: Saídas Totais do Dia | D16: Líquido do Dia | E16: Saldo Acumulado | F16: Cobertura do Dia | G16: Status
A17: =FLUXO_DIARIO!A6 -> 46090 | B17: =FLUXO_DIARIO!B6+FLUXO_DIARIO!D6 -> 0 | C17: =FLUXO_DIARIO!C6+FLUXO_DIARIO!E6 -> 32000 | D17: =B17-C17 -> -32000 | E17: =FLUXO_DIARIO!G6 -> 688000 | F17: =IFERROR(B17/C17,0) -> 0 | G17: =IF(E17<0,"Crítico",IF(F17<1,"Atenção","Saudável")) -> Atenção
A18: =FLUXO_DIARIO!A7 -> 46091 | B18: =FLUXO_DIARIO!B7+FLUXO_DIARIO!D7 -> 0 | C18: =FLUXO_DIARIO!C7+FLUXO_DIARIO!E7 -> 0 | D18: =B18-C18 -> 0 | E18: =FLUXO_DIARIO!G7 -> 688000 | F18: =IFERROR(B18/C18,0) -> 0 | G18: =IF(E18<0,"Crítico",IF(F18<1,"Atenção","Saudável")) -> Atenção
A19: =FLUXO_DIARIO!A8 -> 46092 | B19: =FLUXO_DIARIO!B8+FLUXO_DIARIO!D8 -> 0 | C19: =FLUXO_DIARIO!C8+FLUXO_DIARIO!E8 -> 68500 | D19: =B19-C19 -> -68500 | E19: =FLUXO_DIARIO!G8 -> 619500 | F19: =IFERROR(B19/C19,0) -> 0 | G19: =IF(E19<0,"Crítico",IF(F19<1,"Atenção","Saudável")) -> Atenção
A20: =FLUXO_DIARIO!A9 -> 46093 | B20: =FLUXO_DIARIO!B9+FLUXO_DIARIO!D9 -> 0 | C20: =FLUXO_DIARIO!C9+FLUXO_DIARIO!E9 -> 0 | D20: =B20-C20 -> 0 | E20: =FLUXO_DIARIO!G9 -> 619500 | F20: =IFERROR(B20/C20,0) -> 0 | G20: =IF(E20<0,"Crítico",IF(F20<1,"Atenção","Saudável")) -> Atenção
A21: =FLUXO_DIARIO!A10 -> 46094 | B21: =FLUXO_DIARIO!B10+FLUXO_DIARIO!D10 -> 0 | C21: =FLUXO_DIARIO!C10+FLUXO_DIARIO!E10 -> 0 | D21: =B21-C21 -> 0 | E21: =FLUXO_DIARIO!G10 -> 619500 | F21: =IFERROR(B21/C21,0) -> 0 | G21: =IF(E21<0,"Crítico",IF(F21<1,"Atenção","Saudável")) -> Atenção
A22: =FLUXO_DIARIO!A11 -> 46095 | B22: =FLUXO_DIARIO!B11+FLUXO_DIARIO!D11 -> 0 | C22: =FLUXO_DIARIO!C11+FLUXO_DIARIO!E11 -> 0 | D22: =B22-C22 -> 0 | E22: =FLUXO_DIARIO!G11 -> 619500 | F22: =IFERROR(B22/C22,0) -> 0 | G22: =IF(E22<0,"Crítico",IF(F22<1,"Atenção","Saudável")) -> Atenção
A23: =FLUXO_DIARIO!A12 -> 46096 | B23: =FLUXO_DIARIO!B12+FLUXO_DIARIO!D12 -> 0 | C23: =FLUXO_DIARIO!C12+FLUXO_DIARIO!E12 -> 0 | D23: =B23-C23 -> 0 | E23: =FLUXO_DIARIO!G12 -> 619500 | F23: =IFERROR(B23/C23,0) -> 0 | G23: =IF(E23<0,"Crítico",IF(F23<1,"Atenção","Saudável")) -> Atenção
A24: =FLUXO_DIARIO!A13 -> 46097 | B24: =FLUXO_DIARIO!B13+FLUXO_DIARIO!D13 -> 0 | C24: =FLUXO_DIARIO!C13+FLUXO_DIARIO!E13 -> 0 | D24: =B24-C24 -> 0 | E24: =FLUXO_DIARIO!G13 -> 619500 | F24: =IFERROR(B24/C24,0) -> 0 | G24: =IF(E24<0,"Crítico",IF(F24<1,"Atenção","Saudável")) -> Atenção
A25: =FLUXO_DIARIO!A14 -> 46098 | B25: =FLUXO_DIARIO!B14+FLUXO_DIARIO!D14 -> 0 | C25: =FLUXO_DIARIO!C14+FLUXO_DIARIO!E14 -> 0 | D25: =B25-C25 -> 0 | E25: =FLUXO_DIARIO!G14 -> 619500 | F25: =IFERROR(B25/C25,0) -> 0 | G25: =IF(E25<0,"Crítico",IF(F25<1,"Atenção","Saudável")) -> Atenção
A26: =FLUXO_DIARIO!A15 -> 46099 | B26: =FLUXO_DIARIO!B15+FLUXO_DIARIO!D15 -> 0 | C26: =FLUXO_DIARIO!C15+FLUXO_DIARIO!E15 -> 0 | D26: =B26-C26 -> 0 | E26: =FLUXO_DIARIO!G15 -> 619500 | F26: =IFERROR(B26/C26,0) -> 0 | G26: =IF(E26<0,"Crítico",IF(F26<1,"Atenção","Saudável")) -> Atenção
A27: =FLUXO_DIARIO!A16 -> 46100 | B27: =FLUXO_DIARIO!B16+FLUXO_DIARIO!D16 -> 0 | C27: =FLUXO_DIARIO!C16+FLUXO_DIARIO!E16 -> 0 | D27: =B27-C27 -> 0 | E27: =FLUXO_DIARIO!G16 -> 619500 | F27: =IFERROR(B27/C27,0) -> 0 | G27: =IF(E27<0,"Crítico",IF(F27<1,"Atenção","Saudável")) -> Atenção
A28: =FLUXO_DIARIO!A17 -> 46101 | B28: =FLUXO_DIARIO!B17+FLUXO_DIARIO!D17 -> 0 | C28: =FLUXO_DIARIO!C17+FLUXO_DIARIO!E17 -> 695979.2 | D28: =B28-C28 -> -695979.2 | E28: =FLUXO_DIARIO!G17 -> -76479.2 | F28: =IFERROR(B28/C28,0) -> 0 | G28: =IF(E28<0,"Crítico",IF(F28<1,"Atenção","Saudável")) -> Crítico
... A214: =FLUXO_DIARIO!A203 -> 46287 | B214: =FLUXO_DIARIO!B203+FLUXO_DIARIO!D203 -> 0 | C214: =FLUXO_DIARIO!C203+FLUXO_DIARIO!E203 -> 0 | D214: =B214-C214 -> 0 | E214: =FLUXO_DIARIO!G203 -> -4504668.4 | F214: =IFERROR(B214/C214,0) -> 0 | G214: =IF(E214<0,"Crítico",IF(F214<1,"Atenção","Saudável")) -> Crítico

Sheet ORIGEM_RESUMIDA
B1: MUNICÍPIO: | C1: SÃO FRANCISCO DE PAULA - RS | J1: CUSTO 1 CASA: | L1: 273760.4 | M1: 13593.584 | N1: 221803.69 | O1: 92553.388 | P1: 77621.623 | Q1: 161585.88 | R1: 617320.47 | S1: 973107.25 | T1: 1254450.2 | U1: 1276242.9 | V1: 273760.4 | W1: 13593.584 | X1: 221803.69 | Y1: 92553.388 | Z1: 77621.623 | AA1: 161585.88 | AB1: 617320.47 | AC1: 973107.25 | AD1: 1254450.2 | AE1: 1276242.9
B2: QUANTIDADE CASAS | C2: 64 | J2: 90594.325 | L2: 46090 | M2: 46104 | N2: 46118 | O2: 46132 | P2: 46146 | Q2: 46160 | R2: 46174 | S2: 46188 | T2: 46202 | U2: 46216 | V2: 46090 | W2: 46104 | X2: 46118 | Y2: 46132 | Z2: 46146 | AA2: 46160 | AB2: 46174 | AC2: 46188 | AD2: 46202 | AE2: 46216
B3: ESCOPO | C3: MATERIAL CONSTRUÇÃO CASA 44,33m2 | L3: 46101 | M3: 46115 | N3: 46129 | O3: 46143 | P3: 46157 | Q3: 46171 | R3: 46185 | S3: 46199 | T3: 46213 | U3: 46227 | V3: 46101 | W3: 46115 | X3: 46129 | Y3: 46143 | Z3: 46157 | AA3: 46171 | AB3: 46185 | AC3: 46199 | AD3: 46213 | AE3: 46227
B4: SEMANA INÍCIO OBRAS: | C4: 46090 | K4: 64 CASAS | L4: DISTRIBUIÇÃO PAGAMENTO PERCENTUAL (%) | V4: DISTRIBUIÇÃO PAGAMENTO FINANCEIRO (R$)
B5: APROPIAÇÃO | C5: TIPO | D5: ITEM | E5: OBSERVAÇÕES | F5: QUANT. TOTAL | G5: UN. | H5: QUANT. UNIT | I5: CUSTO UNIT. | J5: CUSTO CASA | K5: CUSTO TOTAL | L5: Q. 1 | M5: Q. 2 | N5: Q. 3 | O5: Q. 4 | P5: Q. 5 | Q5: Q. 6 | R5: Q. 7 | S5: Q. 8 | T5: Q. 9 | U5: Q. 10 | V5: Q. 1 | W5: Q. 2 | X5: Q. 3 | Y5: Q. 4 | Z5: Q. 5 | AA5: Q. 6 | AB5: Q. 7 | AC5: Q. 8 | AD5: Q. 9 | AE5: Q. 10
D6: ESPERAS DE ESGOTO RADIER | J6: 0 | K6: 0 | V6: 0 | W6: 0 | X6: 0 | Y6: 0 | Z6: 0 | AA6: 0 | AB6: 0 | AC6: 0 | AD6: 0 | AE6: 0
B7: ESPERAS DE ESGOTO RADIER | C7: Tubos e conexoes | D7: Tubo PVC DN 40mm branco rígido para esgoto sanitário | F7: 117.76 | G7: m | H7: 1.84 | I7: 3.59 | J7: 6.6056 | K7: 422.7584 | L7: 0 | M7: 0.34 | O7: 0.33 | Q7: 0.33 | V7: 0 | W7: 143.73786 | X7: 0 | Y7: 139.51027 | Z7: 0 | AA7: 139.51027 | AB7: 0 | AC7: 0 | AD7: 0 | AE7: 0
B8: ESPERAS DE ESGOTO RADIER | C8: Tubos e conexoes | D8: Tubo PVC DN 50mm branco rígido para esgoto sanitário | F8: 584.96 | G8: m | H8: 9.14 | I8: 5.69 | J8: 52.0066 | K8: 3328.4224 | L8: 0 | M8: 0.34 | O8: 0.33 | Q8: 0.33 | V8: 0 | W8: 1131.6636 | X8: 0 | Y8: 1098.3794 | Z8: 0 | AA8: 1098.3794 | AB8: 0 | AC8: 0 | AD8: 0 | AE8: 0
B9: ESPERAS DE ESGOTO RADIER | C9: Tubos e conexoes | D9: Tubo PVC DN 75mm branco rígido para esgoto sanitário | F9: 22.4 | G9: m | H9: 0.35 | I9: 10.82 | J9: 3.787 | K9: 242.368 | L9: 0 | M9: 0.34 | O9: 0.33 | Q9: 0.33 | V9: 0 | W9: 82.40512 | X9: 0 | Y9: 79.98144 | Z9: 0 | AA9: 79.98144 | AB9: 0 | AC9: 0 | AD9: 0 | AE9: 0
B10: ESPERAS DE ESGOTO RADIER | C10: Tubos e conexoes | D10: Tubo PVC DN 100mm branco rígido para esgoto sanitário | F10: 140.8 | G10: m | H10: 2.2 | I10: 15.98 | J10: 35.156 | K10: 2249.984 | L10: 0 | M10: 0.34 | O10: 0.33 | Q10: 0.33 | V10: 0 | W10: 764.99456 | X10: 0 | Y10: 742.49472 | Z10: 0 | AA10: 742.49472 | AB10: 0 | AC10: 0 | AD10: 0 | AE10: 0
B11: ESPERAS DE ESGOTO RADIER | C11: Tubos e conexoes | D11: Joelho 90º PVC DN 100mm branco rígido para esgoto sanitário predial | F11: 64 | G11: unidade | H11: 1 | I11: 13.99 | J11: 13.99 | K11: 895.36 | L11: 0 | M11: 0.34 | O11: 0.33 | Q11: 0.33 | V11: 0 | W11: 304.4224 | X11: 0 | Y11: 295.4688 | Z11: 0 | AA11: 295.4688 | AB11: 0 | AC11: 0 | AD11: 0 | AE11: 0
B12: ESPERAS DE ESGOTO RADIER | C12: Tubos e conexoes | D12: Joelho 90º PVC DN 40mm branco rígido para esgoto sanitário predial | F12: 128 | G12: unidade | H12: 2 | I12: 3.09 | J12: 6.18 | K12: 395.52 | L12: 0 | M12: 0.34 | O12: 0.33 | Q12: 0.33 | V12: 0 | W12: 134.4768 | X12: 0 | Y12: 130.5216 | Z12: 0 | AA12: 130.5216 | AB12: 0 | AC12: 0 | AD12: 0 | AE12: 0
B13: ESPERAS DE ESGOTO RADIER | C13: Tubos e conexoes | D13: Joelho 45º PVC DN 40mm branco rígido para esgoto sanitário predial | F13: 64 | G13: unidade | H13: 1 | I13: 1.4 | J13: 1.4 | K13: 89.6 | L13: 0 | M13: 0.34 | O13: 0.33 | Q13: 0.33 | V13: 0 | W13: 30.464 | X13: 0 | Y13: 29.568 | Z13: 0 | AA13: 29.568 | AB13: 0 | AC13: 0 | AD13: 0 | AE13: 0
B14: ESPERAS DE ESGOTO RADIER | C14: Tubos e conexoes | D14: Joelho 90º PVC DN 50mm branco junta elástica para esgoto sanitário | F14: 384 | G14: unidade | H14: 6 | I14: 5.72 | J14: 34.32 | K14: 2196.48 | L14: 0 | M14: 0.34 | O14: 0.33 | Q14: 0.33 | V14: 0 | W14: 746.8032 | X14: 0 | Y14: 724.8384 | Z14: 0 | AA14: 724.8384 | AB14: 0 | AC14: 0 | AD14: 0 | AE14: 0
B15: ESPERAS DE ESGOTO RADIER | C15: Tubos e conexoes | D15: Joelho 45º PVC DN 50mm branco rígido para esgoto sanitário predial | F15: 64 | G15: unidade | H15: 1 | I15: 6 | J15: 6 | K15: 384 | L15: 0 | M15: 0.34 | O15: 0.33 | Q15: 0.33 | V15: 0 | W15: 130.56 | X15: 0 | Y15: 126.72 | Z15: 0 | AA15: 126.72 | AB15: 0 | AC15: 0 | AD15: 0 | AE15: 0
B16: ESPERAS DE ESGOTO RADIER | C16: Tubos e conexoes | D16: Junção simples PVC DN 50x50mm branco rígido para esgoto sanitário predial | F16: 64 | G16: unidade | H16: 1 | I16: 17.98 | J16: 17.98 | K16: 1150.72 | L16: 0 | M16: 0.34 | O16: 0.33 | Q16: 0.33 | V16: 0 | W16: 391.2448 | X16: 0 | Y16: 379.7376 | Z16: 0 | AA16: 379.7376 | AB16: 0 | AC16: 0 | AD16: 0 | AE16: 0
B17: ESPERAS DE ESGOTO RADIER | C17: Tubos e conexoes | D17: Junção de Redução invertica PVC DN 100x50mm branco rígido para esgoto sanitário predial | F17: 64 | G17: unidade | H17: 1 | I17: 21.56 | J17: 21.56 | K17: 1379.84 | L17: 0 | M17: 0.34 | O17: 0.33 | Q17: 0.33 | V17: 0 | W17: 469.1456 | X17: 0 | Y17: 455.3472 | Z17: 0 | AA17: 455.3472 | AB17: 0 | AC17: 0 | AD17: 0 | AE17: 0
B18: ESPERAS DE ESGOTO RADIER | C18: Tubos e conexoes | D18: TE DN 50x50mm PVC branco rígido para esgoto sanitário predial | F18: 64 | G18: unidade | H18: 1 | I18: 4.96 | J18: 4.96 | K18: 317.44 | L18: 0 | M18: 0.34 | O18: 0.33 | Q18: 0.33 | V18: 0 | W18: 107.9296 | X18: 0 | Y18: 104.7552 | Z18: 0 | AA18: 104.7552 | AB18: 0 | AC18: 0 | AD18: 0 | AE18: 0
... B26: ESPERAS DE ESGOTO RADIER | C26: Tubos e conexoes | D26: Tubo DN 25 mm, PVC Rígido Soldável Marrom | F26: 64 | G26: Barra | H26: 1 | I26: 16.07 | J26: 16.07 | K26: 1028.48 | L26: 0 | M26: 0.34 | O26: 0.33 | Q26: 0.33 | V26: 0 | W26: 349.6832 | X26: 0 | Y26: 339.3984 | Z26: 0 | AA26: 339.3984 | AB26: 0 | AC26: 0 | AD26: 0 | AE26: 0
B27: ESPERAS DE ESGOTO RADIER | C27: MAO DE OBRA | D27: Mao de obra Terceirizada Hidrosanitario Radier | E27: EMPREITA: PAGTO EM 45 DIAS APÓS BOLETIM DE FISCALIZAÇÃO | F27: 64 | G27: vb | H27: 1 | I27: 0 | J27: 0 | K27: 0 | V27: 0 | W27: 0 | X27: 0 | Y27: 0 | Z27: 0 | AA27: 0 | AB27: 0 | AC27: 0 | AD27: 0 | AE27: 0
D28: RADIER - 44,38 M² | E28: 16 radiers por semana | F28: 0 | J28: 0 | K28: 0 | V28: 0 | W28: 0 | X28: 0 | Y28: 0 | Z28: 0 | AA28: 0 | AB28: 0 | AC28: 0 | AD28: 0 | AE28: 0
B29: RADIER | C29: CONCRETO | D29: Concreto Usinado fck - 25 Mpa ( Com perda de 10%) - SEM IMPERMEABILIZANTE - 140 +- 30 slump | E29: 21 DIAS | F29: 512 | G29: m³ | H29: 8 | I29: 622.15 | J29: 4977.2 | K29: 318540.8 | M29: 0.25 | N29: 0.25 | O29: 0.25 | P29: 0.25 | V29: 0 | W29: 79635.2 | X29: 79635.2 | Y29: 79635.2 | Z29: 79635.2 | AA29: 0 | AB29: 0 | AC29: 0 | AD29: 0 | AE29: 0
B30: RADIER | C30: CONCRETO | D30: Bomba de concreto ( Taxa divide 1 casa e 1 radier ) | E30: 21 DIAS: uma diaria de bomba faz 3 radies por dia | F30: 8 | G30: vb | H30: 0.125 | I30: 2200 | J30: 275 | K30: 17600 | M30: 0.25 | N30: 0.25 | O30: 0.25 | P30: 0.25 | V30: 0 | W30: 4400 | X30: 4400 | Y30: 4400 | Z30: 4400 | AA30: 0 | AB30: 0 | AC30: 0 | AD30: 0 | AE30: 0
B31: RADIER | C31: Agregado | D31: Brita graduada (lastro para nivelamento) - 10 cm esp.; 15% penetração no solo | E31: 30/60 dias | F31: 371.9008 | G31: m³ | H31: 5.81095 | I31: 91 | J31: 528.79645 | K31: 33842.973 | M31: 0.5 | N31: 0.5 | V31: 0 | W31: 16921.486 | X31: 16921.486 | Y31: 0 | Z31: 0 | AA31: 0 | AB31: 0 | AC31: 0 | AD31: 0 | AE31: 0
B32: RADIER | C32: INSUMO | D32: Lona 150 micras | F32: 3392 | G32: m² | H32: 53 | I32: 2.6 | J32: 137.8 | K32: 8819.2 | M32: 0.5 | O32: 0.5 | V32: 0 | W32: 4409.6 | X32: 0 | Y32: 4409.6 | Z32: 0 | AA32: 0 | AB32: 0 | AC32: 0 | AD32: 0 | AE32: 0
B33: RADIER | C33: INSUMO | D33: Espaçador tipo centopeia - 5 unid. por m² - 50 mm | F33: 16640 | G33: unidade | H33: 260 | I33: 1 | J33: 260 | K33: 16640 | M33: 0.5 | O33: 0.5 | V33: 0 | W33: 8320 | X33: 0 | Y33: 8320 | Z33: 0 | AA33: 0 | AB33: 0 | AC33: 0 | AD33: 0 | AE33: 0
B34: RADIER | C34: FERRAGEM | D34: Aço - Tela Q-138 - 5.0 c/10 - (245 x 600 cm) (frete de 300 + ipi de 133 incluido | F34: 512 | G34: telas | H34: 8 | I34: 234.5 | J34: 1876 | K34: 120064 | M34: 0.34 | O34: 0.33 | Q34: 0.33 | V34: 0 | W34: 40821.76 | X34: 0 | Y34: 39621.12 | Z34: 0 | AA34: 39621.12 | AB34: 0 | AC34: 0 | AD34: 0 | AE34: 0
B35: RADIER | C35: SERVIÇO | D35: Ensaio compreesão corpo prova | F35: 64 | G35: unidade | H35: 1 | I35: 70 | J35: 70 | K35: 4480 | M35: 0.5 | N35: 0.5 | V35: 0 | W35: 2240 | X35: 2240 | Y35: 0 | Z35: 0 | AA35: 0 | AB35: 0 | AC35: 0 | AD35: 0 | AE35: 0
B36: RADIER | C36: FERRAGEM | D36: Arame Recozido bwg 18 | F36: 32 | G36: kg | H36: 0.5 | I36: 12 | J36: 6 | K36: 384 | L36: 0 | M36: 0.5 | O36: 0.5 | V36: 0 | W36: 192 | X36: 0 | Y36: 192 | Z36: 0 | AA36: 0 | AB36: 0 | AC36: 0 | AD36: 0 | AE36: 0
B37: RADIER | C37: INSUMO | D37: Cimento PortlanD CP IV 32 para limpeza da bomba | F37: 10.666667 | G37: kg | H37: 0.16666667 | I37: 49 | J37: 8.1666667 | K37: 522.66667 | L37: 0 | M37: 0.5 | O37: 0.5 | V37: 0 | W37: 261.33333 | X37: 0 | Y37: 261.33333 | Z37: 0 | AA37: 0 | AB37: 0 | AC37: 0 | AD37: 0 | AE37: 0
B38: RADIER | C38: INSUMO | D38: Desmoldante TECNOMOR | F38: 96 | G38: litros | H38: 1.5 | I38: 26 | J38: 39 | K38: 2496 | L38: 0 | M38: 0.5 | O38: 0.5 | V38: 0 | W38: 1248 | X38: 0 | Y38: 1248 | Z38: 0 | AA38: 0 | AB38: 0 | AC38: 0 | AD38: 0 | AE38: 0
B39: RADIER | C39: RATEIO | D39: impermeabilizante para lateral das chapas de compensado (link no grupo) | F39: 2 | G39: unidade | H39: 0.03125 | I39: 57 | J39: 1.78125 | K39: 114 | L39: 0 | M39: 0.5 | O39: 0.5 | V39: 0 | W39: 57 | X39: 0 | Y39: 57 | Z39: 0 | AA39: 0 | AB39: 0 | AC39: 0 | AD39: 0 | AE39: 0
B40: RADIER | C40: RATEIO | D40: Forma para Radier - chapa de compensado naval plastificado 14mm | F40: 35 | G40: unidade | H40: 0.546875 | I40: 138.24 | J40: 75.6 | K40: 4838.4 | L40: 0 | M40: 0.5 | O40: 0.5 | V40: 0 | W40: 2419.2 | X40: 0 | Y40: 2419.2 | Z40: 0 | AA40: 0 | AB40: 0 | AC40: 0 | AD40: 0 | AE40: 0
B41: RADIER | C41: RATEIO | D41: Forma para Radier - tabua pinus 25mm para montagem do gabarito 2,70 m x 15cm | F41: 176 | G41: unidade | H41: 2.75 | I41: 15.5 | J41: 42.625 | K41: 2728 | L41: 0 | M41: 0.5 | O41: 0.5 | V41: 0 | W41: 1364 | X41: 0 | Y41: 1364 | Z41: 0 | AA41: 0 | AB41: 0 | AC41: 0 | AD41: 0 | AE41: 0
B42: RADIER | C42: LOCAÇAO | D42: Placa vibratoria reversivél CR5 | F42: 21.333333 | G42: dia | H42: 0.33333333 | I42: 150 | J42: 50 | K42: 3200 | M42: 0.5 | O42: 0.5 | V42: 0 | W42: 1600 | X42: 0 | Y42: 1600 | Z42: 0 | AA42: 0 | AB42: 0 | AC42: 0 | AD42: 0 | AE42: 0
B43: RADIER | C43: MAO DE OBRA | D43: Mao de obra Terceirizada Radier | F43: 64 | G43: vb | H43: 1 | I43: 2000 | J43: 2000 | K43: 128000 | L43: 0.19335938 | M43: 0.32243359 | N43: 0 | O43: 0.25 | P43: 0.23420704 | V43: 24750 | W43: 41271.499 | X43: 0 | Y43: 32000 | Z43: 29978.501 | AA43: 0 | AB43: 0 | AC43: 0 | AD43: 0 | AE43: 0
B44: RADIER | C44: MADEIRA | D44: ripas de 5cm x 2,7m de 25mm | F44: 704 | G44: pç | H44: 11 | I44: 6 | J44: 66 | K44: 4224 | L44: 0.4 | M44: 0.3 | N44: 0.3 | V44: 1689.6 | W44: 1267.2 | X44: 1267.2 | Y44: 0 | Z44: 0 | AA44: 0 | AB44: 0 | AC44: 0 | AD44: 0 | AE44: 0
F45: 0 | J45: 0 | K45: 0 | V45: 0 | W45: 0 | X45: 0 | Y45: 0 | Z45: 0 | AA45: 0 | AB45: 0 | AC45: 0 | AD45: 0 | AE45: 0
B46: RADIER | C46: FERRAGEM | D46: Prego 17 x 27 cabeça dupla | F46: 140 | G46: kg | H46: 2.1875 | I46: 13.107143 | J46: 28.671875 | K46: 1835 | L46: 0 | M46: 0.5 | O46: 0.5 | V46: 0 | W46: 917.5 | X46: 0 | Y46: 917.5 | Z46: 0 | AA46: 0 | AB46: 0 | AC46: 0 | AD46: 0 | AE46: 0
D47: PAREDES (102,5m² de área interna e externa) (44,38² de Laje) | F47: 0 | J47: 0 | K47: 0 | V47: 0 | W47: 0 | X47: 0 | Y47: 0 | Z47: 0 | AA47: 0 | AB47: 0 | AC47: 0 | AD47: 0 | AE47: 0
B48: PAREDES COM CONCRETO | C48: FABRICA | D48: contrato industrializaçao paredes | E48: 20 | F48: 20 | G48: unidade | H48: 0.3125 | I48: 16000 | J48: 5000 | K48: 320000 | L48: 0.3 | N48: 0.2333 | P48: 0.2333 | R48: 0.2333 | V48: 96000 | W48: 0 | X48: 74656 | Y48: 0 | Z48: 74656 | AA48: 0 | AB48: 74656 | AC48: 0 | AD48: 0 | AE48: 0
B49: PAREDES COM CONCRETO | C49: FABRICA | D49: contrato industrializaçao paredes | E49: 20 | F49: 20 | G49: unidade | H49: 0.3125 | I49: 16000 | J49: 5000 | K49: 320000 | L49: 0.3 | N49: 0.2333 | P49: 0.2333 | R49: 0.2333 | V49: 96000 | W49: 0 | X49: 74656 | Y49: 0 | Z49: 74656 | AA49: 0 | AB49: 74656 | AC49: 0 | AD49: 0 | AE49: 0
B50: PAREDES COM CONCRETO | C50: FABRICA | D50: contrato industrializaçao paredes | E50: 24 | F50: 24 | G50: unidade | H50: 0.375 | I50: 16000 | J50: 6000 | K50: 384000 | L50: 0.3 | N50: 0.2333 | P50: 0.2333 | R50: 0.233 | V50: 115200 | W50: 0 | X50: 89587.2 | Y50: 0 | Z50: 89587.2 | AA50: 0 | AB50: 89472 | AC50: 0 | AD50: 0 | AE50: 0
B51: PAREDES COM CONCRETO | C51: FABRICA | D51: material FERRO: KIT Parede e Laje - FOB na Fabrica | E51: 20 | F51: 20 | G51: unidade | H51: 0.3125 | I51: 6724.38 | J51: 2101.3688 | K51: 134487.6 | L51: 0 | M51: 0 | N51: 0.14453204 | O51: 0.07226602 | P51: 0.30351728 | Q51: 0.15898524 | R51: 0.24570447 | S51: 0.074994946 | T51: 0 | U51: 0 | V51: 0 | W51: 0 | X51: 19437.767 | Y51: 9718.8836 | Z51: 40819.311 | AA51: 21381.544 | AB51: 33044.204 | AC51: 10085.89 | AD51: 0 | AE51: 0
B52: PAREDES COM CONCRETO | C52: FABRICA | D52: material FERRO: KIT Parede e Laje - FOB na Fabrica | E52: 20 | F52: 20 | G52: unidade | H52: 0.3125 | I52: 6724.38 | J52: 2101.3688 | K52: 134487.6 | L52: 0 | M52: 0 | N52: 0.14453204 | O52: 0.07226602 | P52: 0.30351728 | Q52: 0.15898524 | R52: 0.24570447 | S52: 0.074994946 | T52: 0 | U52: 0 | V52: 0 | W52: 0 | X52: 19437.767 | Y52: 9718.8836 | Z52: 40819.311 | AA52: 21381.544 | AB52: 33044.204 | AC52: 10085.89 | AD52: 0 | AE52: 0
B53: PAREDES COM CONCRETO | C53: FABRICA | D53: material FERRO: KIT Parede e Laje - FOB na Fabrica | E53: 24 | F53: 24 | G53: unidade | H53: 0.375 | I53: 6724.38 | J53: 2521.6425 | K53: 161385.12 | L53: 0 | M53: 0 | N53: 0.14453204 | O53: 0.07226602 | P53: 0.30351728 | Q53: 0.15898524 | R53: 0.24570447 | S53: 0.074994946 | T53: 0 | U53: 0 | V53: 0 | W53: 0 | X53: 23325.321 | Y53: 11662.66 | Z53: 48983.173 | AA53: 25657.853 | AB53: 39653.045 | AC53: 12103.068 | AD53: 0 | AE53: 0
B54: PAREDES COM CONCRETO | C54: FABRICA | D54: material CIMENTO : KIT Parede e Laje - FOB na Fabrica | E54: 20 | F54: 20 | G54: unidade | H54: 0.3125 | I54: 9275.626 | J54: 2898.6331 | K54: 185512.52 | L54: 0 | M54: 0 | N54: 0.20689655 | O54: 0.20689655 | P54: 0.20689655 | Q54: 0.20689655 | R54: 0.17241379 | S54: 0 | T54: 0 | U54: 0 | V54: 0 | W54: 0 | X54: 38381.901 | Y54: 38381.901 | Z54: 38381.901 | AA54: 38381.901 | AB54: 31984.917 | AC54: 0 | AD54: 0 | AE54: 0
B55: PAREDES COM CONCRETO | C55: FABRICA | D55: material CIMENTO : KIT Parede e Laje - FOB na Fabrica | E55: 20 | F55: 20 | G55: unidade | H55: 0.3125 | I55: 9275.626 | J55: 2898.6331 | K55: 185512.52 | L55: 0 | M55: 0 | N55: 0.20689655 | O55: 0.20689655 | P55: 0.20689655 | Q55: 0.20689655 | R55: 0.17241379 | S55: 0 | T55: 0 | U55: 0 | V55: 0 | W55: 0 | X55: 38381.901 | Y55: 38381.901 | Z55: 38381.901 | AA55: 38381.901 | AB55: 31984.917 | AC55: 0 | AD55: 0 | AE55: 0
B56: PAREDES COM CONCRETO | C56: FABRICA | D56: material CIMENTO : KIT Parede e Laje - FOB na Fabrica | E56: 24 | F56: 24 | G56: unidade | H56: 0.375 | I56: 9275.626 | J56: 3478.3598 | K56: 222615.02 | L56: 0 | M56: 0 | N56: 0.20689655 | O56: 0.20689655 | P56: 0.20689655 | Q56: 0.20689655 | R56: 0.17241379 | S56: 0 | T56: 0 | U56: 0 | V56: 0 | W56: 0 | X56: 46058.281 | Y56: 46058.281 | Z56: 46058.281 | AA56: 46058.281 | AB56: 38381.901 | AC56: 0 | AD56: 0 | AE56: 0
B57: PAREDES COM CONCRETO | C57: TRANSPORTE | D57: mobilizaçao e desmobilização equipe montagem | E57: 45 dias após boletim fiscalizaçao | F57: 6 | G57: m³ | H57: 0.09375 | I57: 1247.4 | J57: 116.94375 | K57: 7484.4 | O57: 0.3 | P57: 0.3 | Q57: 0.4 | V57: 0 | W57: 0 | X57: 0 | Y57: 2245.32 | Z57: 2245.32 | AA57: 2993.76 | AB57: 0 | AC57: 0 | AD57: 0 | AE57: 0
B58: PAREDES COM CONCRETO | C58: MAO DE OBRA | D58: Montagem de paredes pré-moldadas (içamento, prumo, alinhamento e escoramento com grauteamento) – até 35 t | E58: 45 dias após boletim fiscalizaçao | F58: 896 | G58: m³ | H58: 14 | I58: 178.571 | J58: 2499.994 | K58: 159999.62 | N58: 0.0937 | O58: 0.0938 | P58: 0.33695 | Q58: 0.2225 | R58: 0.25305 | V58: 0 | W58: 0 | X58: 14991.964 | Y58: 15007.964 | Z58: 53911.871 | AA58: 35599.915 | AB58: 40487.903 | AC58: 0 | AD58: 0 | AE58: 0
B59: PAREDES COM CONCRETO | C59: TRANSPORTE | D59: Transporte de paredes e lajes (carreta + munck + carga/descarga) – até 120 km | E59: 50% A VISTA E 50% FATURADO PRA 30 DIAS: 2 casas no bitrem (3k/viagem)e 4 lages de casa na vardeleia (4k/viagem) | F59: 7680 | G59: km | H59: 120 | I59: 21 | J59: 2520 | K59: 161280 | O59: 0.3 | P59: 0.3 | Q59: 0.4 | V59: 0 | W59: 0 | X59: 0 | Y59: 48384 | Z59: 48384 | AA59: 64512 | AB59: 0 | AC59: 0 | AD59: 0 | AE59: 0
B60: PAREDES COM CONCRETO | C60: LOCAÇAO | D60: Icamento para montagem canteiro de obra - Guindaste | E60: 30 DIAS | F60: 64 | G60: diaria | H60: 1 | I60: 2800 | J60: 2800 | K60: 179200 | O60: 0.3 | P60: 0.3 | Q60: 0.4 | V60: 0 | W60: 0 | X60: 0 | Y60: 53760 | Z60: 53760 | AA60: 71680 | AB60: 0 | AC60: 0 | AD60: 0 | AE60: 0
D61: GRAUTEAMENTO | F61: 0 | J61: 0 | K61: 0 | V61: 0 | W61: 0 | X61: 0 | Y61: 0 | Z61: 0 | AA61: 0 | AB61: 0 | AC61: 0 | AD61: 0 | AE61: 0
B62: GRAUTEAMENTO | C62: CONCRETO | D62: graute: cimento PortlanD CP IV 32 | E62: 0,7m³ de graute por casa. 1m3= 12 saco cimento, 30 balde areia e 30 balde brita zero | F62: 576 | G62: saco | H62: 9 | I62: 49 | J62: 441 | K62: 28224 | O62: 0.5 | Q62: 0.5 | V62: 0 | W62: 0 | X62: 0 | Y62: 14112 | Z62: 0 | AA62: 14112 | AB62: 0 | AC62: 0 | AD62: 0 | AE62: 0
B63: GRAUTEAMENTO | C63: CONCRETO | D63: graute: areia grossa | E63: 0,7m³ de graute por casa. 1m3= 12 saco cimento, 30 balde areia e 30 balde brita zero | F63: 38.4 | G63: m3 | H63: 0.6 | I63: 140 | J63: 84 | K63: 5376 | O63: 1 | V63: 0 | W63: 0 | X63: 0 | Y63: 5376 | Z63: 0 | AA63: 0 | AB63: 0 | AC63: 0 | AD63: 0 | AE63: 0
B64: GRAUTEAMENTO | C64: CONCRETO | D64: graute: pedrisco (brita zero) | E64: 0,7m³ de graute por casa. 1m3= 12 saco cimento, 30 balde areia e 30 balde brita zero | F64: 38.4 | G64: m3 | H64: 0.6 | I64: 130 | J64: 78 | K64: 4992 | O64: 1 | V64: 0 | W64: 0 | X64: 0 | Y64: 4992 | Z64: 0 | AA64: 0 | AB64: 0 | AC64: 0 | AD64: 0 | AE64: 0
B65: GRAUTEAMENTO | C65: MADEIRA | D65: Formas de tábua aparelhada de 20x2,5x540cm para fechamento de pilares | F65: 170.66667 | G65: unidade | H65: 2.6666667 | I65: 32.45 | J65: 86.533333 | K65: 5538.1333 | O65: 1 | V65: 0 | W65: 0 | X65: 0 | Y65: 5538.1333 | Z65: 0 | AA65: 0 | AB65: 0 | AC65: 0 | AD65: 0 | AE65: 0
B66: GRAUTEAMENTO | C66: LOCAÇAO | D66: Locação betoneira para bater o graute | F66: 3 | G66: diaria | H66: 0.046875 | I66: 700 | J66: 32.8125 | K66: 2100 | O66: 0.3 | P66: 0.3 | Q66: 0.4 | V66: 0 | W66: 0 | X66: 0 | Y66: 630 | Z66: 630 | AA66: 840 | AB66: 0 | AC66: 0 | AD66: 0 | AE66: 0
B67: GRAUTEAMENTO | C67: INSUMO | D67: Aditivo supercristalizante Penetron | F67: 256 | G67: litros | H67: 4 | I67: 38 | J67: 152 | K67: 9728 | O67: 0.5 | Q67: 0.5 | V67: 0 | W67: 0 | X67: 0 | Y67: 4864 | Z67: 0 | AA67: 4864 | AB67: 0 | AC67: 0 | AD67: 0 | AE67: 0
B68: GRAUTEAMENTO | C68: MAO DE OBRA | D68: Lançamento, adensamento e acabamento de graute estrutural em pilares | E68: Faturamento para 45 dias após boletim fiscalizaçao | F68: 0 | G68: saco | I68: 0 | J68: 0 | K68: 0 | V68: 0 | W68: 0 | X68: 0 | Y68: 0 | Z68: 0 | AA68: 0 | AB68: 0 | AC68: 0 | AD68: 0 | AE68: 0
D69: IMPERMEABILIZAÇÃO | F69: 0 | J69: 0 | K69: 0 | V69: 0 | W69: 0 | X69: 0 | Y69: 0 | Z69: 0 | AA69: 0 | AB69: 0 | AC69: 0 | AD69: 0 | AE69: 0
B70: IMPERMEABILIZAÇAO INTERNA | C70: INSUMO | D70: Membrana líquida de poliuretano bicomponente 15Kg flexivel | F70: 64 | G70: caixa | H70: 1 | I70: 45 | J70: 45 | K70: 2880 | O70: 0.5 | Q70: 0.5 | V70: 0 | W70: 0 | X70: 0 | Y70: 1440 | Z70: 0 | AA70: 1440 | AB70: 0 | AC70: 0 | AD70: 0 | AE70: 0
B71: IMPERMEABILIZAÇAO INTERNA | C71: INSUMO | D71: Membrana líquida de poliuretano bicomponente 15Kg semi flexivel | F71: 128 | G71: caixa | H71: 2 | I71: 45 | J71: 90 | K71: 5760 | O71: 0.5 | Q71: 0.5 | V71: 0 | W71: 0 | X71: 0 | Y71: 2880 | Z71: 0 | AA71: 2880 | AB71: 0 | AC71: 0 | AD71: 0 | AE71: 0
B72: IMPERMEABILIZAÇAO INTERNA | C72: INSUMO | D72: Tela de Poliester | F72: 320 | G72: m² | H72: 5 | I72: 7.0474 | J72: 35.237 | K72: 2255.168 | O72: 0.5 | Q72: 0.5 | V72: 0 | W72: 0 | X72: 0 | Y72: 1127.584 | Z72: 0 | AA72: 1127.584 | AB72: 0 | AC72: 0 | AD72: 0 | AE72: 0
B73: IMPERMEABILIZAÇAO INTERNA | C73: MAO DE OBRA | D73: Mao de obra Impermeabilização de áreas úmidas | E73: Faturamento para 45 dias após boletim fiscalizaçao | F73: 64 | G73: vb | H73: 1 | I73: 420 | J73: 420 | K73: 26880 | N73: 0.0937 | O73: 0.0938 | P73: 0.33695 | Q73: 0.2225 | R73: 0.25305 | V73: 0 | W73: 0 | X73: 2518.656 | Y73: 2521.344 | Z73: 9057.216 | AA73: 5980.8 | AB73: 6801.984 | AC73: 0 | AD73: 0 | AE73: 0
B74: IMPERMEABILIZAÇAO INTERNA | C74: MAO DE OBRA | D74: Mao de obra Impermeabilização de junta | E74: Faturamento para 45 dias após boletim fiscalizaçao | F74: 64 | G74: vb | H74: 1 | I74: 0 | J74: 0 | K74: 0 | N74: 0.0937 | O74: 0.0938 | P74: 0.33695 | Q74: 0.2225 | R74: 0.25305 | V74: 0 | W74: 0 | X74: 0 | Y74: 0 | Z74: 0 | AA74: 0 | AB74: 0 | AC74: 0 | AD74: 0 | AE74: 0
D75: CAIXA D'ÁGUA E BARRILETES | F75: 0 | J75: 0 | K75: 0 | V75: 0 | W75: 0 | X75: 0 | Y75: 0 | Z75: 0 | AA75: 0 | AB75: 0 | AC75: 0 | AD75: 0 | AE75: 0
B76: BARRILETE E RESERV. | C76: Tubos e conexoes | D76: Curva 90° Soldável 25mm | E76: 28/56/84 | F76: 64 | G76: peça | H76: 1 | I76: 3.27 | J76: 3.27 | K76: 209.28 | O76: 0.34 | Q76: 0.33 | S76: 0.33 | V76: 0 | W76: 0 | X76: 0 | Y76: 71.1552 | Z76: 0 | AA76: 69.0624 | AB76: 0 | AC76: 69.0624 | AD76: 0 | AE76: 0
B77: BARRILETE E RESERV. | C77: Tubos e conexoes | D77: Joelho 90 soldavel 25 mm, PVC marrom, água fria | E77: 28/56/84 | F77: 384 | G77: peça | H77: 6 | I77: 0.8 | J77: 4.8 | K77: 307.2 | O77: 0.34 | Q77: 0.33 | S77: 0.33 | V77: 0 | W77: 0 | X77: 0 | Y77: 104.448 | Z77: 0 | AA77: 101.376 | AB77: 0 | AC77: 101.376 | AD77: 0 | AE77: 0
B78: BARRILETE E RESERV. | C78: Tubos e conexoes | D78: Joelho 90 soldavel 32 mm, PVC marrom, água fria | E78: 28/56/84 | F78: 128 | G78: peça | H78: 2 | I78: 2.66 | J78: 5.32 | K78: 340.48 | O78: 0.34 | Q78: 0.33 | S78: 0.33 | V78: 0 | W78: 0 | X78: 0 | Y78: 115.7632 | Z78: 0 | AA78: 112.3584 | AB78: 0 | AC78: 112.3584 | AD78: 0 | AE78: 0
B79: BARRILETE E RESERV. | C79: Tubos e conexoes | D79: Adaptador soldável flange 25mm 3/4 | E79: 28/56/84 | F79: 64 | G79: peça | H79: 1 | I79: 13.5 | J79: 13.5 | K79: 864 | O79: 0.34 | Q79: 0.33 | S79: 0.33 | V79: 0 | W79: 0 | X79: 0 | Y79: 293.76 | Z79: 0 | AA79: 285.12 | AB79: 0 | AC79: 285.12 | AD79: 0 | AE79: 0
B80: BARRILETE E RESERV. | C80: Tubos e conexoes | D80: Registro PVC Esfera Borboleta Soldável 25MM | E80: 28/56/84 | F80: 64 | G80: peça | H80: 1 | I80: 23 | J80: 23 | K80: 1472 | O80: 0.34 | Q80: 0.33 | S80: 0.33 | V80: 0 | W80: 0 | X80: 0 | Y80: 500.48 | Z80: 0 | AA80: 485.76 | AB80: 0 | AC80: 485.76 | AD80: 0 | AE80: 0
B81: BARRILETE E RESERV. | C81: Tubos e conexoes | D81: Registro PVC Esfera Borboleta Soldável 32MM | E81: 28/56/84 | F81: 64 | G81: peça | H81: 1 | I81: 30 | J81: 30 | K81: 1920 | O81: 0.34 | Q81: 0.33 | S81: 0.33 | V81: 0 | W81: 0 | X81: 0 | Y81: 652.8 | Z81: 0 | AA81: 633.6 | AB81: 0 | AC81: 633.6 | AD81: 0 | AE81: 0
B82: BARRILETE E RESERV. | C82: Tubos e conexoes | D82: Adaptador soldável flange 32 mm | E82: 28/56/84 | F82: 64 | G82: peça | H82: 1 | I82: 26.29 | J82: 26.29 | K82: 1682.56 | O82: 0.34 | Q82: 0.33 | S82: 0.33 | V82: 0 | W82: 0 | X82: 0 | Y82: 572.0704 | Z82: 0 | AA82: 555.2448 | AB82: 0 | AC82: 555.2448 | AD82: 0 | AE82: 0
B83: BARRILETE E RESERV. | C83: Tubos e conexoes | D83: LuvaPVC soldavél - 32 mm | E83: 28/56/84 | F83: 128 | G83: peça | H83: 2 | I83: 3.2 | J83: 6.4 | K83: 409.6 | O83: 0.34 | Q83: 0.33 | S83: 0.33 | V83: 0 | W83: 0 | X83: 0 | Y83: 139.264 | Z83: 0 | AA83: 135.168 | AB83: 0 | AC83: 135.168 | AD83: 0 | AE83: 0
B84: BARRILETE E RESERV. | C84: Tubos e conexoes | D84: TE PVC Soldável 32 MM | E84: 28/56/84 | F84: 128 | G84: peça | H84: 2 | I84: 4.13 | J84: 8.26 | K84: 528.64 | O84: 0.34 | Q84: 0.33 | S84: 0.33 | V84: 0 | W84: 0 | X84: 0 | Y84: 179.7376 | Z84: 0 | AA84: 174.4512 | AB84: 0 | AC84: 174.4512 | AD84: 0 | AE84: 0
B85: BARRILETE E RESERV. | C85: Tubos e conexoes | D85: Bucha de redução soldável curta 32mm x 25mm | E85: 28/56/84 | F85: 64 | G85: peça | H85: 1 | I85: 1.6 | J85: 1.6 | K85: 102.4 | O85: 0.34 | Q85: 0.33 | S85: 0.33 | V85: 0 | W85: 0 | X85: 0 | Y85: 34.816 | Z85: 0 | AA85: 33.792 | AB85: 0 | AC85: 33.792 | AD85: 0 | AE85: 0
B86: BARRILETE E RESERV. | C86: Tubos e conexoes | D86: Cola Pincel 175 g | E86: 28/56/84 | F86: 19.2 | G86: unidade | H86: 0.3 | I86: 14.9 | J86: 4.47 | K86: 286.08 | O86: 0.34 | Q86: 0.33 | S86: 0.33 | V86: 0 | W86: 0 | X86: 0 | Y86: 97.2672 | Z86: 0 | AA86: 94.4064 | AB86: 0 | AC86: 94.4064 | AD86: 0 | AE86: 0
B87: BARRILETE E RESERV. | C87: Tubos e conexoes | D87: Caixa D'Água Polietileno 500 Litros - FORTLEV | E87: 28/56/84 | F87: 64 | G87: unidade | H87: 1 | I87: 239.9 | J87: 239.9 | K87: 15353.6 | O87: 0.34 | Q87: 0.33 | S87: 0.33 | V87: 0 | W87: 0 | X87: 0 | Y87: 5220.224 | Z87: 0 | AA87: 5066.688 | AB87: 0 | AC87: 5066.688 | AD87: 0 | AE87: 0
... B90: BARRILETE E RESERV. | C90: Tubos e conexoes | D90: Tubo DN 32 mm, PVC Rígido Soldável Marrom | E90: 28/56/84 | F90: 96 | G90: Barra | H90: 1.5 | I90: 58.92 | J90: 88.38 | K90: 5656.32 | O90: 0.34 | Q90: 0.33 | S90: 0.33 | V90: 0 | W90: 0 | X90: 0 | Y90: 1923.1488 | Z90: 0 | AA90: 1866.5856 | AB90: 0 | AC90: 1866.5856 | AD90: 0 | AE90: 0
B91: BARRILETE E RESERV. | C91: MAO DE OBRA | D91: Mao de obra instalaçao Caixa de agua e barrilete | E91: Faturamento para 45 dias após boletim fiscalizaçao | F91: 64 | G91: vb | H91: 1 | I91: 0 | J91: 0 | K91: 0 | N91: 0.0937 | O91: 0.0938 | P91: 0.33695 | Q91: 0.2225 | R91: 0.25305 | V91: 0 | W91: 0 | X91: 0 | Y91: 0 | Z91: 0 | AA91: 0 | AB91: 0 | AC91: 0 | AD91: 0 | AE91: 0
D92: CAIXAS DE INSPEÇÃO E GORDURA | F92: 0 | J92: 0 | K92: 0 | V92: 0 | W92: 0 | X92: 0 | Y92: 0 | Z92: 0 | AA92: 0 | AB92: 0 | AC92: 0 | AD92: 0 | AE92: 0
B93: CAIXAS DE INSPEÇÃO E GORDURA | C93: Pre moldado | D93: Caixa inspecao 60x60x40 pre moldada com tampa | E93: Faturamento para 30/60 | F93: 192 | G93: unidade | H93: 3 | I93: 160 | J93: 480 | K93: 30720 | P93: 1 | V93: 0 | W93: 0 | X93: 0 | Y93: 0 | Z93: 30720 | AA93: 0 | AB93: 0 | AC93: 0 | AD93: 0 | AE93: 0
B94: CAIXAS DE INSPEÇÃO E GORDURA | C94: Pre moldado | D94: Caixa gordura 40x40x40 pre moldada com tampa | E94: Faturamento para 30/60 | F94: 64 | G94: unidade | H94: 1 | I94: 90 | J94: 90 | K94: 5760 | P94: 1 | V94: 0 | W94: 0 | X94: 0 | Y94: 0 | Z94: 5760 | AA94: 0 | AB94: 0 | AC94: 0 | AD94: 0 | AE94: 0
B95: CAIXAS DE INSPEÇÃO E GORDURA | C95: Agregado | D95: Areia grossa | E95: Faturamento para 30/60 | F95: 4.928 | G95: m³ | H95: 0.077 | I95: 91 | J95: 7.007 | K95: 448.448 | P95: 1 | V95: 0 | W95: 0 | X95: 0 | Y95: 0 | Z95: 448.448 | AA95: 0 | AB95: 0 | AC95: 0 | AD95: 0 | AE95: 0
B96: CAIXAS DE INSPEÇÃO E GORDURA | C96: Agregado | D96: lastro de brita 01 - 10cm | E96: Faturamento para 30/60 | F96: 192 | G96: m³ | H96: 3 | I96: 3.74 | J96: 11.22 | K96: 718.08 | P96: 1 | V96: 0 | W96: 0 | X96: 0 | Y96: 0 | Z96: 718.08 | AA96: 0 | AB96: 0 | AC96: 0 | AD96: 0 | AE96: 0
B97: CAIXAS DE INSPEÇÃO E GORDURA | C97: Tubos e conexoes | D97: Tubo pvc 100mm - Rede de Esgoto | E97: Faturamento para 30/60 | F97: 807.68 | G97: m | H97: 12.62 | I97: 16 | J97: 201.92 | K97: 12922.88 | P97: 0.34 | R97: 0.33 | T97: 0.33 | V97: 0 | W97: 0 | X97: 0 | Y97: 0 | Z97: 4393.7792 | AA97: 0 | AB97: 4264.5504 | AC97: 0 | AD97: 4264.5504 | AE97: 0
B98: CAIXAS DE INSPEÇÃO E GORDURA | C98: Tubos e conexoes | D98: Tubo pvc 50mm - Rede de Esgoto | E98: Faturamento para 30/60 | F98: 115.2 | G98: m | H98: 1.8 | I98: 5.68 | J98: 10.224 | K98: 654.336 | P98: 0.34 | R98: 0.33 | T98: 0.33 | V98: 0 | W98: 0 | X98: 0 | Y98: 0 | Z98: 222.47424 | AA98: 0 | AB98: 215.93088 | AC98: 0 | AD98: 215.93088 | AE98: 0
B99: CAIXAS DE INSPEÇÃO E GORDURA | C99: Tubos e conexoes | D99: Tubo pvc 40mm - Rede de Esgoto | E99: Faturamento para 30/60 | F99: 172.8 | G99: m | H99: 2.7 | I99: 3.59 | J99: 9.693 | K99: 620.352 | P99: 0.34 | R99: 0.33 | T99: 0.33 | V99: 0 | W99: 0 | X99: 0 | Y99: 0 | Z99: 210.91968 | AA99: 0 | AB99: 204.71616 | AC99: 0 | AD99: 204.71616 | AE99: 0
B100: CAIXAS DE INSPEÇÃO E GORDURA | C100: EQUIPAMENTO | D100: Locação de miniescavadeira - nivelamento e abertura de valas para caixa de gordura e hidrosanitario do radier | E100: Faturamento para 30/60 | F100: 70.4 | G100: h | H100: 1.1 | I100: 220 | J100: 242 | K100: 15488 | O100: 0.5 | P100: 0.5 | V100: 0 | W100: 0 | X100: 0 | Y100: 7744 | Z100: 7744 | AA100: 0 | AB100: 0 | AC100: 0 | AD100: 0 | AE100: 0
B101: CAIXAS DE INSPEÇÃO E GORDURA | C101: MAO DE OBRA | D101: MO Terceirizada Caixas de inspecao e gordura | E101: Faturamento para 45 dias após boletim fiscalizaçao | F101: 64 | G101: vb | H101: 1 | I101: 820 | J101: 820 | K101: 52480 | N101: 0.0937 | O101: 0.0938 | P101: 0.33695 | Q101: 0.2225 | R101: 0.25305 | V101: 0 | W101: 0 | X101: 4917.376 | Y101: 4922.624 | Z101: 17683.136 | AA101: 11676.8 | AB101: 13280.064 | AC101: 0 | AD101: 0 | AE101: 0
D102: COBERTURA | F102: 0 | J102: 0 | K102: 0 | V102: 0 | W102: 0 | X102: 0 | Y102: 0 | Z102: 0 | AA102: 0 | AB102: 0 | AC102: 0 | AD102: 0 | AE102: 0
B103: COBERTURA | C103: FABRICA | D103: Estrutura SteelFrame com tesouras | E103: cartão | F103: 64 | G103: unidade | H103: 1 | I103: 3100 | J103: 3100 | K103: 198400 | O103: 0.3 | P103: 0 | Q103: 0.6 | V103: 0 | W103: 0 | X103: 0 | Y103: 59520 | Z103: 0 | AA103: 119040 | AB103: 0 | AC103: 0 | AD103: 0 | AE103: 0
B104: COBERTURA | C104: TELHAS | D104: Telha fibrocimento 6mm 2,44x1,1m | E104: cartão | F104: 1536 | G104: unidade | H104: 24 | I104: 49.5 | J104: 1188 | K104: 76032 | O104: 0.5 | P104: 0 | Q104: 0.5 | V104: 0 | W104: 0 | X104: 0 | Y104: 38016 | Z104: 0 | AA104: 38016 | AB104: 0 | AC104: 0 | AD104: 0 | AE104: 0
B105: COBERTURA | C105: TELHAS | D105: Cumeeira fibrocimento - 20º 6mm | E105: cartão | F105: 384 | G105: unidade | H105: 6 | I105: 35.9 | J105: 215.4 | K105: 13785.6 | O105: 0.5 | P105: 0 | Q105: 0.5 | V105: 0 | W105: 0 | X105: 0 | Y105: 6892.8 | Z105: 0 | AA105: 6892.8 | AB105: 0 | AC105: 0 | AD105: 0 | AE105: 0
B106: COBERTURA | C106: FERRAGEM | D106: Parafuso telheiro 1/4" x 110 mm com arruela/vedante: 150 un. | E106: cartão | F106: 7040 | G106: und | H106: 110 | I106: 1.19 | J106: 130.9 | K106: 8377.6 | O106: 0.5 | P106: 0 | Q106: 0.5 | R106: 0.35 | V106: 0 | W106: 0 | X106: 0 | Y106: 4188.8 | Z106: 0 | AA106: 4188.8 | AB106: 2932.16 | AC106: 0 | AD106: 0 | AE106: 0
B107: COBERTURA | C107: MAO DE OBRA | D107: Mao de obra terceirizada montagem e telhamento | E107: Faturamento para 45 dias após boletim fiscalizaçao | F107: 64 | G107: vb | H107: 1 | I107: 1550 | J107: 1550 | K107: 99200 | N107: 0.0937 | O107: 0.0938 | P107: 0.33695 | Q107: 0.2225 | R107: 0.25305 | V107: 0 | W107: 0 | X107: 9295.04 | Y107: 9304.96 | Z107: 33425.44 | AA107: 22072 | AB107: 25102.56 | AC107: 0 | AD107: 0 | AE107: 0
D108: RUFOS | F108: 0 | J108: 0 | K108: 0 | V108: 0 | W108: 0 | X108: 0 | Y108: 0 | Z108: 0 | AA108: 0 | AB108: 0 | AC108: 0 | AD108: 0 | AE108: 0
B109: COBERTURA | C109: FABRICA | D109: Rufos e calhas | E109: cartão | F109: 2304 | G109: metro | H109: 36 | I109: 50 | J109: 1800 | K109: 115200 | O109: 0.5 | Q109: 0.5 | V109: 0 | W109: 0 | X109: 0 | Y109: 57600 | Z109: 0 | AA109: 57600 | AB109: 0 | AC109: 0 | AD109: 0 | AE109: 0
...

Sheet AGENDA_BANCARIA
A1: Agenda Bancária — movimentos esperados para aparecer no banco/fatura
A2: Esta aba traduz a BASE_CAIXA em eventos de extrato. Ela é o ponto de comparação com o extrato colado em EXTRATO_IMPORTADO.
A4: Base_ID | B4: ID_Concil | C4: Data_Compensacao_Prevista | D4: Tipo_Movimento | E4: Valor_Esperado | F4: Forma_Pagamento | G4: Meio_Financeiro | H4: Conta_Origem | I4: Fornecedor_Cliente | J4: Item_Resumo | K4: Lote_Pagto | L4: Documento | M4: Historico_Padrao_Extrato | N4: Status_Concil | O4: Data_Conciliada | P4: Valor_Conciliado | Q4: Historico_Extrato_Real | R4: Linha_Extrato | S4: Diferenca_Valor | T4: Diferenca_Dias
A5: =IF(BASE_CAIXA!A2="","",BASE_CAIXA!A2) -> 1 | B5: =IF(A5="","",BASE_CAIXA!AL2) -> 000001-CR | C5: =IF(A5="","",BASE_CAIXA!AJ2) -> 46080 | D5: =IF(A5="","",IF(BASE_CAIXA!C2="Entrada","Crédito","Débito")) -> Crédito | E5: =IF(A5="","",BASE_CAIXA!AA2) -> 720000 | F5: =IF(A5="","",BASE_CAIXA!N2) -> PIX | G5: =IF(A5="","",BASE_CAIXA!O2) -> 0 | H5: =IF(A5="","",BASE_CAIXA!P2) -> 0 | I5: =IF(A5="","",IF(BASE_CAIXA!H2<>"",BASE_CAIXA!H2,BASE_CAIXA!G2)) -> FM SOLUÇÕES EM BEBIDAS | J5: =IF(A5="","",BASE_CAIXA!G2) -> MEDIÇÃO CONTRATUAL | K5: =IF(A5="","",BASE_CAIXA!I2) -> INVEST_01 | L5: =IF(A5="","",BASE_CAIXA!J2) -> 0 | M5: =IF(A5="","",BASE_CAIXA!AM2) -> FM SOLUÇÕES EM BEBIDAS | MEDIÇÃO CONTRATUAL | Entrada | MEDI | N5: =IF(A5="","",IF(R5<>"",IF(AND(ABS(S5)<=0.01,ABS(T5)<=3),"Conciliado","Divergente"),IF(TODAY()>C5,"Pendente vencido","Previsto"))) -> Pendente vencido | O5: =IFERROR(INDEX(EXTRATO_IMPORTADO!$A$5:$A$404,MATCH(B5,EXTRATO_IMPORTADO!$I$5:$I$404,0)),"") | P5: =IFERROR(INDEX(EXTRATO_IMPORTADO!$F$5:$F$404,MATCH(B5,EXTRATO_IMPORTADO!$I$5:$I$404,0)),"") | Q5: =IFERROR(INDEX(EXTRATO_IMPORTADO!$B$5:$B$404,MATCH(B5,EXTRATO_IMPORTADO!$I$5:$I$404,0)),"") | R5: =IFERROR(MATCH(B5,EXTRATO_IMPORTADO!$I$5:$I$404,0),"") | S5: =IF(OR(A5="",P5=""),"",P5-E5) | T5: =IF(OR(A5="",O5=""),"",O5-C5)
A6: =IF(BASE_CAIXA!A3="","",BASE_CAIXA!A3) -> 2 | B6: =IF(A6="","",BASE_CAIXA!AL3) -> 000002-DB | C6: =IF(A6="","",BASE_CAIXA!AJ3) -> 46092 | D6: =IF(A6="","",IF(BASE_CAIXA!C3="Entrada","Crédito","Débito")) -> Débito | E6: =IF(A6="","",BASE_CAIXA!AA3) -> 64000 | F6: =IF(A6="","",BASE_CAIXA!N3) -> 0 | G6: =IF(A6="","",BASE_CAIXA!O3) -> 0 | H6: =IF(A6="","",BASE_CAIXA!P3) -> 0 | I6: =IF(A6="","",IF(BASE_CAIXA!H3<>"",BASE_CAIXA!H3,BASE_CAIXA!G3)) -> CAUÇÃO | J6: =IF(A6="","",BASE_CAIXA!G3) -> CAUÇÃO | K6: =IF(A6="","",BASE_CAIXA!I3) -> 0 | L6: =IF(A6="","",BASE_CAIXA!J3) -> 0 | M6: =IF(A6="","",BASE_CAIXA!AM3) -> CAUÇÃO | CAUÇÃO | Saída | DESPESAS ACESSÓRIAS | N6: =IF(A6="","",IF(R6<>"",IF(AND(ABS(S6)<=0.01,ABS(T6)<=3),"Conciliado","Divergente"),IF(TODAY()>C6,"Pendente vencido","Previsto"))) -> Previsto | O6: =IFERROR(INDEX(EXTRATO_IMPORTADO!$A$5:$A$404,MATCH(B6,EXTRATO_IMPORTADO!$I$5:$I$404,0)),"") | P6: =IFERROR(INDEX(EXTRATO_IMPORTADO!$F$5:$F$404,MATCH(B6,EXTRATO_IMPORTADO!$I$5:$I$404,0)),"") | Q6: =IFERROR(INDEX(EXTRATO_IMPORTADO!$B$5:$B$404,MATCH(B6,EXTRATO_IMPORTADO!$I$5:$I$404,0)),"") | R6: =IFERROR(MATCH(B6,EXTRATO_IMPORTADO!$I$5:$I$404,0),"") | S6: =IF(OR(A6="",P6=""),"",P6-E6) | T6: =IF(OR(A6="",O6=""),"",O6-C6)
A7: =IF(BASE_CAIXA!A4="","",BASE_CAIXA!A4) -> 3 | B7: =IF(A7="","",BASE_CAIXA!AL4) -> 000003-DB | C7: =IF(A7="","",BASE_CAIXA!AJ4) -> 46090 | D7: =IF(A7="","",IF(BASE_CAIXA!C4="Entrada","Crédito","Débito")) -> Débito | E7: =IF(A7="","",BASE_CAIXA!AA4) -> 16000 | F7: =IF(A7="","",BASE_CAIXA!N4) -> 0 | G7: =IF(A7="","",BASE_CAIXA!O4) -> 0 | H7: =IF(A7="","",BASE_CAIXA!P4) -> 0 | I7: =IF(A7="","",IF(BASE_CAIXA!H4<>"",BASE_CAIXA!H4,BASE_CAIXA!G4)) -> LOGISTICA GESTÃO VISITA À OBRA | J7: =IF(A7="","",BASE_CAIXA!G4) -> LOGISTICA GESTÃO VISITA À OBRA | K7: =IF(A7="","",BASE_CAIXA!I4) -> 0 | L7: =IF(A7="","",BASE_CAIXA!J4) -> 0 | M7: =IF(A7="","",BASE_CAIXA!AM4) -> LOGISTICA GESTÃO VISITA À OBRA | LOGISTICA GESTÃO VISITA À O | N7: =IF(A7="","",IF(R7<>"",IF(AND(ABS(S7)<=0.01,ABS(T7)<=3),"Conciliado","Divergente"),IF(TODAY()>C7,"Pendente vencido","Previsto"))) -> Previsto | O7: =IFERROR(INDEX(EXTRATO_IMPORTADO!$A$5:$A$404,MATCH(B7,EXTRATO_IMPORTADO!$I$5:$I$404,0)),"") | P7: =IFERROR(INDEX(EXTRATO_IMPORTADO!$F$5:$F$404,MATCH(B7,EXTRATO_IMPORTADO!$I$5:$I$404,0)),"") | Q7: =IFERROR(INDEX(EXTRATO_IMPORTADO!$B$5:$B$404,MATCH(B7,EXTRATO_IMPORTADO!$I$5:$I$404,0)),"") | R7: =IFERROR(MATCH(B7,EXTRATO_IMPORTADO!$I$5:$I$404,0),"") | S7: =IF(OR(A7="",P7=""),"",P7-E7) | T7: =IF(OR(A7="",O7=""),"",O7-C7)
A8: =IF(BASE_CAIXA!A5="","",BASE_CAIXA!A5) -> 4 | B8: =IF(A8="","",BASE_CAIXA!AL5) -> 000004-DB | C8: =IF(A8="","",BASE_CAIXA!AJ5) -> 46090 | D8: =IF(A8="","",IF(BASE_CAIXA!C5="Entrada","Crédito","Débito")) -> Débito | E8: =IF(A8="","",BASE_CAIXA!AA5) -> 16000 | F8: =IF(A8="","",BASE_CAIXA!N5) -> 0 | G8: =IF(A8="","",BASE_CAIXA!O5) -> 0 | H8: =IF(A8="","",BASE_CAIXA!P5) -> 0 | I8: =IF(A8="","",IF(BASE_CAIXA!H5<>"",BASE_CAIXA!H5,BASE_CAIXA!G5)) -> SEGURO | J8: =IF(A8="","",BASE_CAIXA!G5) -> SEGURO | K8: =IF(A8="","",BASE_CAIXA!I5) -> 0 | L8: =IF(A8="","",BASE_CAIXA!J5) -> 0 | M8: =IF(A8="","",BASE_CAIXA!AM5) -> SEGURO | SEGURO | Saída | DESPESAS ACESSÓRIAS | N8: =IF(A8="","",IF(R8<>"",IF(AND(ABS(S8)<=0.01,ABS(T8)<=3),"Conciliado","Divergente"),IF(TODAY()>C8,"Pendente vencido","Previsto"))) -> Previsto | O8: =IFERROR(INDEX(EXTRATO_IMPORTADO!$A$5:$A$404,MATCH(B8,EXTRATO_IMPORTADO!$I$5:$I$404,0)),"") | P8: =IFERROR(INDEX(EXTRATO_IMPORTADO!$F$5:$F$404,MATCH(B8,EXTRATO_IMPORTADO!$I$5:$I$404,0)),"") | Q8: =IFERROR(INDEX(EXTRATO_IMPORTADO!$B$5:$B$404,MATCH(B8,EXTRATO_IMPORTADO!$I$5:$I$404,0)),"") | R8: =IFERROR(MATCH(B8,EXTRATO_IMPORTADO!$I$5:$I$404,0),"") | S8: =IF(OR(A8="",P8=""),"",P8-E8) | T8: =IF(OR(A8="",O8=""),"",O8-C8)
A9: =IF(BASE_CAIXA!A6="","",BASE_CAIXA!A6) -> 5 | B9: =IF(A9="","",BASE_CAIXA!AL6) -> 000005-DB | C9: =IF(A9="","",BASE_CAIXA!AJ6) -> 46092 | D9: =IF(A9="","",IF(BASE_CAIXA!C6="Entrada","Crédito","Débito")) -> Débito | E9: =IF(A9="","",BASE_CAIXA!AA6) -> 2500 | F9: =IF(A9="","",BASE_CAIXA!N6) -> 0 | G9: =IF(A9="","",BASE_CAIXA!O6) -> 0 | H9: =IF(A9="","",BASE_CAIXA!P6) -> 0 | I9: =IF(A9="","",IF(BASE_CAIXA!H6<>"",BASE_CAIXA!H6,BASE_CAIXA!G6)) -> Bebedouro | J9: =IF(A9="","",BASE_CAIXA!G6) -> Bebedouro | K9: =IF(A9="","",BASE_CAIXA!I6) -> 0 | L9: =IF(A9="","",BASE_CAIXA!J6) -> 0 | M9: =IF(A9="","",BASE_CAIXA!AM6) -> Bebedouro | Bebedouro | Saída | GESTÃO LOCAL | N9: =IF(A9="","",IF(R9<>"",IF(AND(ABS(S9)<=0.01,ABS(T9)<=3),"Conciliado","Divergente"),IF(TODAY()>C9,"Pendente vencido","Previsto"))) -> Previsto | O9: =IFERROR(INDEX(EXTRATO_IMPORTADO!$A$5:$A$404,MATCH(B9,EXTRATO_IMPORTADO!$I$5:$I$404,0)),"") | P9: =IFERROR(INDEX(EXTRATO_IMPORTADO!$F$5:$F$404,MATCH(B9,EXTRATO_IMPORTADO!$I$5:$I$404,0)),"") | Q9: =IFERROR(INDEX(EXTRATO_IMPORTADO!$B$5:$B$404,MATCH(B9,EXTRATO_IMPORTADO!$I$5:$I$404,0)),"") | R9: =IFERROR(MATCH(B9,EXTRATO_IMPORTADO!$I$5:$I$404,0),"") | S9: =IF(OR(A9="",P9=""),"",P9-E9) | T9: =IF(OR(A9="",O9=""),"",O9-C9)
A10: =IF(BASE_CAIXA!A7="","",BASE_CAIXA!A7) -> 6 | B10: =IF(A10="","",BASE_CAIXA!AL7) -> 000006-DB | C10: =IF(A10="","",BASE_CAIXA!AJ7) -> 46092 | D10: =IF(A10="","",IF(BASE_CAIXA!C7="Entrada","Crédito","Débito")) -> Débito | E10: =IF(A10="","",BASE_CAIXA!AA7) -> 2000 | F10: =IF(A10="","",BASE_CAIXA!N7) -> 0 | G10: =IF(A10="","",BASE_CAIXA!O7) -> 0 | H10: =IF(A10="","",BASE_CAIXA!P7) -> 0 | I10: =IF(A10="","",IF(BASE_CAIXA!H7<>"",BASE_CAIXA!H7,BASE_CAIXA!G7)) -> Placa da obra | J10: =IF(A10="","",BASE_CAIXA!G7) -> Placa da obra | K10: =IF(A10="","",BASE_CAIXA!I7) -> 0 | L10: =IF(A10="","",BASE_CAIXA!J7) -> 0 | M10: =IF(A10="","",BASE_CAIXA!AM7) -> Placa da obra | Placa da obra | Saída | GESTÃO LOCAL | N10: =IF(A10="","",IF(R10<>"",IF(AND(ABS(S10)<=0.01,ABS(T10)<=3),"Conciliado","Divergente"),IF(TODAY()>C10,"Pendente vencido","Previsto"))) -> Previsto | O10: =IFERROR(INDEX(EXTRATO_IMPORTADO!$A$5:$A$404,MATCH(B10,EXTRATO_IMPORTADO!$I$5:$I$404,0)),"") | P10: =IFERROR(INDEX(EXTRATO_IMPORTADO!$F$5:$F$404,MATCH(B10,EXTRATO_IMPORTADO!$I$5:$I$404,0)),"") | Q10: =IFERROR(INDEX(EXTRATO_IMPORTADO!$B$5:$B$404,MATCH(B10,EXTRATO_IMPORTADO!$I$5:$I$404,0)),"") | R10: =IFERROR(MATCH(B10,EXTRATO_IMPORTADO!$I$5:$I$404,0),"") | S10: =IF(OR(A10="",P10=""),"",P10-E10) | T10: =IF(OR(A10="",O10=""),"",O10-C10)
A11: =IF(BASE_CAIXA!A8="","",BASE_CAIXA!A8) -> 7 | B11: =IF(A11="","",BASE_CAIXA!AL8) -> 000007-DB | C11: =IF(A11="","",BASE_CAIXA!AJ8) -> 46101 | D11: =IF(A11="","",IF(BASE_CAIXA!C8="Entrada","Crédito","Débito")) -> Débito | E11: =IF(A11="","",BASE_CAIXA!AA8) -> 6000 | F11: =IF(A11="","",BASE_CAIXA!N8) -> 0 | G11: =IF(A11="","",BASE_CAIXA!O8) -> 0 | H11: =IF(A11="","",BASE_CAIXA!P8) -> 0 | I11: =IF(A11="","",IF(BASE_CAIXA!H8<>"",BASE_CAIXA!H8,BASE_CAIXA!G8)) -> TOPOGRAFO | J11: =IF(A11="","",BASE_CAIXA!G8) -> TOPOGRAFO | K11: =IF(A11="","",BASE_CAIXA!I8) -> 0 | L11: =IF(A11="","",BASE_CAIXA!J8) -> 0 | M11: =IF(A11="","",BASE_CAIXA!AM8) -> TOPOGRAFO | TOPOGRAFO | Saída | GESTÃO LOCAL | N11: =IF(A11="","",IF(R11<>"",IF(AND(ABS(S11)<=0.01,ABS(T11)<=3),"Conciliado","Divergente"),IF(TODAY()>C11,"Pendente vencido","Previsto"))) -> Previsto | O11: =IFERROR(INDEX(EXTRATO_IMPORTADO!$A$5:$A$404,MATCH(B11,EXTRATO_IMPORTADO!$I$5:$I$404,0)),"") | P11: =IFERROR(INDEX(EXTRATO_IMPORTADO!$F$5:$F$404,MATCH(B11,EXTRATO_IMPORTADO!$I$5:$I$404,0)),"") | Q11: =IFERROR(INDEX(EXTRATO_IMPORTADO!$B$5:$B$404,MATCH(B11,EXTRATO_IMPORTADO!$I$5:$I$404,0)),"") | R11: =IFERROR(MATCH(B11,EXTRATO_IMPORTADO!$I$5:$I$404,0),"") | S11: =IF(OR(A11="",P11=""),"",P11-E11) | T11: =IF(OR(A11="",O11=""),"",O11-C11)
A12: =IF(BASE_CAIXA!A9="","",BASE_CAIXA!A9) -> 8 | B12: =IF(A12="","",BASE_CAIXA!AL9) -> 000008-DB | C12: =IF(A12="","",BASE_CAIXA!AJ9) -> 46101 | D12: =IF(A12="","",IF(BASE_CAIXA!C9="Entrada","Crédito","Débito")) -> Débito | E12: =IF(A12="","",BASE_CAIXA!AA9) -> 6100 | F12: =IF(A12="","",BASE_CAIXA!N9) -> 0 | G12: =IF(A12="","",BASE_CAIXA!O9) -> 0 | H12: =IF(A12="","",BASE_CAIXA!P9) -> 0 | I12: =IF(A12="","",IF(BASE_CAIXA!H9<>"",BASE_CAIXA!H9,BASE_CAIXA!G9)) -> mobilização / desmobilzaçao containers | J12: =IF(A12="","",BASE_CAIXA!G9) -> mobilização / desmobilzaçao containers | K12: =IF(A12="","",BASE_CAIXA!I9) -> 0 | L12: =IF(A12="","",BASE_CAIXA!J9) -> 0 | M12: =IF(A12="","",BASE_CAIXA!AM9) -> mobilização / desmobilzaçao containers | mobilização / desmo | N12: =IF(A12="","",IF(R12<>"",IF(AND(ABS(S12)<=0.01,ABS(T12)<=3),"Conciliado","Divergente"),IF(TODAY()>C12,"Pendente vencido","Previsto"))) -> Previsto | O12: =IFERROR(INDEX(EXTRATO_IMPORTADO!$A$5:$A$404,MATCH(B12,EXTRATO_IMPORTADO!$I$5:$I$404,0)),"") | P12: =IFERROR(INDEX(EXTRATO_IMPORTADO!$F$5:$F$404,MATCH(B12,EXTRATO_IMPORTADO!$I$5:$I$404,0)),"") | Q12: =IFERROR(INDEX(EXTRATO_IMPORTADO!$B$5:$B$404,MATCH(B12,EXTRATO_IMPORTADO!$I$5:$I$404,0)),"") | R12: =IFERROR(MATCH(B12,EXTRATO_IMPORTADO!$I$5:$I$404,0),"") | S12: =IF(OR(A12="",P12=""),"",P12-E12) | T12: =IF(OR(A12="",O12=""),"",O12-C12)
A13: =IF(BASE_CAIXA!A10="","",BASE_CAIXA!A10) -> 9 | B13: =IF(A13="","",BASE_CAIXA!AL10) -> 000009-DB | C13: =IF(A13="","",BASE_CAIXA!AJ10) -> 46101 | D13: =IF(A13="","",IF(BASE_CAIXA!C10="Entrada","Crédito","Débito")) -> Débito | E13: =IF(A13="","",BASE_CAIXA!AA10) -> 96000 | F13: =IF(A13="","",BASE_CAIXA!N10) -> 0 | G13: =IF(A13="","",BASE_CAIXA!O10) -> 0 | H13: =IF(A13="","",BASE_CAIXA!P10) -> 0 | I13: =IF(A13="","",IF(BASE_CAIXA!H10<>"",BASE_CAIXA!H10,BASE_CAIXA!G10)) -> contrato industrializaçao paredes | J13: =IF(A13="","",BASE_CAIXA!G10) -> contrato industrializaçao paredes | K13: =IF(A13="","",BASE_CAIXA!I10) -> 0 | L13: =IF(A13="","",BASE_CAIXA!J10) -> 0 | M13: =IF(A13="","",BASE_CAIXA!AM10) -> contrato industrializaçao paredes | contrato industrializaça | N13: =IF(A13="","",IF(R13<>"",IF(AND(ABS(S13)<=0.01,ABS(T13)<=3),"Conciliado","Divergente"),IF(TODAY()>C13,"Pendente vencido","Previsto"))) -> Previsto | O13: =IFERROR(INDEX(EXTRATO_IMPORTADO!$A$5:$A$404,MATCH(B13,EXTRATO_IMPORTADO!$I$5:$I$404,0)),"") | P13: =IFERROR(INDEX(EXTRATO_IMPORTADO!$F$5:$F$404,MATCH(B13,EXTRATO_IMPORTADO!$I$5:$I$404,0)),"") | Q13: =IFERROR(INDEX(EXTRATO_IMPORTADO!$B$5:$B$404,MATCH(B13,EXTRATO_IMPORTADO!$I$5:$I$404,0)),"") | R13: =IFERROR(MATCH(B13,EXTRATO_IMPORTADO!$I$5:$I$404,0),"") | S13: =IF(OR(A13="",P13=""),"",P13-E13) | T13: =IF(OR(A13="",O13=""),"",O13-C13)
A14: =IF(BASE_CAIXA!A11="","",BASE_CAIXA!A11) -> 10 | B14: =IF(A14="","",BASE_CAIXA!AL11) -> 000010-DB | C14: =IF(A14="","",BASE_CAIXA!AJ11) -> 46101 | D14: =IF(A14="","",IF(BASE_CAIXA!C11="Entrada","Crédito","Débito")) -> Débito | E14: =IF(A14="","",BASE_CAIXA!AA11) -> 96000 | F14: =IF(A14="","",BASE_CAIXA!N11) -> 0 | G14: =IF(A14="","",BASE_CAIXA!O11) -> 0 | H14: =IF(A14="","",BASE_CAIXA!P11) -> 0 | I14: =IF(A14="","",IF(BASE_CAIXA!H11<>"",BASE_CAIXA!H11,BASE_CAIXA!G11)) -> contrato industrializaçao paredes | J14: =IF(A14="","",BASE_CAIXA!G11) -> contrato industrializaçao paredes | K14: =IF(A14="","",BASE_CAIXA!I11) -> 0 | L14: =IF(A14="","",BASE_CAIXA!J11) -> 0 | M14: =IF(A14="","",BASE_CAIXA!AM11) -> contrato industrializaçao paredes | contrato industrializaça | N14: =IF(A14="","",IF(R14<>"",IF(AND(ABS(S14)<=0.01,ABS(T14)<=3),"Conciliado","Divergente"),IF(TODAY()>C14,"Pendente vencido","Previsto"))) -> Previsto | O14: =IFERROR(INDEX(EXTRATO_IMPORTADO!$A$5:$A$404,MATCH(B14,EXTRATO_IMPORTADO!$I$5:$I$404,0)),"") | P14: =IFERROR(INDEX(EXTRATO_IMPORTADO!$F$5:$F$404,MATCH(B14,EXTRATO_IMPORTADO!$I$5:$I$404,0)),"") | Q14: =IFERROR(INDEX(EXTRATO_IMPORTADO!$B$5:$B$404,MATCH(B14,EXTRATO_IMPORTADO!$I$5:$I$404,0)),"") | R14: =IFERROR(MATCH(B14,EXTRATO_IMPORTADO!$I$5:$I$404,0),"") | S14: =IF(OR(A14="",P14=""),"",P14-E14) | T14: =IF(OR(A14="",O14=""),"",O14-C14)
A15: =IF(BASE_CAIXA!A12="","",BASE_CAIXA!A12) -> 11 | B15: =IF(A15="","",BASE_CAIXA!AL12) -> 000011-DB | C15: =IF(A15="","",BASE_CAIXA!AJ12) -> 46101 | D15: =IF(A15="","",IF(BASE_CAIXA!C12="Entrada","Crédito","Débito")) -> Débito | E15: =IF(A15="","",BASE_CAIXA!AA12) -> 115200 | F15: =IF(A15="","",BASE_CAIXA!N12) -> 0 | G15: =IF(A15="","",BASE_CAIXA!O12) -> 0 | H15: =IF(A15="","",BASE_CAIXA!P12) -> 0 | I15: =IF(A15="","",IF(BASE_CAIXA!H12<>"",BASE_CAIXA!H12,BASE_CAIXA!G12)) -> contrato industrializaçao paredes | J15: =IF(A15="","",BASE_CAIXA!G12) -> contrato industrializaçao paredes | K15: =IF(A15="","",BASE_CAIXA!I12) -> 0 | L15: =IF(A15="","",BASE_CAIXA!J12) -> 0 | M15: =IF(A15="","",BASE_CAIXA!AM12) -> contrato industrializaçao paredes | contrato industrializaça | N15: =IF(A15="","",IF(R15<>"",IF(AND(ABS(S15)<=0.01,ABS(T15)<=3),"Conciliado","Divergente"),IF(TODAY()>C15,"Pendente vencido","Previsto"))) -> Previsto | O15: =IFERROR(INDEX(EXTRATO_IMPORTADO!$A$5:$A$404,MATCH(B15,EXTRATO_IMPORTADO!$I$5:$I$404,0)),"") | P15: =IFERROR(INDEX(EXTRATO_IMPORTADO!$F$5:$F$404,MATCH(B15,EXTRATO_IMPORTADO!$I$5:$I$404,0)),"") | Q15: =IFERROR(INDEX(EXTRATO_IMPORTADO!$B$5:$B$404,MATCH(B15,EXTRATO_IMPORTADO!$I$5:$I$404,0)),"") | R15: =IFERROR(MATCH(B15,EXTRATO_IMPORTADO!$I$5:$I$404,0),"") | S15: =IF(OR(A15="",P15=""),"",P15-E15) | T15: =IF(OR(A15="",O15=""),"",O15-C15)
A16: =IF(BASE_CAIXA!A13="","",BASE_CAIXA!A13) -> 12 | B16: =IF(A16="","",BASE_CAIXA!AL13) -> 000012-DB | C16: =IF(A16="","",BASE_CAIXA!AJ13) -> 46101 | D16: =IF(A16="","",IF(BASE_CAIXA!C13="Entrada","Crédito","Débito")) -> Débito | E16: =IF(A16="","",BASE_CAIXA!AA13) -> 24750 | F16: =IF(A16="","",BASE_CAIXA!N13) -> 0 | G16: =IF(A16="","",BASE_CAIXA!O13) -> 0 | H16: =IF(A16="","",BASE_CAIXA!P13) -> 0 | I16: =IF(A16="","",IF(BASE_CAIXA!H13<>"",BASE_CAIXA!H13,BASE_CAIXA!G13)) -> Mao de obra Terceirizada Radier | J16: =IF(A16="","",BASE_CAIXA!G13) -> Mao de obra Terceirizada Radier | K16: =IF(A16="","",BASE_CAIXA!I13) -> 0 | L16: =IF(A16="","",BASE_CAIXA!J13) -> 0 | M16: =IF(A16="","",BASE_CAIXA!AM13) -> Mao de obra Terceirizada Radier | Mao de obra Terceirizada R | N16: =IF(A16="","",IF(R16<>"",IF(AND(ABS(S16)<=0.01,ABS(T16)<=3),"Conciliado","Divergente"),IF(TODAY()>C16,"Pendente vencido","Previsto"))) -> Previsto | O16: =IFERROR(INDEX(EXTRATO_IMPORTADO!$A$5:$A$404,MATCH(B16,EXTRATO_IMPORTADO!$I$5:$I$404,0)),"") | P16: =IFERROR(INDEX(EXTRATO_IMPORTADO!$F$5:$F$404,MATCH(B16,EXTRATO_IMPORTADO!$I$5:$I$404,0)),"") | Q16: =IFERROR(INDEX(EXTRATO_IMPORTADO!$B$5:$B$404,MATCH(B16,EXTRATO_IMPORTADO!$I$5:$I$404,0)),"") | R16: =IFERROR(MATCH(B16,EXTRATO_IMPORTADO!$I$5:$I$404,0),"") | S16: =IF(OR(A16="",P16=""),"",P16-E16) | T16: =IF(OR(A16="",O16=""),"",O16-C16)
... A2003: =IF(BASE_CAIXA!A2000="","",BASE_CAIXA!A2000) | B2003: =IF(A2003="","",BASE_CAIXA!AL2000) | C2003: =IF(A2003="","",BASE_CAIXA!AJ2000) | D2003: =IF(A2003="","",IF(BASE_CAIXA!C2000="Entrada","Crédito","Débito")) | E2003: =IF(A2003="","",BASE_CAIXA!AA2000) | F2003: =IF(A2003="","",BASE_CAIXA!N2000) | G2003: =IF(A2003="","",BASE_CAIXA!O2000) | H2003: =IF(A2003="","",BASE_CAIXA!P2000) | I2003: =IF(A2003="","",IF(BASE_CAIXA!H2000<>"",BASE_CAIXA!H2000,BASE_CAIXA!G2000)) | J2003: =IF(A2003="","",BASE_CAIXA!G2000) | K2003: =IF(A2003="","",BASE_CAIXA!I2000) | L2003: =IF(A2003="","",BASE_CAIXA!J2000) | M2003: =IF(A2003="","",BASE_CAIXA!AM2000) | N2003: =IF(A2003="","",IF(R2003<>"",IF(AND(ABS(S2003)<=0.01,ABS(T2003)<=3),"Conciliado","Divergente"),IF(TODAY()>C2003,"Pendente vencido","Previsto"))) | O2003: =IFERROR(INDEX(EXTRATO_IMPORTADO!$A$5:$A$404,MATCH(B2003,EXTRATO_IMPORTADO!$I$5:$I$404,0)),"") | P2003: =IFERROR(INDEX(EXTRATO_IMPORTADO!$F$5:$F$404,MATCH(B2003,EXTRATO_IMPORTADO!$I$5:$I$404,0)),"") | Q2003: =IFERROR(INDEX(EXTRATO_IMPORTADO!$B$5:$B$404,MATCH(B2003,EXTRATO_IMPORTADO!$I$5:$I$404,0)),"") | R2003: =IFERROR(MATCH(B2003,EXTRATO_IMPORTADO!$I$5:$I$404,0),"") | S2003: =IF(OR(A2003="",P2003=""),"",P2003-E2003) | T2003: =IF(OR(A2003="",O2003=""),"",O2003-C2003)

Sheet EXTRATO_IMPORTADO
A1: Extrato Importado — cole aqui o extrato bruto do banco/fatura
A2: Cole o extrato a partir da linha 2 ou da linha 4, preservando os cabeçalhos. Depois preencha o ID_Concil_Manual quando identificar qual item da agenda aquele movimento representa.
A4: Data_Mov | B4: Historico_Banco | C4: Documento_Banco | D4: Valor_Debito | E4: Valor_Credito | F4: Valor_Liquido | G4: Conta_Bancaria | H4: Forma_Extrato | I4: ID_Concil_Manual | J4: ID_Concil_Sugerido | K4: Status_Concil | L4: Observacao
F5: =IF(OR(D5<>"",E5<>""),IF(E5<>"",E5,-D5),"") | K5: =IF(A5="","",IF(I5<>"",IF(COUNTIF(AGENDA_BANCARIA!$B$5:$B$2000,I5)>0,"Vinculado","ID não encontrado"),"Sem vínculo"))
F6: =IF(OR(D6<>"",E6<>""),IF(E6<>"",E6,-D6),"") | K6: =IF(A6="","",IF(I6<>"",IF(COUNTIF(AGENDA_BANCARIA!$B$5:$B$2000,I6)>0,"Vinculado","ID não encontrado"),"Sem vínculo"))
F7: =IF(OR(D7<>"",E7<>""),IF(E7<>"",E7,-D7),"") | K7: =IF(A7="","",IF(I7<>"",IF(COUNTIF(AGENDA_BANCARIA!$B$5:$B$2000,I7)>0,"Vinculado","ID não encontrado"),"Sem vínculo"))
F8: =IF(OR(D8<>"",E8<>""),IF(E8<>"",E8,-D8),"") | K8: =IF(A8="","",IF(I8<>"",IF(COUNTIF(AGENDA_BANCARIA!$B$5:$B$2000,I8)>0,"Vinculado","ID não encontrado"),"Sem vínculo"))
F9: =IF(OR(D9<>"",E9<>""),IF(E9<>"",E9,-D9),"") | K9: =IF(A9="","",IF(I9<>"",IF(COUNTIF(AGENDA_BANCARIA!$B$5:$B$2000,I9)>0,"Vinculado","ID não encontrado"),"Sem vínculo"))
F10: =IF(OR(D10<>"",E10<>""),IF(E10<>"",E10,-D10),"") | K10: =IF(A10="","",IF(I10<>"",IF(COUNTIF(AGENDA_BANCARIA!$B$5:$B$2000,I10)>0,"Vinculado","ID não encontrado"),"Sem vínculo"))
F11: =IF(OR(D11<>"",E11<>""),IF(E11<>"",E11,-D11),"") | K11: =IF(A11="","",IF(I11<>"",IF(COUNTIF(AGENDA_BANCARIA!$B$5:$B$2000,I11)>0,"Vinculado","ID não encontrado"),"Sem vínculo"))
F12: =IF(OR(D12<>"",E12<>""),IF(E12<>"",E12,-D12),"") | K12: =IF(A12="","",IF(I12<>"",IF(COUNTIF(AGENDA_BANCARIA!$B$5:$B$2000,I12)>0,"Vinculado","ID não encontrado"),"Sem vínculo"))
F13: =IF(OR(D13<>"",E13<>""),IF(E13<>"",E13,-D13),"") | K13: =IF(A13="","",IF(I13<>"",IF(COUNTIF(AGENDA_BANCARIA!$B$5:$B$2000,I13)>0,"Vinculado","ID não encontrado"),"Sem vínculo"))
F14: =IF(OR(D14<>"",E14<>""),IF(E14<>"",E14,-D14),"") | K14: =IF(A14="","",IF(I14<>"",IF(COUNTIF(AGENDA_BANCARIA!$B$5:$B$2000,I14)>0,"Vinculado","ID não encontrado"),"Sem vínculo"))
F15: =IF(OR(D15<>"",E15<>""),IF(E15<>"",E15,-D15),"") | K15: =IF(A15="","",IF(I15<>"",IF(COUNTIF(AGENDA_BANCARIA!$B$5:$B$2000,I15)>0,"Vinculado","ID não encontrado"),"Sem vínculo"))
F16: =IF(OR(D16<>"",E16<>""),IF(E16<>"",E16,-D16),"") | K16: =IF(A16="","",IF(I16<>"",IF(COUNTIF(AGENDA_BANCARIA!$B$5:$B$2000,I16)>0,"Vinculado","ID não encontrado"),"Sem vínculo"))
... F404: =IF(OR(D404<>"",E404<>""),IF(E404<>"",E404,-D404),"") | K404: =IF(A404="","",IF(I404<>"",IF(COUNTIF(AGENDA_BANCARIA!$B$5:$B$2000,I404)>0,"Vinculado","ID não encontrado"),"Sem vínculo"))

Sheet CONCILIACAO
A1: Conciliação Bancária — resumo operacional
A2: Use esta aba para enxergar rapidamente se o banco/fatura está batendo com a agenda financeira do projeto.
B4: Eventos na agenda | C4: =COUNTIF(AGENDA_BANCARIA!A5:A2003,"<>") -> 1999 | E4: Valor esperado na agenda | F4: =SUM(AGENDA_BANCARIA!E5:E2003) -> 20673335
B5: Conciliados | C5: =COUNTIF(AGENDA_BANCARIA!N5:N2003,"Conciliado") -> 0 | E5: Valor conciliado | F5: =SUMIF(AGENDA_BANCARIA!N5:N2003,"Conciliado",AGENDA_BANCARIA!E5:E2003) -> 0
B6: Previstos ainda não vencidos | C6: =COUNTIF(AGENDA_BANCARIA!N5:N2003,"Previsto") -> 643 | E6: Valor pendente | F6: =SUMIFS(AGENDA_BANCARIA!E5:E2003,AGENDA_BANCARIA!N5:N2003,"<>Conciliado",AGENDA_BANCARIA!N5:N2003,"<>Divergente") -> 20673335
B7: Pendentes vencidos | C7: =COUNTIF(AGENDA_BANCARIA!N5:N2003,"Pendente vencido") -> 1 | E7: Valor divergente | F7: =SUMIF(AGENDA_BANCARIA!N5:N2003,"Divergente",AGENDA_BANCARIA!S5:S2003) -> 0
B8: Divergentes | C8: =COUNTIF(AGENDA_BANCARIA!N5:N2003,"Divergente") -> 0
B9: Movimentos no extrato sem vínculo | C9: =COUNTIF(EXTRATO_IMPORTADO!K5:K404,"Sem vínculo") -> 0
A12: Como usar
A13: 1) Preencha os novos campos financeiros na BASE_CAIXA.
A14: 2) Confira a AGENDA_BANCARIA e veja o que deveria aparecer no banco/fatura.
A15: 3) Cole o extrato em EXTRATO_IMPORTADO.
A16: 4) Preencha o ID_Concil_Manual do extrato com o código da agenda.
A17: 5) Volte aqui para enxergar pendências, divergências e itens sem previsão.
A20: Eventos divergentes / pendentes
A21: ID_Concil | B21: Data Prevista | C21: Valor Esperado | D21: Status | E21: Conta/Meio | F21: Histórico
A22: =IF(OR(AGENDA_BANCARIA!N5="Divergente",AGENDA_BANCARIA!N5="Pendente vencido"),AGENDA_BANCARIA!B5,"") -> 000001-CR | B22: =IF(A22="","",AGENDA_BANCARIA!C5) -> 46080 | C22: =IF(A22="","",AGENDA_BANCARIA!E5) -> 720000 | D22: =IF(A22="","",AGENDA_BANCARIA!N5) -> Pendente vencido | E22: =IF(A22="","",AGENDA_BANCARIA!G5&" | "&AGENDA_BANCARIA!H5) -> 0 | 0 | F22: =IF(A22="","",AGENDA_BANCARIA!M5) -> FM SOLUÇÕES EM BEBIDAS | MEDIÇÃO CONTRATUAL | Entrada | MEDI
A23: =IF(OR(AGENDA_BANCARIA!N6="Divergente",AGENDA_BANCARIA!N6="Pendente vencido"),AGENDA_BANCARIA!B6,"") | B23: =IF(A23="","",AGENDA_BANCARIA!C6) | C23: =IF(A23="","",AGENDA_BANCARIA!E6) | D23: =IF(A23="","",AGENDA_BANCARIA!N6) | E23: =IF(A23="","",AGENDA_BANCARIA!G6&" | "&AGENDA_BANCARIA!H6) | F23: =IF(A23="","",AGENDA_BANCARIA!M6)
A24: =IF(OR(AGENDA_BANCARIA!N7="Divergente",AGENDA_BANCARIA!N7="Pendente vencido"),AGENDA_BANCARIA!B7,"") | B24: =IF(A24="","",AGENDA_BANCARIA!C7) | C24: =IF(A24="","",AGENDA_BANCARIA!E7) | D24: =IF(A24="","",AGENDA_BANCARIA!N7) | E24: =IF(A24="","",AGENDA_BANCARIA!G7&" | "&AGENDA_BANCARIA!H7) | F24: =IF(A24="","",AGENDA_BANCARIA!M7)
A25: =IF(OR(AGENDA_BANCARIA!N8="Divergente",AGENDA_BANCARIA!N8="Pendente vencido"),AGENDA_BANCARIA!B8,"") | B25: =IF(A25="","",AGENDA_BANCARIA!C8) | C25: =IF(A25="","",AGENDA_BANCARIA!E8) | D25: =IF(A25="","",AGENDA_BANCARIA!N8) | E25: =IF(A25="","",AGENDA_BANCARIA!G8&" | "&AGENDA_BANCARIA!H8) | F25: =IF(A25="","",AGENDA_BANCARIA!M8)
A26: =IF(OR(AGENDA_BANCARIA!N9="Divergente",AGENDA_BANCARIA!N9="Pendente vencido"),AGENDA_BANCARIA!B9,"") | B26: =IF(A26="","",AGENDA_BANCARIA!C9) | C26: =IF(A26="","",AGENDA_BANCARIA!E9) | D26: =IF(A26="","",AGENDA_BANCARIA!N9) | E26: =IF(A26="","",AGENDA_BANCARIA!G9&" | "&AGENDA_BANCARIA!H9) | F26: =IF(A26="","",AGENDA_BANCARIA!M9)
A27: =IF(OR(AGENDA_BANCARIA!N10="Divergente",AGENDA_BANCARIA!N10="Pendente vencido"),AGENDA_BANCARIA!B10,"") | B27: =IF(A27="","",AGENDA_BANCARIA!C10) | C27: =IF(A27="","",AGENDA_BANCARIA!E10) | D27: =IF(A27="","",AGENDA_BANCARIA!N10) | E27: =IF(A27="","",AGENDA_BANCARIA!G10&" | "&AGENDA_BANCARIA!H10) | F27: =IF(A27="","",AGENDA_BANCARIA!M10)
A28: =IF(OR(AGENDA_BANCARIA!N11="Divergente",AGENDA_BANCARIA!N11="Pendente vencido"),AGENDA_BANCARIA!B11,"") | B28: =IF(A28="","",AGENDA_BANCARIA!C11) | C28: =IF(A28="","",AGENDA_BANCARIA!E11) | D28: =IF(A28="","",AGENDA_BANCARIA!N11) | E28: =IF(A28="","",AGENDA_BANCARIA!G11&" | "&AGENDA_BANCARIA!H11) | F28: =IF(A28="","",AGENDA_BANCARIA!M11)
A29: =IF(OR(AGENDA_BANCARIA!N12="Divergente",AGENDA_BANCARIA!N12="Pendente vencido"),AGENDA_BANCARIA!B12,"") | B29: =IF(A29="","",AGENDA_BANCARIA!C12) | C29: =IF(A29="","",AGENDA_BANCARIA!E12) | D29: =IF(A29="","",AGENDA_BANCARIA!N12) | E29: =IF(A29="","",AGENDA_BANCARIA!G12&" | "&AGENDA_BANCARIA!H12) | F29: =IF(A29="","",AGENDA_BANCARIA!M12)
A30: =IF(OR(AGENDA_BANCARIA!N13="Divergente",AGENDA_BANCARIA!N13="Pendente vencido"),AGENDA_BANCARIA!B13,"") | B30: =IF(A30="","",AGENDA_BANCARIA!C13) | C30: =IF(A30="","",AGENDA_BANCARIA!E13) | D30: =IF(A30="","",AGENDA_BANCARIA!N13) | E30: =IF(A30="","",AGENDA_BANCARIA!G13&" | "&AGENDA_BANCARIA!H13) | F30: =IF(A30="","",AGENDA_BANCARIA!M13)
A31: =IF(OR(AGENDA_BANCARIA!N14="Divergente",AGENDA_BANCARIA!N14="Pendente vencido"),AGENDA_BANCARIA!B14,"") | B31: =IF(A31="","",AGENDA_BANCARIA!C14) | C31: =IF(A31="","",AGENDA_BANCARIA!E14) | D31: =IF(A31="","",AGENDA_BANCARIA!N14) | E31: =IF(A31="","",AGENDA_BANCARIA!G14&" | "&AGENDA_BANCARIA!H14) | F31: =IF(A31="","",AGENDA_BANCARIA!M14)
A32: =IF(OR(AGENDA_BANCARIA!N15="Divergente",AGENDA_BANCARIA!N15="Pendente vencido"),AGENDA_BANCARIA!B15,"") | B32: =IF(A32="","",AGENDA_BANCARIA!C15) | C32: =IF(A32="","",AGENDA_BANCARIA!E15) | D32: =IF(A32="","",AGENDA_BANCARIA!N15) | E32: =IF(A32="","",AGENDA_BANCARIA!G15&" | "&AGENDA_BANCARIA!H15) | F32: =IF(A32="","",AGENDA_BANCARIA!M15)
A33: =IF(OR(AGENDA_BANCARIA!N16="Divergente",AGENDA_BANCARIA!N16="Pendente vencido"),AGENDA_BANCARIA!B16,"") | B33: =IF(A33="","",AGENDA_BANCARIA!C16) | C33: =IF(A33="","",AGENDA_BANCARIA!E16) | D33: =IF(A33="","",AGENDA_BANCARIA!N16) | E33: =IF(A33="","",AGENDA_BANCARIA!G16&" | "&AGENDA_BANCARIA!H16) | F33: =IF(A33="","",AGENDA_BANCARIA!M16)
... A81: =IF(OR(AGENDA_BANCARIA!N64="Divergente",AGENDA_BANCARIA!N64="Pendente vencido"),AGENDA_BANCARIA!B64,"") | B81: =IF(A81="","",AGENDA_BANCARIA!C64) | C81: =IF(A81="","",AGENDA_BANCARIA!E64) | D81: =IF(A81="","",AGENDA_BANCARIA!N64) | E81: =IF(A81="","",AGENDA_BANCARIA!G64&" | "&AGENDA_BANCARIA!H64) | F81: =IF(A81="","",AGENDA_BANCARIA!M64)
